Workbook

Sheet Summary
A1: INVESTMENT SUMMARY
A2: =Inputs!C5&" | "&Inputs!C6&" | "&Inputs!C7&", "&Inputs!C8 -> | | ,
A4: DEAL OVERVIEW | E4: WATERFALL RETURN
B5: Purchase Price | C5: =Inputs!C10 | E5: LP (Capital Partner)
B6: Number of Units | C6: =Inputs!C9 | E6: IRR | F6: ='Equity Waterfall'!N62 -> -
B7: Total Equity Required | C7: =Inputs!C87 -> -345000 | E7: Equity Multiple | F7: ='Equity Waterfall'!N63 -> 0
B8: Total Debt (Acquisition) | C8: =Inputs!C43+Inputs!C52 -> 350000 | E8: Total Distributions | F8: ='Equity Waterfall'!N64 -> 0
B9: LTV | C9: =(Inputs!C43+Inputs!C52)/Inputs!C10 -> #DIV/0! | E9: Equity Invested | F9: =Inputs!C88 -> 85000
B10: Price Per Unit | C10: =Inputs!C10/Inputs!C9 -> #DIV/0! | E10: GP (Manager)
B11: Year 1 Cap Rate | C11: ='Annual CF'!C17/Inputs!C10 -> #DIV/0! | E11: IRR | F11: ='Equity Waterfall'!N67 -> -
B12: Hold Period | C12: =Inputs!C15 | E12: Equity Multiple | F12: ='Equity Waterfall'!N68 -> 0
B13: Refi Year | C13: =Inputs!C16 | E13: Total Distributions | F13: ='Equity Waterfall'!N69 -> 0
B14: Exit Cap Rate | C14: =Inputs!C96 -> 0.09 | E14: Equity Invested | F14: =Inputs!C89 -> -430000
A16: SOURCES & USES | E16: KEY PERFORMANCE METRICS
B17: Purchase Price | C17: =Inputs!C10 | E17: Year 1 NOI | F17: ='Annual CF'!C17 -> 0
B18: Closing Costs | C18: =Inputs!C85 -> 0 | E18: Year 1 DSCR | F18: ='Annual CF'!C72 -> -
B19: Due Diligence | C19: =Inputs!C10*Inputs!C12 -> 0 | E19: Year 1 Cash-on-Cash | F19: =IF(Inputs!C87=0,0,'Annual CF'!C62/Inputs!C87) -> 1.0144928
B20: Loan Origination | C20: =Inputs!C10*Inputs!C13 -> 0 | E20: Year 1 Cap Rate | F20: ='Annual CF'!C17/Inputs!C10 -> #DIV/0!
B21: Immediate Repairs | C21: =Inputs!C86 -> 5000 | E21: 10-Year Total NOI | F21: =SUM('Annual CF'!C17:L17) -> 0
B22: TOTAL USES | C22: =Inputs!C81 -> 5000 | E22: 10-Year Total CFAD | F22: =SUM('Annual CF'!C62:L62) -> -350000
B23: Funded By | E23: Exit Selling Price | F23: =Inputs!C101 -> 0
B24: Seller Finance | C24: =Inputs!C43 -> 0 | E24: Net Sale Proceeds | F24: =Inputs!C103 -> 0
B25: Bank Loan | C25: =Inputs!C52 -> 350000 | E25: Feasibility Checks
B26: Equity | C26: =Inputs!C87 -> -345000 | E26: Year 1 DSCR ≥ 1.25x? | F26: =IF('Annual CF'!C72>=1.25,"✓ PASS","✗ FAIL") -> ✓ PASS
E27: Year 1 CF > $0? | F27: =IF('Annual CF'!C62>0,"✓ PASS","✗ FAIL") -> ✗ FAIL
A29: 10-YEAR ANNUAL SNAPSHOT
B30: Metric | C30: Year 1 | D30: Year 2 | E30: Year 3 | F30: Year 4 | G30: Year 5 | H30: Year 6 | I30: Year 7 | J30: Year 8 | K30: Year 9 | L30: Year 10
B31: NOI | C31: ='Annual CF'!C17 -> 0 | D31: ='Annual CF'!D17 -> 0 | E31: ='Annual CF'!E17 -> 0 | F31: ='Annual CF'!F17 -> 0 | G31: ='Annual CF'!G17 -> 0 | H31: ='Annual CF'!H17 -> 0 | I31: ='Annual CF'!I17 -> 0 | J31: ='Annual CF'!J17 -> 0 | ... L31: ='Annual CF'!L17 -> 0
B32: CF Before Debt | C32: ='Annual CF'!C28 -> -5000 | D32: ='Annual CF'!D28 -> 0 | E32: ='Annual CF'!E28 -> 0 | F32: ='Annual CF'!F28 -> 0 | G32: ='Annual CF'!G28 -> 0 | H32: ='Annual CF'!H28 -> 0 | I32: ='Annual CF'!I28 -> 0 | J32: ='Annual CF'!J28 -> 0 | ... L32: ='Annual CF'!L28 -> 0
B33: CF After Debt | C33: ='Annual CF'!C62 -> -350000 | D33: ='Annual CF'!D62 -> 0 | E33: ='Annual CF'!E62 -> 0 | F33: ='Annual CF'!F62 -> 0 | G33: ='Annual CF'!G62 -> 0 | H33: ='Annual CF'!H62 -> 0 | I33: ='Annual CF'!I62 -> 0 | J33: ='Annual CF'!J62 -> 0 | ... L33: ='Annual CF'!L62 -> 0
B34: DSCR | C34: ='Annual CF'!C72 -> - | D34: ='Annual CF'!D72 -> - | E34: ='Annual CF'!E72 -> - | F34: ='Annual CF'!F72 -> - | G34: ='Annual CF'!G72 -> - | H34: ='Annual CF'!H72 -> - | I34: ='Annual CF'!I72 -> - | J34: ='Annual CF'!J72 -> - | ... L34: ='Annual CF'!L72 -> -
B35: LP Distributions | C35: ='Annual CF'!C67 -> 0 | D35: ='Annual CF'!D67 -> 0 | E35: ='Annual CF'!E67 -> 0 | F35: ='Annual CF'!F67 -> 0 | G35: ='Annual CF'!G67 -> 0 | H35: ='Annual CF'!H67 -> 0 | I35: ='Annual CF'!I67 -> 0 | J35: ='Annual CF'!J67 -> 0 | ... L35: ='Annual CF'!L67 -> 0
B36: GP Distributions | C36: ='Annual CF'!C69 -> 0 | D36: ='Annual CF'!D69 -> 0 | E36: ='Annual CF'!E69 -> 0 | F36: ='Annual CF'!F69 -> 0 | G36: ='Annual CF'!G69 -> 0 | H36: ='Annual CF'!H69 -> 0 | I36: ='Annual CF'!I69 -> 0 | J36: ='Annual CF'!J69 -> 0 | ... L36: ='Annual CF'!L69 -> 0
B37: Cumulative CF | C37: ='Annual CF'!C63 -> -350000 | D37: ='Annual CF'!D63 -> -350000 | E37: ='Annual CF'!E63 -> -350000 | F37: ='Annual CF'!F63 -> -350000 | G37: ='Annual CF'!G63 -> -350000 | H37: ='Annual CF'!H63 -> -350000 | I37: ='Annual CF'!I63 -> -350000 | J37: ='Annual CF'!J63 -> -350000 | ... L37: ='Annual CF'!L63 -> -350000
A39: PROJECT-LEVEL RETURNS | E39: FINANCING SUMMARY
B40: Project IRR | C40: ='Equity Waterfall'!N72 -> - | E40: Seller Finance | F40: =Inputs!C43 -> 0
B41: Project Equity Multiple | C41: ='Equity Waterfall'!N73 -> 0 | E41: Rate / Amort / Balloon | F41: =TEXT(Inputs!C44,"0.0%")&" / "&Inputs!C45&"yr / Yr "&Inputs!C46 -> 5.0% / 25yr / Yr 5
B42: Total Distributable Cash | C42: ='Equity Waterfall'!N53 -> 0 | E42: Bank Loan | F42: =Inputs!C52 -> 350000
B43: Total LP Distributions | C43: ='Equity Waterfall'!N51 -> 0 | E43: Rate / Amort / Balloon | F43: =TEXT(Inputs!C53,"0.0%")&" / "&Inputs!C54&"yr / Yr "&Inputs!C55 -> 5.0% / 25yr / Yr 5
B44: Total GP Distributions | C44: ='Equity Waterfall'!N52 -> 0 | E44: Refi Loan (Year 6) | F44: =Inputs!C67 -> 0
E45: Rate / Amort / Term | F45: =TEXT(Inputs!C68,"0.0%")&" / "&Inputs!C69&"yr / "&Inputs!C70&"yr" -> 7.0% / 25yr / 7yr
A47: MODEL NOTES & ASSUMPTIONS
A48: • Revenue and expenses grow annually at rates defined in the Inputs sheet; Year 1 figures are based on T-12 proforma
A49: • Seller Finance and Bank Loan fund at acquisition; Refinance replaces Bank Loan at the designated Refi Year
A50: • Capital expenditures: Year 1 uses dedicated CapEx input; Years 2-5 and 6-10 use separate annual assumptions
A51: ="• Equity waterfall: Preferred Return → GP Catch-Up → "&TEXT(Inputs!C115,"0%")&"/"&TEXT(Inputs!D115,"0%")&" Residual → "&TEXT(Inputs!C116,"0%")&"/"&TEXT(Inputs!D116,"0%")&" above "&TEXT(Inputs!C109,"0%")&" IRR hurdle" -> • Equity waterfall: Preferred Return → GP Catch-Up → 70%/30% Residual → 50%/50% above 15% IRR hurdle
A52: • DSCR = NOI ÷ Total Debt Service (absolute value); target ≥ 1.25x for bankability
A53: • Net Sale Proceeds = Selling Price − Selling Costs at exit; Sale Year NOI capitalized at Exit Cap Rate
A54: • All green values are formula-linked to Inputs, Monthly CF, Annual CF, or Equity Waterfall — change inputs to rerun

Sheet Inputs
A1: COMMERCIAL REAL ESTATE UNDERWRITING MODEL
A2: INPUT ASSUMPTIONS | All blue cells are inputs
A4: SECTION 1 · PROPERTY INFORMATION
B5: Property Name
B6: Property Type
B7: Address
B8: City / State
B9: Number of Units
B10: Purchase Price | D10: Amount ($)
B11: Down Payment (%) | D11: =C10*C11 -> 0
B12: Due Diligence Costs (%) | C12: =IF(C10=0,0,D12/C10) -> 0
B13: Loan Origination Costs (%) | D13: =C10*C13 -> 0
B14: Purchase Date
B15: End Year
B16: Refi Year
A18: SECTION 2 · REVENUE ASSUMPTIONS | C18: T12 | D18: % Change | E18: Proforma Y-1
B19: Enter monthly T12 averages; model annualizes and projects forward
B20: Gross Potential Rent | D20: 0.1 | E20: =C20*(1+D20) -> 0
B21: Vacancy (%) | E21: =C21
B22: Credit Loss (%) | E22: =C22
B23: SUM Income | C23: =IncomeExpenses!C47 -> 0 | D23: 0.05 | E23: =C23*(1+D23) -> 0
B24: Annual Revenue Growth Rate | C24: 0.05
B25: Revenue Start Month | C25: 1
A27: SECTION 3 · EXPENSE ASSUMPTIONS | C27: T12 | D27: % Change | E27: Proforma Y-1
B28: Property Management Fee (%EGI) | E28: =C28
B29: SUM Expenses | C29: =IncomeExpenses!C90 -> 0
B30: Annual Expense Growth Rate | C30: 0.03
B31: Expense Start Month | C31: 1
A33: SECTION 4 · CAPITAL EXPENDITURES | C33: Amount | D33: Month
B34: CapEx Item 1 | D34: 1
B35: CapEx Item 2 | D35: 4
B36: CapEx Item 3 | D36: 7
B37: CapEx Item 4 | D37: 9
B38: CapEx Item 5 | D38: 11
B39: CapEx Item 6 | D39: 13
A41: SECTION 5 · FUNDING & DEBT ASSUMPTIONS
B42: Acquisition - Seller Finance
B43: Seller Finance Amount | C43: =D81 -> 0
B44: Seller Finance Interest Rate | C44: 0.05
B45: Seller Finance Amortization (Yrs) | C45: 25
B46: Seller Finance Balloon at EOY | C46: 5
B47: Seller Finance IO Period (Mos) | C47: 0
B48: Seller Finance Origination Month | C48: 1
B49: Seller Finance PMT Start Month | C49: 9
B51: 0
B52: Bank Loan Amount | C52: =E81 -> 350000
B53: Bank Loan Interest Rate | C53: 0.05
B54: Bank Loan Amortization (Yrs) | C54: 25
B55: Bank Loan Balloon at EOY | C55: 5
B56: Bank Loan IO Period (Mos)
B57: Bank Loan Origination Month | C57: 1
B58: Bank Loan PMT Start Month | C58: 1
B60: Refinance Loan (Replaces Bank Loan)
B61: Refi Cap Rate (%) | C61: 0.09
B62: Refi LTV (%) | C62: 0.75
B63: Refi Closing Cost (%) | C63: 0.02
B64: =" Refi Year NOI (Year "&C16&")" -> Refi Year NOI (Year ) | C64: {=SUMPRODUCT(('Monthly CF'!$C$5:$DR$5=C16)*'Monthly CF'!$C$20:$DR$20)} -> 0
B65: Refi Property Value | C65: =C64/C61 -> 0
B66: Refi Closing Costs ($) | C66: =C65*C63 -> 0
B67: Refi Loan Amount | C67: =C65*C62 -> 0
B68: Refi Interest Rate | C68: 0.07
B69: Refi Amortization (Yrs) | C69: 25
B70: Refi Term (Yrs) | C70: 7
B71: Refi IO Period (Mos) | C71: 0
B73: Sources & Uses
B74: Uses | C74: Total Cost | D74: Seller Finance | E74: Bank Loan | F74: Equity
B75: Purchase Price | C75: =C10 | D75: =$D$11 -> 0 | E75: 350000 | F75: =C75-D75-E75 -> -350000
B76: Closing Costs | C76: =C85 -> 0 | D76: 0 | E76: 0 | F76: =C76-D76-E76 -> 0
B77: Acquisition Fee | C77: =C10*C93 -> 0 | D77: 0 | E77: 0 | F77: =C77-D77-E77 -> 0
B78: Due Diligence Costs | C78: =D12 | D78: 0 | E78: 0 | F78: =C78-D78-E78 -> 0
B79: Loan Origination Costs | C79: =D13 -> 0 | D79: 0 | E79: 0 | F79: =C79-D79-E79 -> 0
B80: Immediate Repairs / Reserves | C80: =C86 -> 5000 | D80: 0 | E80: 0 | F80: =C80-D80-E80 -> 5000
B81: TOTAL | C81: =SUM(C75:C80) -> 5000 | D81: =SUM(D75:D80) -> 0 | E81: =SUM(E75:E80) -> 350000 | F81: =C81-D81-E81 -> -345000
A84: SECTION 6 · ACQUISITION & EQUITY
B85: Closing Costs | C85: =C10*D85 -> 0 | D85: 0.02
B86: Immediate Repairs / Reserves | C86: 5000
B87: Equity Contribution | C87: =F81 -> -345000
B88: Capital Partner Contribution ($) | C88: 85000
B89: Manager Contribution ($) | C89: =C87-C88 -> -430000
B90: Capital Partner Share (%) | C90: =IF(C87=0,0,C88/C87) -> -0.24637681
B91: Manager Share (%) | C91: =IF(C87=0,0,C89/C87) -> 1.2463768
B92: Asset Management Fee (% EGI) | C92: 0.02
B93: Acquisition Fee (% Purchase) | C93: 0.01
A95: SECTION 7 · DISPOSITION / EXIT
B96: Exit Cap Rate (%) | C96: 0.09
B97: Selling Cost (% of Sale Price) | C97: 0.03
B99: Calculated Exit Values
B100: =" Sale Year NOI (Year "&C15&")" -> Sale Year NOI (Year ) | C100: {=SUMPRODUCT(('Monthly CF'!$C$5:$DR$5=C15)*'Monthly CF'!$C$20:$DR$20)} -> 0
B101: Selling Price | C101: =C100/C96 -> 0
B102: Selling Costs ($) | C102: =C101*C97 -> 0
B103: Net Sale Proceeds | C103: =C101-C102 -> 0
A105: SECTION 8 · EQUITY WATERFALL | B105: SECTION 8 · EQUITY WATERFALL
B106: Preferred Return (Annual) | C106: 0.08
B107: GP Catch-Up Share (%) | C107: 0.5
B108: GP Catch-Up Target (%) | C108: 0.2
B109: IRR Hurdle | C109: 0.15
B111: Tier Distribution Splits | C111: LP % | D111: GP %
B112: 1. Return of Capital | C112: 1 | D112: =1-C112 -> 0
B113: 2. Preferred Return | C113: 1 | D113: =1-C113 -> 0
B114: 3. GP Catch-Up | C114: =1-C107 -> 0.5 | D114: =C107 -> 0.5
...

Sheet IncomeExpenses
A1: COMMERCIAL REAL ESTATE UNDERWRITING MODEL
A2: INPUT ASSUMPTIONS | All blue cells are inputs
A5: SECTION 1 · REVENUE ASSUMPTIONS | C5: T12 | D5: % Change | E5: Proforma Y-1
B6: Enter monthly T12 averages; model annualizes and projects forward
B7: Late Fees | D7: 0.05 | E7: =C7*(1+D7) -> 0
B8: Lot Rent | D8: 0.05 | E8: =C8*(1+D8) -> 0
B9: Down Payment Income | D9: 0.05 | E9: =C9*(1+D9) -> 0
B10: Waste Removal Utility Income | D10: 0.05 | E10: =C10*(1+D10) -> 0
B11: Home Sales | D11: 0.05 | E11: =C11*(1+D11) -> 0
B12: Eviction Fees Collected | D12: 0.05 | E12: =C12*(1+D12) -> 0
D13: 0.05 | E13: =C13*(1+D13) -> 0
D14: 0.05 | E14: =C14*(1+D14) -> 0
D15: 0.05 | E15: =C15*(1+D15) -> 0
D16: 0.05 | E16: =C16*(1+D16) -> 0
D17: 0.05 | E17: =C17*(1+D17) -> 0
D18: 0.05 | E18: =C18*(1+D18) -> 0
D19: 0.05 | E19: =C19*(1+D19) -> 0
D20: 0.05 | E20: =C20*(1+D20) -> 0
D21: 0.05 | E21: =C21*(1+D21) -> 0
D22: 0.05 | E22: =C22*(1+D22) -> 0
D23: 0.05 | E23: =C23*(1+D23) -> 0
D24: 0.05 | E24: =C24*(1+D24) -> 0
... D46: 0.05 | E46: =C46*(1+D46) -> 0
C47: =SUM(C7:C46) -> 0 | E47: =SUM(E7:E46) -> 0
A49: SECTION 2 · EXPENSE ASSUMPTIONS | C49: T12 | D49: % Change | E49: Proforma Y-1
B50: Property Tax | D50: 0.04 | E50: =C50*(1+D50) -> 0
B51: Insurance | D51: 0.04 | E51: =C51*(1+D51) -> 0
B52: Repairs | D52: 0.04 | E52: =C52*(1+D52) -> 0
B53: Utilities | D53: 0.04 | E53: =C53*(1+D53) -> 0
B54: Capital Expenditures | D54: 0.04 | E54: =C54*(1+D54) -> 0
B55: Landscape | D55: 0.04 | E55: =C55*(1+D55) -> 0
B56: Legal Fees | D56: 0.04 | E56: =C56*(1+D56) -> 0
B57: Sheriff Eviction Fee | D57: 0.04 | E57: =C57*(1+D57) -> 0
B58: CAM - Insurance | D58: 0.04 | E58: =C58*(1+D58) -> 0
B59: Other CAM Expenses | D59: 0.04 | E59: =C59*(1+D59) -> 0
B60: Software | D60: 0.04 | E60: =C60*(1+D60) -> 0
B61: Bad Debt | D61: 0.04 | E61: =C61*(1+D61) -> 0
... B69: Remove mobile home | D69: 0.02 | E69: =C69*(1+D69) -> 0
D70: 0.02 | E70: =C70*(1+D70) -> 0
D71: 0.02 | E71: =C71*(1+D71) -> 0
D72: 0.02 | E72: =C72*(1+D72) -> 0
D73: 0.02 | E73: =C73*(1+D73) -> 0
D74: 0.02 | E74: =C74*(1+D74) -> 0
D75: 0.02 | E75: =C75*(1+D75) -> 0
D76: 0.02 | E76: =C76*(1+D76) -> 0
D77: 0.02 | E77: =C77*(1+D77) -> 0
D78: 0.02 | E78: =C78*(1+D78) -> 0
D79: 0.02 | E79: =C79*(1+D79) -> 0
D80: 0.02 | E80: =C80*(1+D80) -> 0
D81: 0.02 | E81: =C81*(1+D81) -> 0
... D89: 0.02 | E89: =C89*(1+D89) -> 0
C90: =SUM(C50:C89) -> 0 | E90: =SUM(E50:E89) -> 0

Sheet Notes
A1: NOTES FOR PEDRO – What Data Does the Client Give Us?
A3: Hey Pedro! This document explains what information we need from the client so we can plug it into our model.
A4: The "Inputs" sheet is where ALL the client data goes. Think of it as the control panel — everything we type there drives the entire model.
A5: Blue cells = things we type in (client data or our assumptions). Black cells = the model calculates automatically. Green cells = pulled from other sheets.
A7: Below is a section-by-section breakdown of what the client provides and where it goes.
A9: ═══════════════════════════════════════════════════════════════════
A10: SECTION 1 · PROPERTY INFORMATION (Inputs sheet, rows 5–16)
A11: ═══════════════════════════════════════════════════════════════════
A13: This is basic info about the property the client wants to buy. Ask the client for:
A15: • Property Name (cell C5) — What is the property called? Example: "High Land Park"
A16: • Property Type (cell C6) — What kind of property? Example: "RV Park", "Apartment", "Retail"
A17: • Address (cell C7) — Street address of the property
... A148: 7. Waterfall terms — preferred return %, catch-up terms, profit split percentages for each tier

Sheet Monthly CF
A1: MONTHLY CASHFLOW MODEL
A2: All values driven by Inputs sheet | Blue = Input | Green = Linked | Black = Formula
B3: Month No. | C3: 1 | D3: 2 | E3: 3 | F3: 4 | G3: 5 | H3: 6 | I3: 7 | J3: 8 | K3: 9 | L3: 10 | M3: 11 | N3: 12 | O3: 13 | P3: 14 | Q3: 15 | R3: 16 | S3: 17 | T3: 18 | U3: 19 | V3: 20 | W3: 21 | X3: 22 | Y3: 23 | Z3: 24 | AA3: 25 | AB3: 26 | AC3: 27 | AD3: 28 | AE3: 29 | AF3: 30 | AG3: 31 | AH3: 32 | AI3: 33 | AJ3: 34 | AK3: 35 | AL3: 36 | AM3: 37 | AN3: 38 | AO3: 39 | AP3: 40 | AQ3: 41 | AR3: 42 | AS3: 43 | AT3: 44 | AU3: 45 | AV3: 46 | AW3: 47 | AX3: 48 | AY3: 49 | AZ3: 50 | BA3: 51 | BB3: 52 | BC3: 53 | BD3: 54 | BE3: 55 | BF3: 56 | BG3: 57 | BH3: 58 | BI3: 59 | BJ3: 60 | BK3: 61 | BL3: 62 | BM3: 63 | BN3: 64 | BO3: 65 | BP3: 66 | BQ3: 67 | BR3: 68 | BS3: 69 | BT3: 70 | BU3: 71 | BV3: 72 | BW3: 73 | BX3: 74 | BY3: 75 | BZ3: 76 | CA3: 77 | CB3: 78 | CC3: 79 | CD3: 80 | CE3: 81 | CF3: 82 | CG3: 83 | CH3: 84 | CI3: 85 | CJ3: 86 | CK3: 87 | CL3: 88 | CM3: 89 | CN3: 90 | CO3: 91 | CP3: 92 | CQ3: 93 | CR3: 94 | CS3: 95 | CT3: 96 | CU3: 97 | CV3: 98 | CW3: 99 | CX3: 100 | CY3: 101 | CZ3: 102 | DA3: 103 | DB3: 104 | DC3: 105 | DD3: 106 | DE3: 107 | DF3: 108 | DG3: 109 | DH3: 110 | DI3: 111 | DJ3: 112 | DK3: 113 | DL3: 114 | DM3: 115 | DN3: 116 | DO3: 117 | DP3: 118 | DQ3: 119 | DR3: 120
B4: Quarter No. | C4: 1 | D4: 1 | E4: 1 | F4: 2 | G4: 2 | H4: 2 | I4: 3 | J4: 3 | K4: 3 | L4: 4 | M4: 4 | N4: 4 | O4: 5 | P4: 5 | Q4: 5 | R4: 6 | S4: 6 | T4: 6 | U4: 7 | V4: 7 | W4: 7 | X4: 8 | Y4: 8 | Z4: 8 | AA4: 9 | AB4: 9 | AC4: 9 | AD4: 10 | AE4: 10 | AF4: 10 | AG4: 11 | AH4: 11 | AI4: 11 | AJ4: 12 | AK4: 12 | AL4: 12 | AM4: 13 | AN4: 13 | AO4: 13 | AP4: 14 | AQ4: 14 | AR4: 14 | AS4: 15 | AT4: 15 | AU4: 15 | AV4: 16 | AW4: 16 | AX4: 16 | AY4: 17 | AZ4: 17 | BA4: 17 | BB4: 18 | BC4: 18 | BD4: 18 | BE4: 19 | BF4: 19 | BG4: 19 | BH4: 20 | BI4: 20 | BJ4: 20 | BK4: 21 | BL4: 21 | BM4: 21 | BN4: 22 | BO4: 22 | BP4: 22 | BQ4: 23 | BR4: 23 | BS4: 23 | BT4: 24 | BU4: 24 | BV4: 24 | BW4: 25 | BX4: 25 | BY4: 25 | BZ4: 26 | CA4: 26 | CB4: 26 | CC4: 27 | CD4: 27 | CE4: 27 | CF4: 28 | CG4: 28 | CH4: 28 | CI4: 29 | CJ4: 29 | CK4: 29 | CL4: 30 | CM4: 30 | CN4: 30 | CO4: 31 | CP4: 31 | CQ4: 31 | CR4: 32 | CS4: 32 | CT4: 32 | CU4: 33 | CV4: 33 | CW4: 33 | CX4: 34 | CY4: 34 | CZ4: 34 | DA4: 35 | DB4: 35 | DC4: 35 | DD4: 36 | DE4: 36 | DF4: 36 | DG4: 37 | DH4: 37 | DI4: 37 | DJ4: 38 | DK4: 38 | DL4: 38 | DM4: 39 | DN4: 39 | DO4: 39 | DP4: 40 | DQ4: 40 | DR4: 40
B5: Year No. | C5: 1 | D5: 1 | E5: 1 | F5: 1 | G5: 1 | H5: 1 | I5: 1 | J5: 1 | K5: 1 | L5: 1 | M5: 1 | N5: 1 | O5: 2 | P5: 2 | Q5: 2 | R5: 2 | S5: 2 | T5: 2 | U5: 2 | V5: 2 | W5: 2 | X5: 2 | Y5: 2 | Z5: 2 | AA5: 3 | AB5: 3 | AC5: 3 | AD5: 3 | AE5: 3 | AF5: 3 | AG5: 3 | AH5: 3 | AI5: 3 | AJ5: 3 | AK5: 3 | AL5: 3 | AM5: 4 | AN5: 4 | AO5: 4 | AP5: 4 | AQ5: 4 | AR5: 4 | AS5: 4 | AT5: 4 | AU5: 4 | AV5: 4 | AW5: 4 | AX5: 4 | AY5: 5 | AZ5: 5 | BA5: 5 | BB5: 5 | BC5: 5 | BD5: 5 | BE5: 5 | BF5: 5 | BG5: 5 | BH5: 5 | BI5: 5 | BJ5: 5 | BK5: 6 | BL5: 6 | BM5: 6 | BN5: 6 | BO5: 6 | BP5: 6 | BQ5: 6 | BR5: 6 | BS5: 6 | BT5: 6 | BU5: 6 | BV5: 6 | BW5: 7 | BX5: 7 | BY5: 7 | BZ5: 7 | CA5: 7 | CB5: 7 | CC5: 7 | CD5: 7 | CE5: 7 | CF5: 7 | CG5: 7 | CH5: 7 | CI5: 8 | CJ5: 8 | CK5: 8 | CL5: 8 | CM5: 8 | CN5: 8 | CO5: 8 | CP5: 8 | CQ5: 8 | CR5: 8 | CS5: 8 | CT5: 8 | CU5: 9 | CV5: 9 | CW5: 9 | CX5: 9 | CY5: 9 | CZ5: 9 | DA5: 9 | DB5: 9 | DC5: 9 | DD5: 9 | DE5: 9 | DF5: 9 | DG5: 10 | DH5: 10 | DI5: 10 | DJ5: 10 | DK5: 10 | DL5: 10 | DM5: 10 | DN5: 10 | DO5: 10 | DP5: 10 | DQ5: 10 | DR5: 10
C6: 45658 | D6: 45689 | E6: 45717 | F6: 45748 | G6: 45778 | H6: 45809 | I6: 45839 | J6: 45870 | K6: 45901 | L6: 45931 | M6: 45962 | N6: 45992 | O6: 46023 | P6: 46054 | Q6: 46082 | R6: 46113 | S6: 46143 | T6: 46174 | U6: 46204 | V6: 46235 | W6: 46266 | X6: 46296 | Y6: 46327 | Z6: 46357 | AA6: 46388 | AB6: 46419 | AC6: 46447 | AD6: 46478 | AE6: 46508 | AF6: 46539 | AG6: 46569 | AH6: 46600 | AI6: 46631 | AJ6: 46661 | AK6: 46692 | AL6: 46722 | AM6: 46753 | AN6: 46784 | AO6: 46813 | AP6: 46844 | AQ6: 46874 | AR6: 46905 | AS6: 46935 | AT6: 46966 | AU6: 46997 | AV6: 47027 | AW6: 47058 | AX6: 47088 | AY6: 47119 | AZ6: 47150 | BA6: 47178 | BB6: 47209 | BC6: 47239 | BD6: 47270 | BE6: 47300 | BF6: 47331 | BG6: 47362 | BH6: 47392 | BI6: 47423 | BJ6: 47453 | BK6: 47484 | BL6: 47515 | BM6: 47543 | BN6: 47574 | BO6: 47604 | BP6: 47635 | BQ6: 47665 | BR6: 47696 | BS6: 47727 | BT6: 47757 | BU6: 47788 | BV6: 47818 | BW6: 47849 | BX6: 47880 | BY6: 47908 | BZ6: 47939 | CA6: 47969 | CB6: 48000 | CC6: 48030 | CD6: 48061 | CE6: 48092 | CF6: 48122 | CG6: 48153 | CH6: 48183 | CI6: 48214 | CJ6: 48245 | CK6: 48274 | CL6: 48305 | CM6: 48335 | CN6: 48366 | CO6: 48396 | CP6: 48427 | CQ6: 48458 | CR6: 48488 | CS6: 48519 | CT6: 48549 | CU6: 48580 | CV6: 48611 | CW6: 48639 | CX6: 48670 | CY6: 48700 | CZ6: 48731 | DA6: 48761 | DB6: 48792 | DC6: 48823 | DD6: 48853 | DE6: 48884 | DF6: 48914 | DG6: 48945 | DH6: 48976 | DI6: 49004 | DJ6: 49035 | DK6: 49065 | DL6: 49096 | DM6: 49126 | DN6: 49157 | DO6: 49188 | DP6: 49218 | DQ6: 49249 | DR6: 49279
B7: REVENUE
B8: Gross Potential Rent | C8: {=IF(AND(C$3>=INDEX(Inputs!$C:$C,MATCH("*Revenue Start Month*",Inputs!$B:$B,0)),C$3<=INDEX(Inputs!$C:$C,MATCH("End Year",Inputs!$B:$B,0))*12),INDEX(Inputs!$E:$E,MATCH("*Gross Potential Rent*",Inputs!$B:$B,0))/12*(1+INDEX(Inputs!$C:$C,MATCH("*Annual Revenue Growth Rate*",Inputs!$B:$B,0)))^(C$5-1),0)} -> 0 | D8: {=IF(AND(D$3>=INDEX(Inputs!$C:$C,MATCH("*Revenue Start Month*",Inputs!$B:$B,0)),D$3<=INDEX(Inputs!$C:$C,MATCH("End Year",Inputs!$B:$B,0))*12),INDEX(Inputs!$E:$E,MATCH("*Gross Potential Rent*",Inputs!$B:$B,0))/12*(1+INDEX(Inputs!$C:$C,MATCH("*Annual Revenue Growth Rate*",Inputs!$B:$B,0)))^(D$5-1),0)} -> 0 | E8: {=IF(AND(E$3>=INDEX(Inputs!$C:$C,MATCH("*Revenue Start Month*",Inputs!$B:$B,0)),E$3<=INDEX(Inputs!$C:$C,MATCH("End Year",Inputs!$B:$B,0))*12),INDEX(Inputs!$E:$E,MATCH("*Gross Potential Rent*",Inputs!$B:$B,0))/12*(1+INDEX(Inputs!$C:$C,MATCH("*Annual Revenue Growth Rate*",Inputs!$B:$B,0)))^(E$5-1),0)} -> 0 | F8: {=IF(AND(F$3>=INDEX(Inputs!$C:$C,MATCH("*Revenue Start Month*",Inputs!$B:$B,0)),F$3<=INDEX(Inputs!$C:$C,MATCH("End Year",Inputs!$B:$B,0))*12),INDEX(Inputs!$E:$E,MATCH("*Gross Potential Rent*",Inputs!$B:$B,0))/12*(1+INDEX(Inputs!$C:$C,MATCH("*Annual Revenue Growth Rate*",Inputs!$B:$B,0)))^(F$5-1),0)} -> 0 | G8: {=IF(AND(G$3>=INDEX(Inputs!$C:$C,MATCH("*Revenue Start Month*",Inputs!$B:$B,0)),G$3<=INDEX(Inputs!$C:$C,MATCH("End Year",Inputs!$B:$B,0))*12),INDEX(Inputs!$E:$E,MATCH("*Gross Potential Rent*",Inputs!$B:$B,0))/12*(1+INDEX(Inputs!$C:$C,MATCH("*Annual Revenue Growth Rate*",Inputs!$B:$B,0)))^(G$5-1),0)} -> 0 | H8: {=IF(AND(H$3>=INDEX(Inputs!$C:$C,MATCH("*Revenue Start Month*",Inputs!$B:$B,0)),H$3<=INDEX(Inputs!$C:$C,MATCH("End Year",Inputs!$B:$B,0))*12),INDEX(Inputs!$E:$E,MATCH("*Gross Potential Rent*",Inputs!$B:$B,0))/12*(1+INDEX(Inputs!$C:$C,MATCH("*Annual Revenue Growth Rate*",Inputs!$B:$B,0)))^(H$5-1),0)} -> 0 | I8: {=IF(AND(I$3>=INDEX(Inputs!$C:$C,MATCH("*Revenue Start Month*",Inputs!$B:$B,0)),I$3<=INDEX(Inputs!$C:$C,MATCH("End Year",Inputs!$B:$B,0))*12),INDEX(Inputs!$E:$E,MATCH("*Gross Potential Rent*",Inputs!$B:$B,0))/12*(1+INDEX(Inputs!$C:$C,MATCH("*Annual Revenue Growth Rate*",Inputs!$B:$B,0)))^(I$5-1),0)} -> 0 | J8: {=IF(AND(J$3>=INDEX(Inputs!$C:$C,MATCH("*Revenue Start Month*",Inputs!$B:$B,0)),J$3<=INDEX(Inputs!$C:$C,MATCH("End Year",Inputs!$B:$B,0))*12),INDEX(Inputs!$E:$E,MATCH("*Gross Potential Rent*",Inputs!$B:$B,0))/12*(1+INDEX(Inputs!$C:$C,MATCH("*Annual Revenue Growth Rate*",Inputs!$B:$B,0)))^(J$5-1),0)} -> 0 | ... DS8: {=IF(AND(DS$3>=INDEX(Inputs!$C:$C,MATCH("*Revenue Start Month*",Inputs!$B:$B,0)),DS$3<=INDEX(Inputs!$C:$C,MATCH("End Year",Inputs!$B:$B,0))*12),INDEX(Inputs!$E:$E,MATCH("*Gross Potential Rent*",Inputs!$B:$B,0))/12*(1+INDEX(Inputs!$C:$C,MATCH("*Annual Revenue Growth Rate*",Inputs!$B:$B,0)))^(DS$5-1),0)} -> 0
B9: Less: Vacancy | C9: {=IF(C$3<=INDEX(Inputs!$C:$C,MATCH("End Year",Inputs!$B:$B,0))*12,-C8*INDEX(Inputs!$E:$E,MATCH("*Vacancy*",Inputs!$B:$B,0)),0)} -> 0 | D9: {=IF(D$3<=INDEX(Inputs!$C:$C,MATCH("End Year",Inputs!$B:$B,0))*12,-D8*INDEX(Inputs!$E:$E,MATCH("*Vacancy*",Inputs!$B:$B,0)),0)} -> 0 | E9: {=IF(E$3<=INDEX(Inputs!$C:$C,MATCH("End Year",Inputs!$B:$B,0))*12,-E8*INDEX(Inputs!$E:$E,MATCH("*Vacancy*",Inputs!$B:$B,0)),0)} -> 0 | F9: {=IF(F$3<=INDEX(Inputs!$C:$C,MATCH("End Year",Inputs!$B:$B,0))*12,-F8*INDEX(Inputs!$E:$E,MATCH("*Vacancy*",Inputs!$B:$B,0)),0)} -> 0 | G9: {=IF(G$3<=INDEX(Inputs!$C:$C,MATCH("End Year",Inputs!$B:$B,0))*12,-G8*INDEX(Inputs!$E:$E,MATCH("*Vacancy*",Inputs!$B:$B,0)),0)} -> 0 | H9: {=IF(H$3<=INDEX(Inputs!$C:$C,MATCH("End Year",Inputs!$B:$B,0))*12,-H8*INDEX(Inputs!$E:$E,MATCH("*Vacancy*",Inputs!$B:$B,0)),0)} -> 0 | I9: {=IF(I$3<=INDEX(Inputs!$C:$C,MATCH("End Year",Inputs!$B:$B,0))*12,-I8*INDEX(Inputs!$E:$E,MATCH("*Vacancy*",Inputs!$B:$B,0)),0)} -> 0 | J9: {=IF(J$3<=INDEX(Inputs!$C:$C,MATCH("End Year",Inputs!$B:$B,0))*12,-J8*INDEX(Inputs!$E:$E,MATCH("*Vacancy*",Inputs!$B:$B,0)),0)} -> 0 | ... DS9: {=IF(DS$3<=INDEX(Inputs!$C:$C,MATCH("End Year",Inputs!$B:$B,0))*12,-DS8*INDEX(Inputs!$E:$E,MATCH("*Vacancy*",Inputs!$B:$B,0)),0)} -> 0
B10: Less: Credit Loss | C10: {=IF(C$3<=INDEX(Inputs!$C:$C,MATCH("End Year",Inputs!$B:$B,0))*12,-C8*INDEX(Inputs!$E:$E,MATCH("*Credit Loss*",Inputs!$B:$B,0)),0)} -> 0 | D10: {=IF(D$3<=INDEX(Inputs!$C:$C,MATCH("End Year",Inputs!$B:$B,0))*12,-D8*INDEX(Inputs!$E:$E,MATCH("*Credit Loss*",Inputs!$B:$B,0)),0)} -> 0 | E10: {=IF(E$3<=INDEX(Inputs!$C:$C,MATCH("End Year",Inputs!$B:$B,0))*12,-E8*INDEX(Inputs!$E:$E,MATCH("*Credit Loss*",Inputs!$B:$B,0)),0)} -> 0 | F10: {=IF(F$3<=INDEX(Inputs!$C:$C,MATCH("End Year",Inputs!$B:$B,0))*12,-F8*INDEX(Inputs!$E:$E,MATCH("*Credit Loss*",Inputs!$B:$B,0)),0)} -> 0 | G10: {=IF(G$3<=INDEX(Inputs!$C:$C,MATCH("End Year",Inputs!$B:$B,0))*12,-G8*INDEX(Inputs!$E:$E,MATCH("*Credit Loss*",Inputs!$B:$B,0)),0)} -> 0 | H10: {=IF(H$3<=INDEX(Inputs!$C:$C,MATCH("End Year",Inputs!$B:$B,0))*12,-H8*INDEX(Inputs!$E:$E,MATCH("*Credit Loss*",Inputs!$B:$B,0)),0)} -> 0 | I10: {=IF(I$3<=INDEX(Inputs!$C:$C,MATCH("End Year",Inputs!$B:$B,0))*12,-I8*INDEX(Inputs!$E:$E,MATCH("*Credit Loss*",Inputs!$B:$B,0)),0)} -> 0 | J10: {=IF(J$3<=INDEX(Inputs!$C:$C,MATCH("End Year",Inputs!$B:$B,0))*12,-J8*INDEX(Inputs!$E:$E,MATCH("*Credit Loss*",Inputs!$B:$B,0)),0)} -> 0 | ... DS10: {=IF(DS$3<=INDEX(Inputs!$C:$C,MATCH("End Year",Inputs!$B:$B,0))*12,-DS8*INDEX(Inputs!$E:$E,MATCH("*Credit Loss*",Inputs!$B:$B,0)),0)} -> 0
B11: Effective Gross Income (EGI) | C11: =C8+C9+C10 -> 0 | D11: =D8+D9+D10 -> 0 | E11: =E8+E9+E10 -> 0 | F11: =F8+F9+F10 -> 0 | G11: =G8+G9+G10 -> 0 | H11: =H8+H9+H10 -> 0 | I11: =I8+I9+I10 -> 0 | J11: =J8+J9+J10 -> 0 | ... DR11: =DR8+DR9+DR10 -> 0
B12: Revenue | C12: {=IF($B12="",0,IF(AND(C$3>=INDEX(Inputs!$C:$C,MATCH("*Revenue Start Month*",Inputs!$B:$B,0)),C$3<=INDEX(Inputs!$C:$C,MATCH("End Year",Inputs!$B:$B,0))*12),IncomeExpenses!$C$47/12*(1+INDEX(Inputs!$C:$C,MATCH("*Annual Revenue Growth Rate*",Inputs!$B:$B,0)))^(C$5-1),0))} -> 0 | D12: {=IF($B12="",0,IF(AND(D$3>=INDEX(Inputs!$C:$C,MATCH("*Revenue Start Month*",Inputs!$B:$B,0)),D$3<=INDEX(Inputs!$C:$C,MATCH("End Year",Inputs!$B:$B,0))*12),IncomeExpenses!$C$47/12*(1+INDEX(Inputs!$C:$C,MATCH("*Annual Revenue Growth Rate*",Inputs!$B:$B,0)))^(D$5-1),0))} -> 0 | E12: {=IF($B12="",0,IF(AND(E$3>=INDEX(Inputs!$C:$C,MATCH("*Revenue Start Month*",Inputs!$B:$B,0)),E$3<=INDEX(Inputs!$C:$C,MATCH("End Year",Inputs!$B:$B,0))*12),IncomeExpenses!$C$47/12*(1+INDEX(Inputs!$C:$C,MATCH("*Annual Revenue Growth Rate*",Inputs!$B:$B,0)))^(E$5-1),0))} -> 0 | F12: {=IF($B12="",0,IF(AND(F$3>=INDEX(Inputs!$C:$C,MATCH("*Revenue Start Month*",Inputs!$B:$B,0)),F$3<=INDEX(Inputs!$C:$C,MATCH("End Year",Inputs!$B:$B,0))*12),IncomeExpenses!$C$47/12*(1+INDEX(Inputs!$C:$C,MATCH("*Annual Revenue Growth Rate*",Inputs!$B:$B,0)))^(F$5-1),0))} -> 0 | G12: {=IF($B12="",0,IF(AND(G$3>=INDEX(Inputs!$C:$C,MATCH("*Revenue Start Month*",Inputs!$B:$B,0)),G$3<=INDEX(Inputs!$C:$C,MATCH("End Year",Inputs!$B:$B,0))*12),IncomeExpenses!$C$47/12*(1+INDEX(Inputs!$C:$C,MATCH("*Annual Revenue Growth Rate*",Inputs!$B:$B,0)))^(G$5-1),0))} -> 0 | H12: {=IF($B12="",0,IF(AND(H$3>=INDEX(Inputs!$C:$C,MATCH("*Revenue Start Month*",Inputs!$B:$B,0)),H$3<=INDEX(Inputs!$C:$C,MATCH("End Year",Inputs!$B:$B,0))*12),IncomeExpenses!$C$47/12*(1+INDEX(Inputs!$C:$C,MATCH("*Annual Revenue Growth Rate*",Inputs!$B:$B,0)))^(H$5-1),0))} -> 0 | I12: {=IF($B12="",0,IF(AND(I$3>=INDEX(Inputs!$C:$C,MATCH("*Revenue Start Month*",Inputs!$B:$B,0)),I$3<=INDEX(Inputs!$C:$C,MATCH("End Year",Inputs!$B:$B,0))*12),IncomeExpenses!$C$47/12*(1+INDEX(Inputs!$C:$C,MATCH("*Annual Revenue Growth Rate*",Inputs!$B:$B,0)))^(I$5-1),0))} -> 0 | J12: {=IF($B12="",0,IF(AND(J$3>=INDEX(Inputs!$C:$C,MATCH("*Revenue Start Month*",Inputs!$B:$B,0)),J$3<=INDEX(Inputs!$C:$C,MATCH("End Year",Inputs!$B:$B,0))*12),IncomeExpenses!$C$47/12*(1+INDEX(Inputs!$C:$C,MATCH("*Annual Revenue Growth Rate*",Inputs!$B:$B,0)))^(J$5-1),0))} -> 0 | ... DS12: {=IF($B12="",0,IF(AND(DS$3>=INDEX(Inputs!$C:$C,MATCH("*Revenue Start Month*",Inputs!$B:$B,0)),DS$3<=INDEX(Inputs!$C:$C,MATCH("End Year",Inputs!$B:$B,0))*12),IncomeExpenses!$C$47/12*(1+INDEX(Inputs!$C:$C,MATCH("*Annual Revenue Growth Rate*",Inputs!$B:$B,0)))^(DS$5-1),0))} -> 0
B13: TOTAL REVENUE | C13: =C11+SUM(C12) -> 0 | D13: =D11+SUM(D12) -> 0 | E13: =E11+SUM(E12) -> 0 | F13: =F11+SUM(F12) -> 0 | G13: =G11+SUM(G12) -> 0 | H13: =H11+SUM(H12) -> 0 | I13: =I11+SUM(I12) -> 0 | J13: =J11+SUM(J12) -> 0 | ... DS13: =DS11+SUM(DS12) -> 0
B15: OPERATING EXPENSES
B16: Property Management Fee (%EGI) | C16: {=IF($B16="",0,IF(AND(C$3>=INDEX(Inputs!$C:$C,MATCH("*Expense Start Month*",Inputs!$B:$B,0)),C$3<=INDEX(Inputs!$C:$C,MATCH("End Year",Inputs!$B:$B,0))*12),IF($B16="Property Management Fee (%EGI)",-C11*Inputs!$C$28,-IncomeExpenses!$C$90/12*(1+INDEX(Inputs!$C:$C,MATCH("*Annual Expense Growth Rate*",Inputs!$B:$B,0)))^(C$5-1)),0))} -> 0 | D16: {=IF($B16="",0,IF(AND(D$3>=INDEX(Inputs!$C:$C,MATCH("*Expense Start Month*",Inputs!$B:$B,0)),D$3<=INDEX(Inputs!$C:$C,MATCH("End Year",Inputs!$B:$B,0))*12),IF($B16="Property Management Fee (%EGI)",-D11*Inputs!$C$28,-IncomeExpenses!$C$90/12*(1+INDEX(Inputs!$C:$C,MATCH("*Annual Expense Growth Rate*",Inputs!$B:$B,0)))^(D$5-1)),0))} -> 0 | E16: {=IF($B16="",0,IF(AND(E$3>=INDEX(Inputs!$C:$C,MATCH("*Expense Start Month*",Inputs!$B:$B,0)),E$3<=INDEX(Inputs!$C:$C,MATCH("End Year",Inputs!$B:$B,0))*12),IF($B16="Property Management Fee (%EGI)",-E11*Inputs!$C$28,-IncomeExpenses!$C$90/12*(1+INDEX(Inputs!$C:$C,MATCH("*Annual Expense Growth Rate*",Inputs!$B:$B,0)))^(E$5-1)),0))} -> 0 | F16: {=IF($B16="",0,IF(AND(F$3>=INDEX(Inputs!$C:$C,MATCH("*Expense Start Month*",Inputs!$B:$B,0)),F$3<=INDEX(Inputs!$C:$C,MATCH("End Year",Inputs!$B:$B,0))*12),IF($B16="Property Management Fee (%EGI)",-F11*Inputs!$C$28,-IncomeExpenses!$C$90/12*(1+INDEX(Inputs!$C:$C,MATCH("*Annual Expense Growth Rate*",Inputs!$B:$B,0)))^(F$5-1)),0))} -> 0 | G16: {=IF($B16="",0,IF(AND(G$3>=INDEX(Inputs!$C:$C,MATCH("*Expense Start Month*",Inputs!$B:$B,0)),G$3<=INDEX(Inputs!$C:$C,MATCH("End Year",Inputs!$B:$B,0))*12),IF($B16="Property Management Fee (%EGI)",-G11*Inputs!$C$28,-IncomeExpenses!$C$90/12*(1+INDEX(Inputs!$C:$C,MATCH("*Annual Expense Growth Rate*",Inputs!$B:$B,0)))^(G$5-1)),0))} -> 0 | H16: {=IF($B16="",0,IF(AND(H$3>=INDEX(Inputs!$C:$C,MATCH("*Expense Start Month*",Inputs!$B:$B,0)),H$3<=INDEX(Inputs!$C:$C,MATCH("End Year",Inputs!$B:$B,0))*12),IF($B16="Property Management Fee (%EGI)",-H11*Inputs!$C$28,-IncomeExpenses!$C$90/12*(1+INDEX(Inputs!$C:$C,MATCH("*Annual Expense Growth Rate*",Inputs!$B:$B,0)))^(H$5-1)),0))} -> 0 | I16: {=IF($B16="",0,IF(AND(I$3>=INDEX(Inputs!$C:$C,MATCH("*Expense Start Month*",Inputs!$B:$B,0)),I$3<=INDEX(Inputs!$C:$C,MATCH("End Year",Inputs!$B:$B,0))*12),IF($B16="Property Management Fee (%EGI)",-I11*Inputs!$C$28,-IncomeExpenses!$C$90/12*(1+INDEX(Inputs!$C:$C,MATCH("*Annual Expense Growth Rate*",Inputs!$B:$B,0)))^(I$5-1)),0))} -> 0 | J16: {=IF($B16="",0,IF(AND(J$3>=INDEX(Inputs!$C:$C,MATCH("*Expense Start Month*",Inputs!$B:$B,0)),J$3<=INDEX(Inputs!$C:$C,MATCH("End Year",Inputs!$B:$B,0))*12),IF($B16="Property Management Fee (%EGI)",-J11*Inputs!$C$28,-IncomeExpenses!$C$90/12*(1+INDEX(Inputs!$C:$C,MATCH("*Annual Expense Growth Rate*",Inputs!$B:$B,0)))^(J$5-1)),0))} -> 0 | ... DS16: {=IF($B16="",0,IF(AND(DS$3>=INDEX(Inputs!$C:$C,MATCH("*Expense Start Month*",Inputs!$B:$B,0)),DS$3<=INDEX(Inputs!$C:$C,MATCH("End Year",Inputs!$B:$B,0))*12),IF($B16="Property Management Fee (%EGI)",-DS11*Inputs!$C$28,-IncomeExpenses!$C$90/12*(1+INDEX(Inputs!$C:$C,MATCH("*Annual Expense Growth Rate*",Inputs!$B:$B,0)))^(DS$5-1)),0))} -> 0
B17: Expenses | C17: {=IF($B17="",0,IF(AND(C$3>=INDEX(Inputs!$C:$C,MATCH("*Expense Start Month*",Inputs!$B:$B,0)),C$3<=INDEX(Inputs!$C:$C,MATCH("End Year",Inputs!$B:$B,0))*12),IF($B17="Property Management Fee (%EGI)",-C11*Inputs!$C$28,-IncomeExpenses!$C$90/12*(1+INDEX(Inputs!$C:$C,MATCH("*Annual Expense Growth Rate*",Inputs!$B:$B,0)))^(C$5-1)),0))} -> 0 | D17: {=IF($B17="",0,IF(AND(D$3>=INDEX(Inputs!$C:$C,MATCH("*Expense Start Month*",Inputs!$B:$B,0)),D$3<=INDEX(Inputs!$C:$C,MATCH("End Year",Inputs!$B:$B,0))*12),IF($B17="Property Management Fee (%EGI)",-D11*Inputs!$C$28,-IncomeExpenses!$C$90/12*(1+INDEX(Inputs!$C:$C,MATCH("*Annual Expense Growth Rate*",Inputs!$B:$B,0)))^(D$5-1)),0))} -> 0 | E17: {=IF($B17="",0,IF(AND(E$3>=INDEX(Inputs!$C:$C,MATCH("*Expense Start Month*",Inputs!$B:$B,0)),E$3<=INDEX(Inputs!$C:$C,MATCH("End Year",Inputs!$B:$B,0))*12),IF($B17="Property Management Fee (%EGI)",-E11*Inputs!$C$28,-IncomeExpenses!$C$90/12*(1+INDEX(Inputs!$C:$C,MATCH("*Annual Expense Growth Rate*",Inputs!$B:$B,0)))^(E$5-1)),0))} -> 0 | F17: {=IF($B17="",0,IF(AND(F$3>=INDEX(Inputs!$C:$C,MATCH("*Expense Start Month*",Inputs!$B:$B,0)),F$3<=INDEX(Inputs!$C:$C,MATCH("End Year",Inputs!$B:$B,0))*12),IF($B17="Property Management Fee (%EGI)",-F11*Inputs!$C$28,-IncomeExpenses!$C$90/12*(1+INDEX(Inputs!$C:$C,MATCH("*Annual Expense Growth Rate*",Inputs!$B:$B,0)))^(F$5-1)),0))} -> 0 | G17: {=IF($B17="",0,IF(AND(G$3>=INDEX(Inputs!$C:$C,MATCH("*Expense Start Month*",Inputs!$B:$B,0)),G$3<=INDEX(Inputs!$C:$C,MATCH("End Year",Inputs!$B:$B,0))*12),IF($B17="Property Management Fee (%EGI)",-G11*Inputs!$C$28,-IncomeExpenses!$C$90/12*(1+INDEX(Inputs!$C:$C,MATCH("*Annual Expense Growth Rate*",Inputs!$B:$B,0)))^(G$5-1)),0))} -> 0 | H17: {=IF($B17="",0,IF(AND(H$3>=INDEX(Inputs!$C:$C,MATCH("*Expense Start Month*",Inputs!$B:$B,0)),H$3<=INDEX(Inputs!$C:$C,MATCH("End Year",Inputs!$B:$B,0))*12),IF($B17="Property Management Fee (%EGI)",-H11*Inputs!$C$28,-IncomeExpenses!$C$90/12*(1+INDEX(Inputs!$C:$C,MATCH("*Annual Expense Growth Rate*",Inputs!$B:$B,0)))^(H$5-1)),0))} -> 0 | I17: {=IF($B17="",0,IF(AND(I$3>=INDEX(Inputs!$C:$C,MATCH("*Expense Start Month*",Inputs!$B:$B,0)),I$3<=INDEX(Inputs!$C:$C,MATCH("End Year",Inputs!$B:$B,0))*12),IF($B17="Property Management Fee (%EGI)",-I11*Inputs!$C$28,-IncomeExpenses!$C$90/12*(1+INDEX(Inputs!$C:$C,MATCH("*Annual Expense Growth Rate*",Inputs!$B:$B,0)))^(I$5-1)),0))} -> 0 | J17: {=IF($B17="",0,IF(AND(J$3>=INDEX(Inputs!$C:$C,MATCH("*Expense Start Month*",Inputs!$B:$B,0)),J$3<=INDEX(Inputs!$C:$C,MATCH("End Year",Inputs!$B:$B,0))*12),IF($B17="Property Management Fee (%EGI)",-J11*Inputs!$C$28,-IncomeExpenses!$C$90/12*(1+INDEX(Inputs!$C:$C,MATCH("*Annual Expense Growth Rate*",Inputs!$B:$B,0)))^(J$5-1)),0))} -> 0 | ... DS17: {=IF($B17="",0,IF(AND(DS$3>=INDEX(Inputs!$C:$C,MATCH("*Expense Start Month*",Inputs!$B:$B,0)),DS$3<=INDEX(Inputs!$C:$C,MATCH("End Year",Inputs!$B:$B,0))*12),IF($B17="Property Management Fee (%EGI)",-DS11*Inputs!$C$28,-IncomeExpenses!$C$90/12*(1+INDEX(Inputs!$C:$C,MATCH("*Annual Expense Growth Rate*",Inputs!$B:$B,0)))^(DS$5-1)),0))} -> 0
B18: TOTAL OPERATING EXPENSES | C18: =SUM(C16:C17) -> 0 | D18: =SUM(D16:D17) -> 0 | E18: =SUM(E16:E17) -> 0 | F18: =SUM(F16:F17) -> 0 | G18: =SUM(G16:G17) -> 0 | H18: =SUM(H16:H17) -> 0 | I18: =SUM(I16:I17) -> 0 | J18: =SUM(J16:J17) -> 0 | ... DS18: =SUM(DS16:DS17) -> 0
B20: NET OPERATING INCOME (NOI) | C20: =C13+C18 -> 0 | D20: =D13+D18 -> 0 | E20: =E13+E18 -> 0 | F20: =F13+F18 -> 0 | G20: =G13+G18 -> 0 | H20: =H13+H18 -> 0 | I20: =I13+I18 -> 0 | J20: =J13+J18 -> 0 | ... DS20: =DS13+DS18 -> 0
B22: CAPITAL EXPENDITURES
B23: Capital Expenditures (CapEx) | C23: {=IF(C$3<=INDEX(Inputs!$C:$C,MATCH("End Year",Inputs!$B:$B,0))*12,-SUMIFS(Inputs!$C:$C,Inputs!$B:$B,"*CapEx Item*",Inputs!$D:$D,C$3),0)} -> 0 | D23: {=IF(D$3<=INDEX(Inputs!$C:$C,MATCH("End Year",Inputs!$B:$B,0))*12,-SUMIFS(Inputs!$C:$C,Inputs!$B:$B,"*CapEx Item*",Inputs!$D:$D,D$3),0)} -> 0 | E23: {=IF(E$3<=INDEX(Inputs!$C:$C,MATCH("End Year",Inputs!$B:$B,0))*12,-SUMIFS(Inputs!$C:$C,Inputs!$B:$B,"*CapEx Item*",Inputs!$D:$D,E$3),0)} -> 0 | F23: {=IF(F$3<=INDEX(Inputs!$C:$C,MATCH("End Year",Inputs!$B:$B,0))*12,-SUMIFS(Inputs!$C:$C,Inputs!$B:$B,"*CapEx Item*",Inputs!$D:$D,F$3),0)} -> 0 | G23: {=IF(G$3<=INDEX(Inputs!$C:$C,MATCH("End Year",Inputs!$B:$B,0))*12,-SUMIFS(Inputs!$C:$C,Inputs!$B:$B,"*CapEx Item*",Inputs!$D:$D,G$3),0)} -> 0 | H23: {=IF(H$3<=INDEX(Inputs!$C:$C,MATCH("End Year",Inputs!$B:$B,0))*12,-SUMIFS(Inputs!$C:$C,Inputs!$B:$B,"*CapEx Item*",Inputs!$D:$D,H$3),0)} -> 0 | I23: {=IF(I$3<=INDEX(Inputs!$C:$C,MATCH("End Year",Inputs!$B:$B,0))*12,-SUMIFS(Inputs!$C:$C,Inputs!$B:$B,"*CapEx Item*",Inputs!$D:$D,I$3),0)} -> 0 | J23: {=IF(J$3<=INDEX(Inputs!$C:$C,MATCH("End Year",Inputs!$B:$B,0))*12,-SUMIFS(Inputs!$C:$C,Inputs!$B:$B,"*CapEx Item*",Inputs!$D:$D,J$3),0)} -> 0 | ... DS23: {=IF(DS$3<=INDEX(Inputs!$C:$C,MATCH("End Year",Inputs!$B:$B,0))*12,-SUMIFS(Inputs!$C:$C,Inputs!$B:$B,"*CapEx Item*",Inputs!$D:$D,DS$3),0)} -> 0
B25: ACQUISITION
B26: Purchase Price | C26: {=IF(C$3=1,-INDEX(Inputs!$C:$C,MATCH("*Purchase Price*",Inputs!$B:$B,0)),0)} -> 0 | D26: {=IF(D$3=1,-INDEX(Inputs!$C:$C,MATCH("*Purchase Price*",Inputs!$B:$B,0)),0)} -> 0 | E26: {=IF(E$3=1,-INDEX(Inputs!$C:$C,MATCH("*Purchase Price*",Inputs!$B:$B,0)),0)} -> 0 | F26: {=IF(F$3=1,-INDEX(Inputs!$C:$C,MATCH("*Purchase Price*",Inputs!$B:$B,0)),0)} -> 0 | G26: {=IF(G$3=1,-INDEX(Inputs!$C:$C,MATCH("*Purchase Price*",Inputs!$B:$B,0)),0)} -> 0 | H26: {=IF(H$3=1,-INDEX(Inputs!$C:$C,MATCH("*Purchase Price*",Inputs!$B:$B,0)),0)} -> 0 | I26: {=IF(I$3=1,-INDEX(Inputs!$C:$C,MATCH("*Purchase Price*",Inputs!$B:$B,0)),0)} -> 0 | J26: {=IF(J$3=1,-INDEX(Inputs!$C:$C,MATCH("*Purchase Price*",Inputs!$B:$B,0)),0)} -> 0 | ... DS26: {=IF(DS$3=1,-INDEX(Inputs!$C:$C,MATCH("*Purchase Price*",Inputs!$B:$B,0)),0)} -> 0
B27: Closing Costs | C27: =IF(C$3=1,-Inputs!C85,0) -> 0 | D27: =IF(D$3=1,-Inputs!C85,0) -> 0 | E27: =IF(E$3=1,-Inputs!C85,0) -> 0 | F27: =IF(F$3=1,-Inputs!C85,0) -> 0 | G27: =IF(G$3=1,-Inputs!C85,0) -> 0 | H27: =IF(H$3=1,-Inputs!C85,0) -> 0 | I27: =IF(I$3=1,-Inputs!C85,0) -> 0 | J27: =IF(J$3=1,-Inputs!C85,0) -> 0 | K27: =IF(K$3=1,-Inputs!C85,0) -> 0 | L27: =IF(L$3=1,-Inputs!C85,0) -> 0 | M27: =IF(M$3=1,-Inputs!C85,0) -> 0 | N27: =IF(N$3=1,-Inputs!C85,0) -> 0 | O27: =IF(O$3=1,-Inputs!C85,0) -> 0 | P27: =IF(P$3=1,-Inputs!C85,0) -> 0 | Q27: =IF(Q$3=1,-Inputs!C85,0) -> 0 | R27: =IF(R$3=1,-Inputs!C85,0) -> 0 | S27: =IF(S$3=1,-Inputs!C85,0) -> 0 | T27: =IF(T$3=1,-Inputs!C85,0) -> 0 | U27: =IF(U$3=1,-Inputs!C85,0) -> 0 | V27: =IF(V$3=1,-Inputs!C85,0) -> 0 | W27: =IF(W$3=1,-Inputs!C85,0) -> 0 | X27: =IF(X$3=1,-Inputs!C85,0) -> 0 | Y27: =IF(Y$3=1,-Inputs!C85,0) -> 0 | Z27: =IF(Z$3=1,-Inputs!C85,0) -> 0 | AA27: =IF(AA$3=1,-Inputs!C85,0) -> 0 | AB27: =IF(AB$3=1,-Inputs!C85,0) -> 0 | AC27: =IF(AC$3=1,-Inputs!C85,0) -> 0 | AD27: =IF(AD$3=1,-Inputs!C85,0) -> 0 | AE27: =IF(AE$3=1,-Inputs!C85,0) -> 0 | AF27: =IF(AF$3=1,-Inputs!C85,0) -> 0 | AG27: =IF(AG$3=1,-Inputs!C85,0) -> 0 | AH27: =IF(AH$3=1,-Inputs!C85,0) -> 0 | AI27: =IF(AI$3=1,-Inputs!C85,0) -> 0 | AJ27: =IF(AJ$3=1,-Inputs!C85,0) -> 0 | AK27: =IF(AK$3=1,-Inputs!C85,0) -> 0 | AL27: =IF(AL$3=1,-Inputs!C85,0) -> 0 | AM27: =IF(AM$3=1,-Inputs!C85,0) -> 0 | AN27: =IF(AN$3=1,-Inputs!C85,0) -> 0 | AO27: =IF(AO$3=1,-Inputs!C85,0) -> 0 | AP27: =IF(AP$3=1,-Inputs!C85,0) -> 0 | AQ27: =IF(AQ$3=1,-Inputs!C85,0) -> 0 | AR27: =IF(AR$3=1,-Inputs!C85,0) -> 0 | AS27: =IF(AS$3=1,-Inputs!C85,0) -> 0 | AT27: =IF(AT$3=1,-Inputs!C85,0) -> 0 | AU27: =IF(AU$3=1,-Inputs!C85,0) -> 0 | AV27: =IF(AV$3=1,-Inputs!C85,0) -> 0 | AW27: =IF(AW$3=1,-Inputs!C85,0) -> 0 | AX27: =IF(AX$3=1,-Inputs!C85,0) -> 0 | AY27: =IF(AY$3=1,-Inputs!C85,0) -> 0 | AZ27: =IF(AZ$3=1,-Inputs!C85,0) -> 0 | BA27: =IF(BA$3=1,-Inputs!C85,0) -> 0 | BB27: =IF(BB$3=1,-Inputs!C85,0) -> 0 | BC27: =IF(BC$3=1,-Inputs!C85,0) -> 0 | BD27: =IF(BD$3=1,-Inputs!C85,0) -> 0 | BE27: =IF(BE$3=1,-Inputs!C85,0) -> 0 | BF27: =IF(BF$3=1,-Inputs!C85,0) -> 0 | BG27: =IF(BG$3=1,-Inputs!C85,0) -> 0 | BH27: =IF(BH$3=1,-Inputs!C85,0) -> 0 | BI27: =IF(BI$3=1,-Inputs!C85,0) -> 0 | BJ27: =IF(BJ$3=1,-Inputs!C85,0) -> 0 | BK27: =IF(BK$3=1,-Inputs!C85,0) -> 0 | BL27: =IF(BL$3=1,-Inputs!C85,0) -> 0 | BM27: =IF(BM$3=1,-Inputs!C85,0) -> 0 | BN27: =IF(BN$3=1,-Inputs!C85,0) -> 0 | BO27: =IF(BO$3=1,-Inputs!C85,0) -> 0 | BP27: =IF(BP$3=1,-Inputs!C85,0) -> 0 | BQ27: =IF(BQ$3=1,-Inputs!C85,0) -> 0 | BR27: =IF(BR$3=1,-Inputs!C85,0) -> 0 | BS27: =IF(BS$3=1,-Inputs!C85,0) -> 0 | BT27: =IF(BT$3=1,-Inputs!C85,0) -> 0 | BU27: =IF(BU$3=1,-Inputs!C85,0) -> 0 | BV27: =IF(BV$3=1,-Inputs!C85,0) -> 0 | BW27: =IF(BW$3=1,-Inputs!C85,0) -> 0 | BX27: =IF(BX$3=1,-Inputs!C85,0) -> 0 | BY27: =IF(BY$3=1,-Inputs!C85,0) -> 0 | BZ27: =IF(BZ$3=1,-Inputs!C85,0) -> 0 | CA27: =IF(CA$3=1,-Inputs!C85,0) -> 0 | CB27: =IF(CB$3=1,-Inputs!C85,0) -> 0 | CC27: =IF(CC$3=1,-Inputs!C85,0) -> 0 | CD27: =IF(CD$3=1,-Inputs!C85,0) -> 0 | CE27: =IF(CE$3=1,-Inputs!C85,0) -> 0 | CF27: =IF(CF$3=1,-Inputs!C85,0) -> 0 | CG27: =IF(CG$3=1,-Inputs!C85,0) -> 0 | CH27: =IF(CH$3=1,-Inputs!C85,0) -> 0 | CI27: =IF(CI$3=1,-Inputs!C85,0) -> 0 | CJ27: =IF(CJ$3=1,-Inputs!C85,0) -> 0 | CK27: =IF(CK$3=1,-Inputs!C85,0) -> 0 | CL27: =IF(CL$3=1,-Inputs!C85,0) -> 0 | CM27: =IF(CM$3=1,-Inputs!C85,0) -> 0 | CN27: =IF(CN$3=1,-Inputs!C85,0) -> 0 | CO27: =IF(CO$3=1,-Inputs!C85,0) -> 0 | CP27: =IF(CP$3=1,-Inputs!C85,0) -> 0 | CQ27: =IF(CQ$3=1,-Inputs!C85,0) -> 0 | CR27: =IF(CR$3=1,-Inputs!C85,0) -> 0 | CS27: =IF(CS$3=1,-Inputs!C85,0) -> 0 | CT27: =IF(CT$3=1,-Inputs!C85,0) -> 0 | CU27: =IF(CU$3=1,-Inputs!C85,0) -> 0 | CV27: =IF(CV$3=1,-Inputs!C85,0) -> 0 | CW27: =IF(CW$3=1,-Inputs!C85,0) -> 0 | CX27: =IF(CX$3=1,-Inputs!C85,0) -> 0 | CY27: =IF(CY$3=1,-Inputs!C85,0) -> 0 | CZ27: =IF(CZ$3=1,-Inputs!C85,0) -> 0 | DA27: =IF(DA$3=1,-Inputs!C85,0) -> 0 | DB27: =IF(DB$3=1,-Inputs!C85,0) -> 0 | DC27: =IF(DC$3=1,-Inputs!C85,0) -> 0 | DD27: =IF(DD$3=1,-Inputs!C85,0) -> 0 | DE27: =IF(DE$3=1,-Inputs!C85,0) -> 0 | DF27: =IF(DF$3=1,-Inputs!C85,0) -> 0 | DG27: =IF(DG$3=1,-Inputs!C85,0) -> 0 | DH27: =IF(DH$3=1,-Inputs!C85,0) -> 0 | DI27: =IF(DI$3=1,-Inputs!C85,0) -> 0 | DJ27: =IF(DJ$3=1,-Inputs!C85,0) -> 0 | DK27: =IF(DK$3=1,-Inputs!C85,0) -> 0 | DL27: =IF(DL$3=1,-Inputs!C85,0) -> 0 | DM27: =IF(DM$3=1,-Inputs!C85,0) -> 0 | DN27: =IF(DN$3=1,-Inputs!C85,0) -> 0 | DO27: =IF(DO$3=1,-Inputs!C85,0) -> 0 | DP27: =IF(DP$3=1,-Inputs!C85,0) -> 0 | DQ27: =IF(DQ$3=1,-Inputs!C85,0) -> 0 | DR27: =IF(DR$3=1,-Inputs!C85,0) -> 0 | DS27: =IF(DS$3=1,-Inputs!C85,0) -> 0
B28: Immediate Repairs / Reserves | C28: =IF(C$3=1,-Inputs!C86,0) -> -5000 | D28: =IF(D$3=1,-Inputs!C86,0) -> 0 | E28: =IF(E$3=1,-Inputs!C86,0) -> 0 | F28: =IF(F$3=1,-Inputs!C86,0) -> 0 | G28: =IF(G$3=1,-Inputs!C86,0) -> 0 | H28: =IF(H$3=1,-Inputs!C86,0) -> 0 | I28: =IF(I$3=1,-Inputs!C86,0) -> 0 | J28: =IF(J$3=1,-Inputs!C86,0) -> 0 | K28: =IF(K$3=1,-Inputs!C86,0) -> 0 | L28: =IF(L$3=1,-Inputs!C86,0) -> 0 | M28: =IF(M$3=1,-Inputs!C86,0) -> 0 | N28: =IF(N$3=1,-Inputs!C86,0) -> 0 | O28: =IF(O$3=1,-Inputs!C86,0) -> 0 | P28: =IF(P$3=1,-Inputs!C86,0) -> 0 | Q28: =IF(Q$3=1,-Inputs!C86,0) -> 0 | R28: =IF(R$3=1,-Inputs!C86,0) -> 0 | S28: =IF(S$3=1,-Inputs!C86,0) -> 0 | T28: =IF(T$3=1,-Inputs!C86,0) -> 0 | U28: =IF(U$3=1,-Inputs!C86,0) -> 0 | V28: =IF(V$3=1,-Inputs!C86,0) -> 0 | W28: =IF(W$3=1,-Inputs!C86,0) -> 0 | X28: =IF(X$3=1,-Inputs!C86,0) -> 0 | Y28: =IF(Y$3=1,-Inputs!C86,0) -> 0 | Z28: =IF(Z$3=1,-Inputs!C86,0) -> 0 | AA28: =IF(AA$3=1,-Inputs!C86,0) -> 0 | AB28: =IF(AB$3=1,-Inputs!C86,0) -> 0 | AC28: =IF(AC$3=1,-Inputs!C86,0) -> 0 | AD28: =IF(AD$3=1,-Inputs!C86,0) -> 0 | AE28: =IF(AE$3=1,-Inputs!C86,0) -> 0 | AF28: =IF(AF$3=1,-Inputs!C86,0) -> 0 | AG28: =IF(AG$3=1,-Inputs!C86,0) -> 0 | AH28: =IF(AH$3=1,-Inputs!C86,0) -> 0 | AI28: =IF(AI$3=1,-Inputs!C86,0) -> 0 | AJ28: =IF(AJ$3=1,-Inputs!C86,0) -> 0 | AK28: =IF(AK$3=1,-Inputs!C86,0) -> 0 | AL28: =IF(AL$3=1,-Inputs!C86,0) -> 0 | AM28: =IF(AM$3=1,-Inputs!C86,0) -> 0 | AN28: =IF(AN$3=1,-Inputs!C86,0) -> 0 | AO28: =IF(AO$3=1,-Inputs!C86,0) -> 0 | AP28: =IF(AP$3=1,-Inputs!C86,0) -> 0 | AQ28: =IF(AQ$3=1,-Inputs!C86,0) -> 0 | AR28: =IF(AR$3=1,-Inputs!C86,0) -> 0 | AS28: =IF(AS$3=1,-Inputs!C86,0) -> 0 | AT28: =IF(AT$3=1,-Inputs!C86,0) -> 0 | AU28: =IF(AU$3=1,-Inputs!C86,0) -> 0 | AV28: =IF(AV$3=1,-Inputs!C86,0) -> 0 | AW28: =IF(AW$3=1,-Inputs!C86,0) -> 0 | AX28: =IF(AX$3=1,-Inputs!C86,0) -> 0 | AY28: =IF(AY$3=1,-Inputs!C86,0) -> 0 | AZ28: =IF(AZ$3=1,-Inputs!C86,0) -> 0 | BA28: =IF(BA$3=1,-Inputs!C86,0) -> 0 | BB28: =IF(BB$3=1,-Inputs!C86,0) -> 0 | BC28: =IF(BC$3=1,-Inputs!C86,0) -> 0 | BD28: =IF(BD$3=1,-Inputs!C86,0) -> 0 | BE28: =IF(BE$3=1,-Inputs!C86,0) -> 0 | BF28: =IF(BF$3=1,-Inputs!C86,0) -> 0 | BG28: =IF(BG$3=1,-Inputs!C86,0) -> 0 | BH28: =IF(BH$3=1,-Inputs!C86,0) -> 0 | BI28: =IF(BI$3=1,-Inputs!C86,0) -> 0 | BJ28: =IF(BJ$3=1,-Inputs!C86,0) -> 0 | BK28: =IF(BK$3=1,-Inputs!C86,0) -> 0 | BL28: =IF(BL$3=1,-Inputs!C86,0) -> 0 | BM28: =IF(BM$3=1,-Inputs!C86,0) -> 0 | BN28: =IF(BN$3=1,-Inputs!C86,0) -> 0 | BO28: =IF(BO$3=1,-Inputs!C86,0) -> 0 | BP28: =IF(BP$3=1,-Inputs!C86,0) -> 0 | BQ28: =IF(BQ$3=1,-Inputs!C86,0) -> 0 | BR28: =IF(BR$3=1,-Inputs!C86,0) -> 0 | BS28: =IF(BS$3=1,-Inputs!C86,0) -> 0 | BT28: =IF(BT$3=1,-Inputs!C86,0) -> 0 | BU28: =IF(BU$3=1,-Inputs!C86,0) -> 0 | BV28: =IF(BV$3=1,-Inputs!C86,0) -> 0 | BW28: =IF(BW$3=1,-Inputs!C86,0) -> 0 | BX28: =IF(BX$3=1,-Inputs!C86,0) -> 0 | BY28: =IF(BY$3=1,-Inputs!C86,0) -> 0 | BZ28: =IF(BZ$3=1,-Inputs!C86,0) -> 0 | CA28: =IF(CA$3=1,-Inputs!C86,0) -> 0 | CB28: =IF(CB$3=1,-Inputs!C86,0) -> 0 | CC28: =IF(CC$3=1,-Inputs!C86,0) -> 0 | CD28: =IF(CD$3=1,-Inputs!C86,0) -> 0 | CE28: =IF(CE$3=1,-Inputs!C86,0) -> 0 | CF28: =IF(CF$3=1,-Inputs!C86,0) -> 0 | CG28: =IF(CG$3=1,-Inputs!C86,0) -> 0 | CH28: =IF(CH$3=1,-Inputs!C86,0) -> 0 | CI28: =IF(CI$3=1,-Inputs!C86,0) -> 0 | CJ28: =IF(CJ$3=1,-Inputs!C86,0) -> 0 | CK28: =IF(CK$3=1,-Inputs!C86,0) -> 0 | CL28: =IF(CL$3=1,-Inputs!C86,0) -> 0 | CM28: =IF(CM$3=1,-Inputs!C86,0) -> 0 | CN28: =IF(CN$3=1,-Inputs!C86,0) -> 0 | CO28: =IF(CO$3=1,-Inputs!C86,0) -> 0 | CP28: =IF(CP$3=1,-Inputs!C86,0) -> 0 | CQ28: =IF(CQ$3=1,-Inputs!C86,0) -> 0 | CR28: =IF(CR$3=1,-Inputs!C86,0) -> 0 | CS28: =IF(CS$3=1,-Inputs!C86,0) -> 0 | CT28: =IF(CT$3=1,-Inputs!C86,0) -> 0 | CU28: =IF(CU$3=1,-Inputs!C86,0) -> 0 | CV28: =IF(CV$3=1,-Inputs!C86,0) -> 0 | CW28: =IF(CW$3=1,-Inputs!C86,0) -> 0 | CX28: =IF(CX$3=1,-Inputs!C86,0) -> 0 | CY28: =IF(CY$3=1,-Inputs!C86,0) -> 0 | CZ28: =IF(CZ$3=1,-Inputs!C86,0) -> 0 | DA28: =IF(DA$3=1,-Inputs!C86,0) -> 0 | DB28: =IF(DB$3=1,-Inputs!C86,0) -> 0 | DC28: =IF(DC$3=1,-Inputs!C86,0) -> 0 | DD28: =IF(DD$3=1,-Inputs!C86,0) -> 0 | DE28: =IF(DE$3=1,-Inputs!C86,0) -> 0 | DF28: =IF(DF$3=1,-Inputs!C86,0) -> 0 | DG28: =IF(DG$3=1,-Inputs!C86,0) -> 0 | DH28: =IF(DH$3=1,-Inputs!C86,0) -> 0 | DI28: =IF(DI$3=1,-Inputs!C86,0) -> 0 | DJ28: =IF(DJ$3=1,-Inputs!C86,0) -> 0 | DK28: =IF(DK$3=1,-Inputs!C86,0) -> 0 | DL28: =IF(DL$3=1,-Inputs!C86,0) -> 0 | DM28: =IF(DM$3=1,-Inputs!C86,0) -> 0 | DN28: =IF(DN$3=1,-Inputs!C86,0) -> 0 | DO28: =IF(DO$3=1,-Inputs!C86,0) -> 0 | DP28: =IF(DP$3=1,-Inputs!C86,0) -> 0 | DQ28: =IF(DQ$3=1,-Inputs!C86,0) -> 0 | DR28: =IF(DR$3=1,-Inputs!C86,0) -> 0 | DS28: =IF(DS$3=1,-Inputs!C86,0) -> 0
B29: Acquisition Fee | C29: {=IF(C$3=1,-INDEX(Inputs!$C:$C,MATCH("*Purchase Price*",Inputs!$B:$B,0))*Inputs!C93,0)} -> 0 | D29: {=IF(D$3=1,-INDEX(Inputs!$C:$C,MATCH("*Purchase Price*",Inputs!$B:$B,0))*Inputs!C93,0)} -> 0 | E29: {=IF(E$3=1,-INDEX(Inputs!$C:$C,MATCH("*Purchase Price*",Inputs!$B:$B,0))*Inputs!C93,0)} -> 0 | F29: {=IF(F$3=1,-INDEX(Inputs!$C:$C,MATCH("*Purchase Price*",Inputs!$B:$B,0))*Inputs!C93,0)} -> 0 | G29: {=IF(G$3=1,-INDEX(Inputs!$C:$C,MATCH("*Purchase Price*",Inputs!$B:$B,0))*Inputs!C93,0)} -> 0 | H29: {=IF(H$3=1,-INDEX(Inputs!$C:$C,MATCH("*Purchase Price*",Inputs!$B:$B,0))*Inputs!C93,0)} -> 0 | I29: {=IF(I$3=1,-INDEX(Inputs!$C:$C,MATCH("*Purchase Price*",Inputs!$B:$B,0))*Inputs!C93,0)} -> 0 | J29: {=IF(J$3=1,-INDEX(Inputs!$C:$C,MATCH("*Purchase Price*",Inputs!$B:$B,0))*Inputs!C93,0)} -> 0 | K29: {=IF(K$3=1,-INDEX(Inputs!$C:$C,MATCH("*Purchase Price*",Inputs!$B:$B,0))*Inputs!C93,0)} -> 0 | L29: {=IF(L$3=1,-INDEX(Inputs!$C:$C,MATCH("*Purchase Price*",Inputs!$B:$B,0))*Inputs!C93,0)} -> 0 | M29: {=IF(M$3=1,-INDEX(Inputs!$C:$C,MATCH("*Purchase Price*",Inputs!$B:$B,0))*Inputs!C93,0)} -> 0 | N29: {=IF(N$3=1,-INDEX(Inputs!$C:$C,MATCH("*Purchase Price*",Inputs!$B:$B,0))*Inputs!C93,0)} -> 0 | O29: {=IF(O$3=1,-INDEX(Inputs!$C:$C,MATCH("*Purchase Price*",Inputs!$B:$B,0))*Inputs!C93,0)} -> 0 | P29: {=IF(P$3=1,-INDEX(Inputs!$C:$C,MATCH("*Purchase Price*",Inputs!$B:$B,0))*Inputs!C93,0)} -> 0 | Q29: {=IF(Q$3=1,-INDEX(Inputs!$C:$C,MATCH("*Purchase Price*",Inputs!$B:$B,0))*Inputs!C93,0)} -> 0 | R29: {=IF(R$3=1,-INDEX(Inputs!$C:$C,MATCH("*Purchase Price*",Inputs!$B:$B,0))*Inputs!C93,0)} -> 0 | S29: {=IF(S$3=1,-INDEX(Inputs!$C:$C,MATCH("*Purchase Price*",Inputs!$B:$B,0))*Inputs!C93,0)} -> 0 | T29: {=IF(T$3=1,-INDEX(Inputs!$C:$C,MATCH("*Purchase Price*",Inputs!$B:$B,0))*Inputs!C93,0)} -> 0 | U29: {=IF(U$3=1,-INDEX(Inputs!$C:$C,MATCH("*Purchase Price*",Inputs!$B:$B,0))*Inputs!C93,0)} -> 0 | V29: {=IF(V$3=1,-INDEX(Inputs!$C:$C,MATCH("*Purchase Price*",Inputs!$B:$B,0))*Inputs!C93,0)} -> 0 | W29: {=IF(W$3=1,-INDEX(Inputs!$C:$C,MATCH("*Purchase Price*",Inputs!$B:$B,0))*Inputs!C93,0)} -> 0 | X29: {=IF(X$3=1,-INDEX(Inputs!$C:$C,MATCH("*Purchase Price*",Inputs!$B:$B,0))*Inputs!C93,0)} -> 0 | Y29: {=IF(Y$3=1,-INDEX(Inputs!$C:$C,MATCH("*Purchase Price*",Inputs!$B:$B,0))*Inputs!C93,0)} -> 0 | Z29: {=IF(Z$3=1,-INDEX(Inputs!$C:$C,MATCH("*Purchase Price*",Inputs!$B:$B,0))*Inputs!C93,0)} -> 0 | AA29: {=IF(AA$3=1,-INDEX(Inputs!$C:$C,MATCH("*Purchase Price*",Inputs!$B:$B,0))*Inputs!C93,0)} -> 0 | AB29: {=IF(AB$3=1,-INDEX(Inputs!$C:$C,MATCH("*Purchase Price*",Inputs!$B:$B,0))*Inputs!C93,0)} -> 0 | AC29: {=IF(AC$3=1,-INDEX(Inputs!$C:$C,MATCH("*Purchase Price*",Inputs!$B:$B,0))*Inputs!C93,0)} -> 0 | AD29: {=IF(AD$3=1,-INDEX(Inputs!$C:$C,MATCH("*Purchase Price*",Inputs!$B:$B,0))*Inputs!C93,0)} -> 0 | AE29: {=IF(AE$3=1,-INDEX(Inputs!$C:$C,MATCH("*Purchase Price*",Inputs!$B:$B,0))*Inputs!C93,0)} -> 0 | AF29: {=IF(AF$3=1,-INDEX(Inputs!$C:$C,MATCH("*Purchase Price*",Inputs!$B:$B,0))*Inputs!C93,0)} -> 0 | AG29: {=IF(AG$3=1,-INDEX(Inputs!$C:$C,MATCH("*Purchase Price*",Inputs!$B:$B,0))*Inputs!C93,0)} -> 0 | AH29: {=IF(AH$3=1,-INDEX(Inputs!$C:$C,MATCH("*Purchase Price*",Inputs!$B:$B,0))*Inputs!C93,0)} -> 0 | AI29: {=IF(AI$3=1,-INDEX(Inputs!$C:$C,MATCH("*Purchase Price*",Inputs!$B:$B,0))*Inputs!C93,0)} -> 0 | AJ29: {=IF(AJ$3=1,-INDEX(Inputs!$C:$C,MATCH("*Purchase Price*",Inputs!$B:$B,0))*Inputs!C93,0)} -> 0 | AK29: {=IF(AK$3=1,-INDEX(Inputs!$C:$C,MATCH("*Purchase Price*",Inputs!$B:$B,0))*Inputs!C93,0)} -> 0 | AL29: {=IF(AL$3=1,-INDEX(Inputs!$C:$C,MATCH("*Purchase Price*",Inputs!$B:$B,0))*Inputs!C93,0)} -> 0 | AM29: {=IF(AM$3=1,-INDEX(Inputs!$C:$C,MATCH("*Purchase Price*",Inputs!$B:$B,0))*Inputs!C93,0)} -> 0 | AN29: {=IF(AN$3=1,-INDEX(Inputs!$C:$C,MATCH("*Purchase Price*",Inputs!$B:$B,0))*Inputs!C93,0)} -> 0 | AO29: {=IF(AO$3=1,-INDEX(Inputs!$C:$C,MATCH("*Purchase Price*",Inputs!$B:$B,0))*Inputs!C93,0)} -> 0 | AP29: {=IF(AP$3=1,-INDEX(Inputs!$C:$C,MATCH("*Purchase Price*",Inputs!$B:$B,0))*Inputs!C93,0)} -> 0 | AQ29: {=IF(AQ$3=1,-INDEX(Inputs!$C:$C,MATCH("*Purchase Price*",Inputs!$B:$B,0))*Inputs!C93,0)} -> 0 | AR29: {=IF(AR$3=1,-INDEX(Inputs!$C:$C,MATCH("*Purchase Price*",Inputs!$B:$B,0))*Inputs!C93,0)} -> 0 | AS29: {=IF(AS$3=1,-INDEX(Inputs!$C:$C,MATCH("*Purchase Price*",Inputs!$B:$B,0))*Inputs!C93,0)} -> 0 | AT29: {=IF(AT$3=1,-INDEX(Inputs!$C:$C,MATCH("*Purchase Price*",Inputs!$B:$B,0))*Inputs!C93,0)} -> 0 | AU29: {=IF(AU$3=1,-INDEX(Inputs!$C:$C,MATCH("*Purchase Price*",Inputs!$B:$B,0))*Inputs!C93,0)} -> 0 | AV29: {=IF(AV$3=1,-INDEX(Inputs!$C:$C,MATCH("*Purchase Price*",Inputs!$B:$B,0))*Inputs!C93,0)} -> 0 | AW29: {=IF(AW$3=1,-INDEX(Inputs!$C:$C,MATCH("*Purchase Price*",Inputs!$B:$B,0))*Inputs!C93,0)} -> 0 | AX29: {=IF(AX$3=1,-INDEX(Inputs!$C:$C,MATCH("*Purchase Price*",Inputs!$B:$B,0))*Inputs!C93,0)} -> 0 | AY29: {=IF(AY$3=1,-INDEX(Inputs!$C:$C,MATCH("*Purchase Price*",Inputs!$B:$B,0))*Inputs!C93,0)} -> 0 | AZ29: {=IF(AZ$3=1,-INDEX(Inputs!$C:$C,MATCH("*Purchase Price*",Inputs!$B:$B,0))*Inputs!C93,0)} -> 0 | BA29: {=IF(BA$3=1,-INDEX(Inputs!$C:$C,MATCH("*Purchase Price*",Inputs!$B:$B,0))*Inputs!C93,0)} -> 0 | BB29: {=IF(BB$3=1,-INDEX(Inputs!$C:$C,MATCH("*Purchase Price*",Inputs!$B:$B,0))*Inputs!C93,0)} -> 0 | BC29: {=IF(BC$3=1,-INDEX(Inputs!$C:$C,MATCH("*Purchase Price*",Inputs!$B:$B,0))*Inputs!C93,0)} -> 0 | BD29: {=IF(BD$3=1,-INDEX(Inputs!$C:$C,MATCH("*Purchase Price*",Inputs!$B:$B,0))*Inputs!C93,0)} -> 0 | BE29: {=IF(BE$3=1,-INDEX(Inputs!$C:$C,MATCH("*Purchase Price*",Inputs!$B:$B,0))*Inputs!C93,0)} -> 0 | BF29: {=IF(BF$3=1,-INDEX(Inputs!$C:$C,MATCH("*Purchase Price*",Inputs!$B:$B,0))*Inputs!C93,0)} -> 0 | BG29: {=IF(BG$3=1,-INDEX(Inputs!$C:$C,MATCH("*Purchase Price*",Inputs!$B:$B,0))*Inputs!C93,0)} -> 0 | BH29: {=IF(BH$3=1,-INDEX(Inputs!$C:$C,MATCH("*Purchase Price*",Inputs!$B:$B,0))*Inputs!C93,0)} -> 0 | BI29: {=IF(BI$3=1,-INDEX(Inputs!$C:$C,MATCH("*Purchase Price*",Inputs!$B:$B,0))*Inputs!C93,0)} -> 0 | BJ29: {=IF(BJ$3=1,-INDEX(Inputs!$C:$C,MATCH("*Purchase Price*",Inputs!$B:$B,0))*Inputs!C93,0)} -> 0 | BK29: {=IF(BK$3=1,-INDEX(Inputs!$C:$C,MATCH("*Purchase Price*",Inputs!$B:$B,0))*Inputs!C93,0)} -> 0 | BL29: {=IF(BL$3=1,-INDEX(Inputs!$C:$C,MATCH("*Purchase Price*",Inputs!$B:$B,0))*Inputs!C93,0)} -> 0 | BM29: {=IF(BM$3=1,-INDEX(Inputs!$C:$C,MATCH("*Purchase Price*",Inputs!$B:$B,0))*Inputs!C93,0)} -> 0 | BN29: {=IF(BN$3=1,-INDEX(Inputs!$C:$C,MATCH("*Purchase Price*",Inputs!$B:$B,0))*Inputs!C93,0)} -> 0 | BO29: {=IF(BO$3=1,-INDEX(Inputs!$C:$C,MATCH("*Purchase Price*",Inputs!$B:$B,0))*Inputs!C93,0)} -> 0 | BP29: {=IF(BP$3=1,-INDEX(Inputs!$C:$C,MATCH("*Purchase Price*",Inputs!$B:$B,0))*Inputs!C93,0)} -> 0 | BQ29: {=IF(BQ$3=1,-INDEX(Inputs!$C:$C,MATCH("*Purchase Price*",Inputs!$B:$B,0))*Inputs!C93,0)} -> 0 | BR29: {=IF(BR$3=1,-INDEX(Inputs!$C:$C,MATCH("*Purchase Price*",Inputs!$B:$B,0))*Inputs!C93,0)} -> 0 | BS29: {=IF(BS$3=1,-INDEX(Inputs!$C:$C,MATCH("*Purchase Price*",Inputs!$B:$B,0))*Inputs!C93,0)} -> 0 | BT29: {=IF(BT$3=1,-INDEX(Inputs!$C:$C,MATCH("*Purchase Price*",Inputs!$B:$B,0))*Inputs!C93,0)} -> 0 | BU29: {=IF(BU$3=1,-INDEX(Inputs!$C:$C,MATCH("*Purchase Price*",Inputs!$B:$B,0))*Inputs!C93,0)} -> 0 | BV29: {=IF(BV$3=1,-INDEX(Inputs!$C:$C,MATCH("*Purchase Price*",Inputs!$B:$B,0))*Inputs!C93,0)} -> 0 | BW29: {=IF(BW$3=1,-INDEX(Inputs!$C:$C,MATCH("*Purchase Price*",Inputs!$B:$B,0))*Inputs!C93,0)} -> 0 | BX29: {=IF(BX$3=1,-INDEX(Inputs!$C:$C,MATCH("*Purchase Price*",Inputs!$B:$B,0))*Inputs!C93,0)} -> 0 | BY29: {=IF(BY$3=1,-INDEX(Inputs!$C:$C,MATCH("*Purchase Price*",Inputs!$B:$B,0))*Inputs!C93,0)} -> 0 | BZ29: {=IF(BZ$3=1,-INDEX(Inputs!$C:$C,MATCH("*Purchase Price*",Inputs!$B:$B,0))*Inputs!C93,0)} -> 0 | CA29: {=IF(CA$3=1,-INDEX(Inputs!$C:$C,MATCH("*Purchase Price*",Inputs!$B:$B,0))*Inputs!C93,0)} -> 0 | CB29: {=IF(CB$3=1,-INDEX(Inputs!$C:$C,MATCH("*Purchase Price*",Inputs!$B:$B,0))*Inputs!C93,0)} -> 0 | CC29: {=IF(CC$3=1,-INDEX(Inputs!$C:$C,MATCH("*Purchase Price*",Inputs!$B:$B,0))*Inputs!C93,0)} -> 0 | CD29: {=IF(CD$3=1,-INDEX(Inputs!$C:$C,MATCH("*Purchase Price*",Inputs!$B:$B,0))*Inputs!C93,0)} -> 0 | CE29: {=IF(CE$3=1,-INDEX(Inputs!$C:$C,MATCH("*Purchase Price*",Inputs!$B:$B,0))*Inputs!C93,0)} -> 0 | CF29: {=IF(CF$3=1,-INDEX(Inputs!$C:$C,MATCH("*Purchase Price*",Inputs!$B:$B,0))*Inputs!C93,0)} -> 0 | CG29: {=IF(CG$3=1,-INDEX(Inputs!$C:$C,MATCH("*Purchase Price*",Inputs!$B:$B,0))*Inputs!C93,0)} -> 0 | CH29: {=IF(CH$3=1,-INDEX(Inputs!$C:$C,MATCH("*Purchase Price*",Inputs!$B:$B,0))*Inputs!C93,0)} -> 0 | CI29: {=IF(CI$3=1,-INDEX(Inputs!$C:$C,MATCH("*Purchase Price*",Inputs!$B:$B,0))*Inputs!C93,0)} -> 0 | CJ29: {=IF(CJ$3=1,-INDEX(Inputs!$C:$C,MATCH("*Purchase Price*",Inputs!$B:$B,0))*Inputs!C93,0)} -> 0 | CK29: {=IF(CK$3=1,-INDEX(Inputs!$C:$C,MATCH("*Purchase Price*",Inputs!$B:$B,0))*Inputs!C93,0)} -> 0 | CL29: {=IF(CL$3=1,-INDEX(Inputs!$C:$C,MATCH("*Purchase Price*",Inputs!$B:$B,0))*Inputs!C93,0)} -> 0 | CM29: {=IF(CM$3=1,-INDEX(Inputs!$C:$C,MATCH("*Purchase Price*",Inputs!$B:$B,0))*Inputs!C93,0)} -> 0 | CN29: {=IF(CN$3=1,-INDEX(Inputs!$C:$C,MATCH("*Purchase Price*",Inputs!$B:$B,0))*Inputs!C93,0)} -> 0 | CO29: {=IF(CO$3=1,-INDEX(Inputs!$C:$C,MATCH("*Purchase Price*",Inputs!$B:$B,0))*Inputs!C93,0)} -> 0 | CP29: {=IF(CP$3=1,-INDEX(Inputs!$C:$C,MATCH("*Purchase Price*",Inputs!$B:$B,0))*Inputs!C93,0)} -> 0 | CQ29: {=IF(CQ$3=1,-INDEX(Inputs!$C:$C,MATCH("*Purchase Price*",Inputs!$B:$B,0))*Inputs!C93,0)} -> 0 | CR29: {=IF(CR$3=1,-INDEX(Inputs!$C:$C,MATCH("*Purchase Price*",Inputs!$B:$B,0))*Inputs!C93,0)} -> 0 | CS29: {=IF(CS$3=1,-INDEX(Inputs!$C:$C,MATCH("*Purchase Price*",Inputs!$B:$B,0))*Inputs!C93,0)} -> 0 | CT29: {=IF(CT$3=1,-INDEX(Inputs!$C:$C,MATCH("*Purchase Price*",Inputs!$B:$B,0))*Inputs!C93,0)} -> 0 | CU29: {=IF(CU$3=1,-INDEX(Inputs!$C:$C,MATCH("*Purchase Price*",Inputs!$B:$B,0))*Inputs!C93,0)} -> 0 | CV29: {=IF(CV$3=1,-INDEX(Inputs!$C:$C,MATCH("*Purchase Price*",Inputs!$B:$B,0))*Inputs!C93,0)} -> 0 | CW29: {=IF(CW$3=1,-INDEX(Inputs!$C:$C,MATCH("*Purchase Price*",Inputs!$B:$B,0))*Inputs!C93,0)} -> 0 | CX29: {=IF(CX$3=1,-INDEX(Inputs!$C:$C,MATCH("*Purchase Price*",Inputs!$B:$B,0))*Inputs!C93,0)} -> 0 | CY29: {=IF(CY$3=1,-INDEX(Inputs!$C:$C,MATCH("*Purchase Price*",Inputs!$B:$B,0))*Inputs!C93,0)} -> 0 | CZ29: {=IF(CZ$3=1,-INDEX(Inputs!$C:$C,MATCH("*Purchase Price*",Inputs!$B:$B,0))*Inputs!C93,0)} -> 0 | DA29: {=IF(DA$3=1,-INDEX(Inputs!$C:$C,MATCH("*Purchase Price*",Inputs!$B:$B,0))*Inputs!C93,0)} -> 0 | DB29: {=IF(DB$3=1,-INDEX(Inputs!$C:$C,MATCH("*Purchase Price*",Inputs!$B:$B,0))*Inputs!C93,0)} -> 0 | DC29: {=IF(DC$3=1,-INDEX(Inputs!$C:$C,MATCH("*Purchase Price*",Inputs!$B:$B,0))*Inputs!C93,0)} -> 0 | DD29: {=IF(DD$3=1,-INDEX(Inputs!$C:$C,MATCH("*Purchase Price*",Inputs!$B:$B,0))*Inputs!C93,0)} -> 0 | DE29: {=IF(DE$3=1,-INDEX(Inputs!$C:$C,MATCH("*Purchase Price*",Inputs!$B:$B,0))*Inputs!C93,0)} -> 0 | DF29: {=IF(DF$3=1,-INDEX(Inputs!$C:$C,MATCH("*Purchase Price*",Inputs!$B:$B,0))*Inputs!C93,0)} -> 0 | DG29: {=IF(DG$3=1,-INDEX(Inputs!$C:$C,MATCH("*Purchase Price*",Inputs!$B:$B,0))*Inputs!C93,0)} -> 0 | DH29: {=IF(DH$3=1,-INDEX(Inputs!$C:$C,MATCH("*Purchase Price*",Inputs!$B:$B,0))*Inputs!C93,0)} -> 0 | DI29: {=IF(DI$3=1,-INDEX(Inputs!$C:$C,MATCH("*Purchase Price*",Inputs!$B:$B,0))*Inputs!C93,0)} -> 0 | DJ29: {=IF(DJ$3=1,-INDEX(Inputs!$C:$C,MATCH("*Purchase Price*",Inputs!$B:$B,0))*Inputs!C93,0)} -> 0 | DK29: {=IF(DK$3=1,-INDEX(Inputs!$C:$C,MATCH("*Purchase Price*",Inputs!$B:$B,0))*Inputs!C93,0)} -> 0 | DL29: {=IF(DL$3=1,-INDEX(Inputs!$C:$C,MATCH("*Purchase Price*",Inputs!$B:$B,0))*Inputs!C93,0)} -> 0 | DM29: {=IF(DM$3=1,-INDEX(Inputs!$C:$C,MATCH("*Purchase Price*",Inputs!$B:$B,0))*Inputs!C93,0)} -> 0 | DN29: {=IF(DN$3=1,-INDEX(Inputs!$C:$C,MATCH("*Purchase Price*",Inputs!$B:$B,0))*Inputs!C93,0)} -> 0 | DO29: {=IF(DO$3=1,-INDEX(Inputs!$C:$C,MATCH("*Purchase Price*",Inputs!$B:$B,0))*Inputs!C93,0)} -> 0 | DP29: {=IF(DP$3=1,-INDEX(Inputs!$C:$C,MATCH("*Purchase Price*",Inputs!$B:$B,0))*Inputs!C93,0)} -> 0 | DQ29: {=IF(DQ$3=1,-INDEX(Inputs!$C:$C,MATCH("*Purchase Price*",Inputs!$B:$B,0))*Inputs!C93,0)} -> 0 | DR29: {=IF(DR$3=1,-INDEX(Inputs!$C:$C,MATCH("*Purchase Price*",Inputs!$B:$B,0))*Inputs!C93,0)} -> 0 | DS29: {=IF(DS$3=1,-INDEX(Inputs!$C:$C,MATCH("*Purchase Price*",Inputs!$B:$B,0))*Inputs!C93,0)} -> 0
B30: Due Diligence Costs | C30: {=IF(C$3=1,-INDEX(Inputs!$D:$D,MATCH("*Due Diligence Costs*",Inputs!$B:$B,0)),0)} -> 0 | D30: 0 | E30: 0 | F30: 0 | G30: 0 | H30: 0 | I30: 0 | J30: 0 | K30: 0 | L30: 0 | M30: 0 | N30: 0 | O30: 0 | P30: 0 | Q30: 0 | R30: 0 | S30: 0 | T30: 0 | U30: 0 | V30: 0 | W30: 0 | X30: 0 | Y30: 0 | Z30: 0 | AA30: 0 | AB30: 0 | AC30: 0 | AD30: 0 | AE30: 0 | AF30: 0 | AG30: 0 | AH30: 0 | AI30: 0 | AJ30: 0 | AK30: 0 | AL30: 0 | AM30: 0 | AN30: 0 | AO30: 0 | AP30: 0 | AQ30: 0 | AR30: 0 | AS30: 0 | AT30: 0 | AU30: 0 | AV30: 0 | AW30: 0 | AX30: 0 | AY30: 0 | AZ30: 0 | BA30: 0 | BB30: 0 | BC30: 0 | BD30: 0 | BE30: 0 | BF30: 0 | BG30: 0 | BH30: 0 | BI30: 0 | BJ30: 0 | BK30: 0 | BL30: 0 | BM30: 0 | BN30: 0 | BO30: 0 | BP30: 0 | BQ30: 0 | BR30: 0 | BS30: 0 | BT30: 0 | BU30: 0 | BV30: 0 | BW30: 0 | BX30: 0 | BY30: 0 | BZ30: 0 | CA30: 0 | CB30: 0 | CC30: 0 | CD30: 0 | CE30: 0 | CF30: 0 | CG30: 0 | CH30: 0 | CI30: 0 | CJ30: 0 | CK30: 0 | CL30: 0 | CM30: 0 | CN30: 0 | CO30: 0 | CP30: 0 | CQ30: 0 | CR30: 0 | CS30: 0 | CT30: 0 | CU30: 0 | CV30: 0 | CW30: 0 | CX30: 0 | CY30: 0 | CZ30: 0 | DA30: 0 | DB30: 0 | DC30: 0 | DD30: 0 | DE30: 0 | DF30: 0 | DG30: 0 | DH30: 0 | DI30: 0 | DJ30: 0 | DK30: 0 | DL30: 0 | DM30: 0 | DN30: 0 | DO30: 0 | DP30: 0 | DQ30: 0 | DR30: 0 | DS30: 0
B31: Loan Origination Costs | C31: {=IF(C$3=1,-INDEX(Inputs!$D:$D,MATCH("*Loan Origination Costs*",Inputs!$B:$B,0)),0)} -> 0 | D31: 0 | E31: 0 | F31: 0 | G31: 0 | H31: 0 | I31: 0 | J31: 0 | K31: 0 | L31: 0 | M31: 0 | N31: 0 | O31: 0 | P31: 0 | Q31: 0 | R31: 0 | S31: 0 | T31: 0 | U31: 0 | V31: 0 | W31: 0 | X31: 0 | Y31: 0 | Z31: 0 | AA31: 0 | AB31: 0 | AC31: 0 | AD31: 0 | AE31: 0 | AF31: 0 | AG31: 0 | AH31: 0 | AI31: 0 | AJ31: 0 | AK31: 0 | AL31: 0 | AM31: 0 | AN31: 0 | AO31: 0 | AP31: 0 | AQ31: 0 | AR31: 0 | AS31: 0 | AT31: 0 | AU31: 0 | AV31: 0 | AW31: 0 | AX31: 0 | AY31: 0 | AZ31: 0 | BA31: 0 | BB31: 0 | BC31: 0 | BD31: 0 | BE31: 0 | BF31: 0 | BG31: 0 | BH31: 0 | BI31: 0 | BJ31: 0 | BK31: 0 | BL31: 0 | BM31: 0 | BN31: 0 | BO31: 0 | BP31: 0 | BQ31: 0 | BR31: 0 | BS31: 0 | BT31: 0 | BU31: 0 | BV31: 0 | BW31: 0 | BX31: 0 | BY31: 0 | BZ31: 0 | CA31: 0 | CB31: 0 | CC31: 0 | CD31: 0 | CE31: 0 | CF31: 0 | CG31: 0 | CH31: 0 | CI31: 0 | CJ31: 0 | CK31: 0 | CL31: 0 | CM31: 0 | CN31: 0 | CO31: 0 | CP31: 0 | CQ31: 0 | CR31: 0 | CS31: 0 | CT31: 0 | CU31: 0 | CV31: 0 | CW31: 0 | CX31: 0 | CY31: 0 | CZ31: 0 | DA31: 0 | DB31: 0 | DC31: 0 | DD31: 0 | DE31: 0 | DF31: 0 | DG31: 0 | DH31: 0 | DI31: 0 | DJ31: 0 | DK31: 0 | DL31: 0 | DM31: 0 | DN31: 0 | DO31: 0 | DP31: 0 | DQ31: 0 | DR31: 0 | DS31: 0
B32: TOTAL ACQUISITION COSTS | C32: =SUM(C26:C31) -> -5000 | D32: =SUM(D26:D31) -> 0 | E32: =SUM(E26:E31) -> 0 | F32: =SUM(F26:F31) -> 0 | G32: =SUM(G26:G31) -> 0 | H32: =SUM(H26:H31) -> 0 | I32: =SUM(I26:I31) -> 0 | J32: =SUM(J26:J31) -> 0 | ... DS32: =SUM(DS26:DS31) -> 0
B34: DISPOSITION / EXIT
B35: Sale Proceeds | C35: {=IF(C$3=INDEX(Inputs!$C:$C,MATCH("End Year",Inputs!$B:$B,0))*12,Inputs!C101,0)} -> 0 | D35: {=IF(D$3=INDEX(Inputs!$C:$C,MATCH("End Year",Inputs!$B:$B,0))*12,Inputs!C101,0)} -> 0 | E35: {=IF(E$3=INDEX(Inputs!$C:$C,MATCH("End Year",Inputs!$B:$B,0))*12,Inputs!C101,0)} -> 0 | F35: {=IF(F$3=INDEX(Inputs!$C:$C,MATCH("End Year",Inputs!$B:$B,0))*12,Inputs!C101,0)} -> 0 | G35: {=IF(G$3=INDEX(Inputs!$C:$C,MATCH("End Year",Inputs!$B:$B,0))*12,Inputs!C101,0)} -> 0 | H35: {=IF(H$3=INDEX(Inputs!$C:$C,MATCH("End Year",Inputs!$B:$B,0))*12,Inputs!C101,0)} -> 0 | I35: {=IF(I$3=INDEX(Inputs!$C:$C,MATCH("End Year",Inputs!$B:$B,0))*12,Inputs!C101,0)} -> 0 | J35: {=IF(J$3=INDEX(Inputs!$C:$C,MATCH("End Year",Inputs!$B:$B,0))*12,Inputs!C101,0)} -> 0 | K35: {=IF(K$3=INDEX(Inputs!$C:$C,MATCH("End Year",Inputs!$B:$B,0))*12,Inputs!C101,0)} -> 0 | L35: {=IF(L$3=INDEX(Inputs!$C:$C,MATCH("End Year",Inputs!$B:$B,0))*12,Inputs!C101,0)} -> 0 | M35: {=IF(M$3=INDEX(Inputs!$C:$C,MATCH("End Year",Inputs!$B:$B,0))*12,Inputs!C101,0)} -> 0 | N35: {=IF(N$3=INDEX(Inputs!$C:$C,MATCH("End Year",Inputs!$B:$B,0))*12,Inputs!C101,0)} -> 0 | O35: {=IF(O$3=INDEX(Inputs!$C:$C,MATCH("End Year",Inputs!$B:$B,0))*12,Inputs!C101,0)} -> 0 | P35: {=IF(P$3=INDEX(Inputs!$C:$C,MATCH("End Year",Inputs!$B:$B,0))*12,Inputs!C101,0)} -> 0 | Q35: {=IF(Q$3=INDEX(Inputs!$C:$C,MATCH("End Year",Inputs!$B:$B,0))*12,Inputs!C101,0)} -> 0 | R35: {=IF(R$3=INDEX(Inputs!$C:$C,MATCH("End Year",Inputs!$B:$B,0))*12,Inputs!C101,0)} -> 0 | S35: {=IF(S$3=INDEX(Inputs!$C:$C,MATCH("End Year",Inputs!$B:$B,0))*12,Inputs!C101,0)} -> 0 | T35: {=IF(T$3=INDEX(Inputs!$C:$C,MATCH("End Year",Inputs!$B:$B,0))*12,Inputs!C101,0)} -> 0 | U35: {=IF(U$3=INDEX(Inputs!$C:$C,MATCH("End Year",Inputs!$B:$B,0))*12,Inputs!C101,0)} -> 0 | V35: {=IF(V$3=INDEX(Inputs!$C:$C,MATCH("End Year",Inputs!$B:$B,0))*12,Inputs!C101,0)} -> 0 | W35: {=IF(W$3=INDEX(Inputs!$C:$C,MATCH("End Year",Inputs!$B:$B,0))*12,Inputs!C101,0)} -> 0 | X35: {=IF(X$3=INDEX(Inputs!$C:$C,MATCH("End Year",Inputs!$B:$B,0))*12,Inputs!C101,0)} -> 0 | Y35: {=IF(Y$3=INDEX(Inputs!$C:$C,MATCH("End Year",Inputs!$B:$B,0))*12,Inputs!C101,0)} -> 0 | Z35: {=IF(Z$3=INDEX(Inputs!$C:$C,MATCH("End Year",Inputs!$B:$B,0))*12,Inputs!C101,0)} -> 0 | AA35: {=IF(AA$3=INDEX(Inputs!$C:$C,MATCH("End Year",Inputs!$B:$B,0))*12,Inputs!C101,0)} -> 0 | AB35: {=IF(AB$3=INDEX(Inputs!$C:$C,MATCH("End Year",Inputs!$B:$B,0))*12,Inputs!C101,0)} -> 0 | AC35: {=IF(AC$3=INDEX(Inputs!$C:$C,MATCH("End Year",Inputs!$B:$B,0))*12,Inputs!C101,0)} -> 0 | AD35: {=IF(AD$3=INDEX(Inputs!$C:$C,MATCH("End Year",Inputs!$B:$B,0))*12,Inputs!C101,0)} -> 0 | AE35: {=IF(AE$3=INDEX(Inputs!$C:$C,MATCH("End Year",Inputs!$B:$B,0))*12,Inputs!C101,0)} -> 0 | AF35: {=IF(AF$3=INDEX(Inputs!$C:$C,MATCH("End Year",Inputs!$B:$B,0))*12,Inputs!C101,0)} -> 0 | AG35: {=IF(AG$3=INDEX(Inputs!$C:$C,MATCH("End Year",Inputs!$B:$B,0))*12,Inputs!C101,0)} -> 0 | AH35: {=IF(AH$3=INDEX(Inputs!$C:$C,MATCH("End Year",Inputs!$B:$B,0))*12,Inputs!C101,0)} -> 0 | AI35: {=IF(AI$3=INDEX(Inputs!$C:$C,MATCH("End Year",Inputs!$B:$B,0))*12,Inputs!C101,0)} -> 0 | AJ35: {=IF(AJ$3=INDEX(Inputs!$C:$C,MATCH("End Year",Inputs!$B:$B,0))*12,Inputs!C101,0)} -> 0 | AK35: {=IF(AK$3=INDEX(Inputs!$C:$C,MATCH("End Year",Inputs!$B:$B,0))*12,Inputs!C101,0)} -> 0 | AL35: {=IF(AL$3=INDEX(Inputs!$C:$C,MATCH("End Year",Inputs!$B:$B,0))*12,Inputs!C101,0)} -> 0 | AM35: {=IF(AM$3=INDEX(Inputs!$C:$C,MATCH("End Year",Inputs!$B:$B,0))*12,Inputs!C101,0)} -> 0 | AN35: {=IF(AN$3=INDEX(Inputs!$C:$C,MATCH("End Year",Inputs!$B:$B,0))*12,Inputs!C101,0)} -> 0 | AO35: {=IF(AO$3=INDEX(Inputs!$C:$C,MATCH("End Year",Inputs!$B:$B,0))*12,Inputs!C101,0)} -> 0 | AP35: {=IF(AP$3=INDEX(Inputs!$C:$C,MATCH("End Year",Inputs!$B:$B,0))*12,Inputs!C101,0)} -> 0 | AQ35: {=IF(AQ$3=INDEX(Inputs!$C:$C,MATCH("End Year",Inputs!$B:$B,0))*12,Inputs!C101,0)} -> 0 | AR35: {=IF(AR$3=INDEX(Inputs!$C:$C,MATCH("End Year",Inputs!$B:$B,0))*12,Inputs!C101,0)} -> 0 | AS35: {=IF(AS$3=INDEX(Inputs!$C:$C,MATCH("End Year",Inputs!$B:$B,0))*12,Inputs!C101,0)} -> 0 | AT35: {=IF(AT$3=INDEX(Inputs!$C:$C,MATCH("End Year",Inputs!$B:$B,0))*12,Inputs!C101,0)} -> 0 | AU35: {=IF(AU$3=INDEX(Inputs!$C:$C,MATCH("End Year",Inputs!$B:$B,0))*12,Inputs!C101,0)} -> 0 | AV35: {=IF(AV$3=INDEX(Inputs!$C:$C,MATCH("End Year",Inputs!$B:$B,0))*12,Inputs!C101,0)} -> 0 | AW35: {=IF(AW$3=INDEX(Inputs!$C:$C,MATCH("End Year",Inputs!$B:$B,0))*12,Inputs!C101,0)} -> 0 | AX35: {=IF(AX$3=INDEX(Inputs!$C:$C,MATCH("End Year",Inputs!$B:$B,0))*12,Inputs!C101,0)} -> 0 | AY35: {=IF(AY$3=INDEX(Inputs!$C:$C,MATCH("End Year",Inputs!$B:$B,0))*12,Inputs!C101,0)} -> 0 | AZ35: {=IF(AZ$3=INDEX(Inputs!$C:$C,MATCH("End Year",Inputs!$B:$B,0))*12,Inputs!C101,0)} -> 0 | BA35: {=IF(BA$3=INDEX(Inputs!$C:$C,MATCH("End Year",Inputs!$B:$B,0))*12,Inputs!C101,0)} -> 0 | BB35: {=IF(BB$3=INDEX(Inputs!$C:$C,MATCH("End Year",Inputs!$B:$B,0))*12,Inputs!C101,0)} -> 0 | BC35: {=IF(BC$3=INDEX(Inputs!$C:$C,MATCH("End Year",Inputs!$B:$B,0))*12,Inputs!C101,0)} -> 0 | BD35: {=IF(BD$3=INDEX(Inputs!$C:$C,MATCH("End Year",Inputs!$B:$B,0))*12,Inputs!C101,0)} -> 0 | BE35: {=IF(BE$3=INDEX(Inputs!$C:$C,MATCH("End Year",Inputs!$B:$B,0))*12,Inputs!C101,0)} -> 0 | BF35: {=IF(BF$3=INDEX(Inputs!$C:$C,MATCH("End Year",Inputs!$B:$B,0))*12,Inputs!C101,0)} -> 0 | BG35: {=IF(BG$3=INDEX(Inputs!$C:$C,MATCH("End Year",Inputs!$B:$B,0))*12,Inputs!C101,0)} -> 0 | BH35: {=IF(BH$3=INDEX(Inputs!$C:$C,MATCH("End Year",Inputs!$B:$B,0))*12,Inputs!C101,0)} -> 0 | BI35: {=IF(BI$3=INDEX(Inputs!$C:$C,MATCH("End Year",Inputs!$B:$B,0))*12,Inputs!C101,0)} -> 0 | BJ35: {=IF(BJ$3=INDEX(Inputs!$C:$C,MATCH("End Year",Inputs!$B:$B,0))*12,Inputs!C101,0)} -> 0 | BK35: {=IF(BK$3=INDEX(Inputs!$C:$C,MATCH("End Year",Inputs!$B:$B,0))*12,Inputs!C101,0)} -> 0 | BL35: {=IF(BL$3=INDEX(Inputs!$C:$C,MATCH("End Year",Inputs!$B:$B,0))*12,Inputs!C101,0)} -> 0 | BM35: {=IF(BM$3=INDEX(Inputs!$C:$C,MATCH("End Year",Inputs!$B:$B,0))*12,Inputs!C101,0)} -> 0 | BN35: {=IF(BN$3=INDEX(Inputs!$C:$C,MATCH("End Year",Inputs!$B:$B,0))*12,Inputs!C101,0)} -> 0 | BO35: {=IF(BO$3=INDEX(Inputs!$C:$C,MATCH("End Year",Inputs!$B:$B,0))*12,Inputs!C101,0)} -> 0 | BP35: {=IF(BP$3=INDEX(Inputs!$C:$C,MATCH("End Year",Inputs!$B:$B,0))*12,Inputs!C101,0)} -> 0 | BQ35: {=IF(BQ$3=INDEX(Inputs!$C:$C,MATCH("End Year",Inputs!$B:$B,0))*12,Inputs!C101,0)} -> 0 | BR35: {=IF(BR$3=INDEX(Inputs!$C:$C,MATCH("End Year",Inputs!$B:$B,0))*12,Inputs!C101,0)} -> 0 | BS35: {=IF(BS$3=INDEX(Inputs!$C:$C,MATCH("End Year",Inputs!$B:$B,0))*12,Inputs!C101,0)} -> 0 | BT35: {=IF(BT$3=INDEX(Inputs!$C:$C,MATCH("End Year",Inputs!$B:$B,0))*12,Inputs!C101,0)} -> 0 | BU35: {=IF(BU$3=INDEX(Inputs!$C:$C,MATCH("End Year",Inputs!$B:$B,0))*12,Inputs!C101,0)} -> 0 | BV35: {=IF(BV$3=INDEX(Inputs!$C:$C,MATCH("End Year",Inputs!$B:$B,0))*12,Inputs!C101,0)} -> 0 | BW35: {=IF(BW$3=INDEX(Inputs!$C:$C,MATCH("End Year",Inputs!$B:$B,0))*12,Inputs!C101,0)} -> 0 | BX35: {=IF(BX$3=INDEX(Inputs!$C:$C,MATCH("End Year",Inputs!$B:$B,0))*12,Inputs!C101,0)} -> 0 | BY35: {=IF(BY$3=INDEX(Inputs!$C:$C,MATCH("End Year",Inputs!$B:$B,0))*12,Inputs!C101,0)} -> 0 | BZ35: {=IF(BZ$3=INDEX(Inputs!$C:$C,MATCH("End Year",Inputs!$B:$B,0))*12,Inputs!C101,0)} -> 0 | CA35: {=IF(CA$3=INDEX(Inputs!$C:$C,MATCH("End Year",Inputs!$B:$B,0))*12,Inputs!C101,0)} -> 0 | CB35: {=IF(CB$3=INDEX(Inputs!$C:$C,MATCH("End Year",Inputs!$B:$B,0))*12,Inputs!C101,0)} -> 0 | CC35: {=IF(CC$3=INDEX(Inputs!$C:$C,MATCH("End Year",Inputs!$B:$B,0))*12,Inputs!C101,0)} -> 0 | CD35: {=IF(CD$3=INDEX(Inputs!$C:$C,MATCH("End Year",Inputs!$B:$B,0))*12,Inputs!C101,0)} -> 0 | CE35: {=IF(CE$3=INDEX(Inputs!$C:$C,MATCH("End Year",Inputs!$B:$B,0))*12,Inputs!C101,0)} -> 0 | CF35: {=IF(CF$3=INDEX(Inputs!$C:$C,MATCH("End Year",Inputs!$B:$B,0))*12,Inputs!C101,0)} -> 0 | CG35: {=IF(CG$3=INDEX(Inputs!$C:$C,MATCH("End Year",Inputs!$B:$B,0))*12,Inputs!C101,0)} -> 0 | CH35: {=IF(CH$3=INDEX(Inputs!$C:$C,MATCH("End Year",Inputs!$B:$B,0))*12,Inputs!C101,0)} -> 0 | CI35: {=IF(CI$3=INDEX(Inputs!$C:$C,MATCH("End Year",Inputs!$B:$B,0))*12,Inputs!C101,0)} -> 0 | CJ35: {=IF(CJ$3=INDEX(Inputs!$C:$C,MATCH("End Year",Inputs!$B:$B,0))*12,Inputs!C101,0)} -> 0 | CK35: {=IF(CK$3=INDEX(Inputs!$C:$C,MATCH("End Year",Inputs!$B:$B,0))*12,Inputs!C101,0)} -> 0 | CL35: {=IF(CL$3=INDEX(Inputs!$C:$C,MATCH("End Year",Inputs!$B:$B,0))*12,Inputs!C101,0)} -> 0 | CM35: {=IF(CM$3=INDEX(Inputs!$C:$C,MATCH("End Year",Inputs!$B:$B,0))*12,Inputs!C101,0)} -> 0 | CN35: {=IF(CN$3=INDEX(Inputs!$C:$C,MATCH("End Year",Inputs!$B:$B,0))*12,Inputs!C101,0)} -> 0 | CO35: {=IF(CO$3=INDEX(Inputs!$C:$C,MATCH("End Year",Inputs!$B:$B,0))*12,Inputs!C101,0)} -> 0 | CP35: {=IF(CP$3=INDEX(Inputs!$C:$C,MATCH("End Year",Inputs!$B:$B,0))*12,Inputs!C101,0)} -> 0 | CQ35: {=IF(CQ$3=INDEX(Inputs!$C:$C,MATCH("End Year",Inputs!$B:$B,0))*12,Inputs!C101,0)} -> 0 | CR35: {=IF(CR$3=INDEX(Inputs!$C:$C,MATCH("End Year",Inputs!$B:$B,0))*12,Inputs!C101,0)} -> 0 | CS35: {=IF(CS$3=INDEX(Inputs!$C:$C,MATCH("End Year",Inputs!$B:$B,0))*12,Inputs!C101,0)} -> 0 | CT35: {=IF(CT$3=INDEX(Inputs!$C:$C,MATCH("End Year",Inputs!$B:$B,0))*12,Inputs!C101,0)} -> 0 | CU35: {=IF(CU$3=INDEX(Inputs!$C:$C,MATCH("End Year",Inputs!$B:$B,0))*12,Inputs!C101,0)} -> 0 | CV35: {=IF(CV$3=INDEX(Inputs!$C:$C,MATCH("End Year",Inputs!$B:$B,0))*12,Inputs!C101,0)} -> 0 | CW35: {=IF(CW$3=INDEX(Inputs!$C:$C,MATCH("End Year",Inputs!$B:$B,0))*12,Inputs!C101,0)} -> 0 | CX35: {=IF(CX$3=INDEX(Inputs!$C:$C,MATCH("End Year",Inputs!$B:$B,0))*12,Inputs!C101,0)} -> 0 | CY35: {=IF(CY$3=INDEX(Inputs!$C:$C,MATCH("End Year",Inputs!$B:$B,0))*12,Inputs!C101,0)} -> 0 | CZ35: {=IF(CZ$3=INDEX(Inputs!$C:$C,MATCH("End Year",Inputs!$B:$B,0))*12,Inputs!C101,0)} -> 0 | DA35: {=IF(DA$3=INDEX(Inputs!$C:$C,MATCH("End Year",Inputs!$B:$B,0))*12,Inputs!C101,0)} -> 0 | DB35: {=IF(DB$3=INDEX(Inputs!$C:$C,MATCH("End Year",Inputs!$B:$B,0))*12,Inputs!C101,0)} -> 0 | DC35: {=IF(DC$3=INDEX(Inputs!$C:$C,MATCH("End Year",Inputs!$B:$B,0))*12,Inputs!C101,0)} -> 0 | DD35: {=IF(DD$3=INDEX(Inputs!$C:$C,MATCH("End Year",Inputs!$B:$B,0))*12,Inputs!C101,0)} -> 0 | DE35: {=IF(DE$3=INDEX(Inputs!$C:$C,MATCH("End Year",Inputs!$B:$B,0))*12,Inputs!C101,0)} -> 0 | DF35: {=IF(DF$3=INDEX(Inputs!$C:$C,MATCH("End Year",Inputs!$B:$B,0))*12,Inputs!C101,0)} -> 0 | DG35: {=IF(DG$3=INDEX(Inputs!$C:$C,MATCH("End Year",Inputs!$B:$B,0))*12,Inputs!C101,0)} -> 0 | DH35: {=IF(DH$3=INDEX(Inputs!$C:$C,MATCH("End Year",Inputs!$B:$B,0))*12,Inputs!C101,0)} -> 0 | DI35: {=IF(DI$3=INDEX(Inputs!$C:$C,MATCH("End Year",Inputs!$B:$B,0))*12,Inputs!C101,0)} -> 0 | DJ35: {=IF(DJ$3=INDEX(Inputs!$C:$C,MATCH("End Year",Inputs!$B:$B,0))*12,Inputs!C101,0)} -> 0 | DK35: {=IF(DK$3=INDEX(Inputs!$C:$C,MATCH("End Year",Inputs!$B:$B,0))*12,Inputs!C101,0)} -> 0 | DL35: {=IF(DL$3=INDEX(Inputs!$C:$C,MATCH("End Year",Inputs!$B:$B,0))*12,Inputs!C101,0)} -> 0 | DM35: {=IF(DM$3=INDEX(Inputs!$C:$C,MATCH("End Year",Inputs!$B:$B,0))*12,Inputs!C101,0)} -> 0 | DN35: {=IF(DN$3=INDEX(Inputs!$C:$C,MATCH("End Year",Inputs!$B:$B,0))*12,Inputs!C101,0)} -> 0 | DO35: {=IF(DO$3=INDEX(Inputs!$C:$C,MATCH("End Year",Inputs!$B:$B,0))*12,Inputs!C101,0)} -> 0 | DP35: {=IF(DP$3=INDEX(Inputs!$C:$C,MATCH("End Year",Inputs!$B:$B,0))*12,Inputs!C101,0)} -> 0 | DQ35: {=IF(DQ$3=INDEX(Inputs!$C:$C,MATCH("End Year",Inputs!$B:$B,0))*12,Inputs!C101,0)} -> 0 | DR35: {=IF(DR$3=INDEX(Inputs!$C:$C,MATCH("End Year",Inputs!$B:$B,0))*12,Inputs!C101,0)} -> 0 | DS35: {=IF(DS$3=INDEX(Inputs!$C:$C,MATCH("End Year",Inputs!$B:$B,0))*12,Inputs!C101,0)} -> 0
B36: Selling Costs | C36: {=IF(C$3=INDEX(Inputs!$C:$C,MATCH("End Year",Inputs!$B:$B,0))*12,-Inputs!C102,0)} -> 0 | D36: {=IF(D$3=INDEX(Inputs!$C:$C,MATCH("End Year",Inputs!$B:$B,0))*12,-Inputs!C102,0)} -> 0 | E36: {=IF(E$3=INDEX(Inputs!$C:$C,MATCH("End Year",Inputs!$B:$B,0))*12,-Inputs!C102,0)} -> 0 | F36: {=IF(F$3=INDEX(Inputs!$C:$C,MATCH("End Year",Inputs!$B:$B,0))*12,-Inputs!C102,0)} -> 0 | G36: {=IF(G$3=INDEX(Inputs!$C:$C,MATCH("End Year",Inputs!$B:$B,0))*12,-Inputs!C102,0)} -> 0 | H36: {=IF(H$3=INDEX(Inputs!$C:$C,MATCH("End Year",Inputs!$B:$B,0))*12,-Inputs!C102,0)} -> 0 | I36: {=IF(I$3=INDEX(Inputs!$C:$C,MATCH("End Year",Inputs!$B:$B,0))*12,-Inputs!C102,0)} -> 0 | J36: {=IF(J$3=INDEX(Inputs!$C:$C,MATCH("End Year",Inputs!$B:$B,0))*12,-Inputs!C102,0)} -> 0 | K36: {=IF(K$3=INDEX(Inputs!$C:$C,MATCH("End Year",Inputs!$B:$B,0))*12,-Inputs!C102,0)} -> 0 | L36: {=IF(L$3=INDEX(Inputs!$C:$C,MATCH("End Year",Inputs!$B:$B,0))*12,-Inputs!C102,0)} -> 0 | M36: {=IF(M$3=INDEX(Inputs!$C:$C,MATCH("End Year",Inputs!$B:$B,0))*12,-Inputs!C102,0)} -> 0 | N36: {=IF(N$3=INDEX(Inputs!$C:$C,MATCH("End Year",Inputs!$B:$B,0))*12,-Inputs!C102,0)} -> 0 | O36: {=IF(O$3=INDEX(Inputs!$C:$C,MATCH("End Year",Inputs!$B:$B,0))*12,-Inputs!C102,0)} -> 0 | P36: {=IF(P$3=INDEX(Inputs!$C:$C,MATCH("End Year",Inputs!$B:$B,0))*12,-Inputs!C102,0)} -> 0 | Q36: {=IF(Q$3=INDEX(Inputs!$C:$C,MATCH("End Year",Inputs!$B:$B,0))*12,-Inputs!C102,0)} -> 0 | R36: {=IF(R$3=INDEX(Inputs!$C:$C,MATCH("End Year",Inputs!$B:$B,0))*12,-Inputs!C102,0)} -> 0 | S36: {=IF(S$3=INDEX(Inputs!$C:$C,MATCH("End Year",Inputs!$B:$B,0))*12,-Inputs!C102,0)} -> 0 | T36: {=IF(T$3=INDEX(Inputs!$C:$C,MATCH("End Year",Inputs!$B:$B,0))*12,-Inputs!C102,0)} -> 0 | U36: {=IF(U$3=INDEX(Inputs!$C:$C,MATCH("End Year",Inputs!$B:$B,0))*12,-Inputs!C102,0)} -> 0 | V36: {=IF(V$3=INDEX(Inputs!$C:$C,MATCH("End Year",Inputs!$B:$B,0))*12,-Inputs!C102,0)} -> 0 | W36: {=IF(W$3=INDEX(Inputs!$C:$C,MATCH("End Year",Inputs!$B:$B,0))*12,-Inputs!C102,0)} -> 0 | X36: {=IF(X$3=INDEX(Inputs!$C:$C,MATCH("End Year",Inputs!$B:$B,0))*12,-Inputs!C102,0)} -> 0 | Y36: {=IF(Y$3=INDEX(Inputs!$C:$C,MATCH("End Year",Inputs!$B:$B,0))*12,-Inputs!C102,0)} -> 0 | Z36: {=IF(Z$3=INDEX(Inputs!$C:$C,MATCH("End Year",Inputs!$B:$B,0))*12,-Inputs!C102,0)} -> 0 | AA36: {=IF(AA$3=INDEX(Inputs!$C:$C,MATCH("End Year",Inputs!$B:$B,0))*12,-Inputs!C102,0)} -> 0 | AB36: {=IF(AB$3=INDEX(Inputs!$C:$C,MATCH("End Year",Inputs!$B:$B,0))*12,-Inputs!C102,0)} -> 0 | AC36: {=IF(AC$3=INDEX(Inputs!$C:$C,MATCH("End Year",Inputs!$B:$B,0))*12,-Inputs!C102,0)} -> 0 | AD36: {=IF(AD$3=INDEX(Inputs!$C:$C,MATCH("End Year",Inputs!$B:$B,0))*12,-Inputs!C102,0)} -> 0 | AE36: {=IF(AE$3=INDEX(Inputs!$C:$C,MATCH("End Year",Inputs!$B:$B,0))*12,-Inputs!C102,0)} -> 0 | AF36: {=IF(AF$3=INDEX(Inputs!$C:$C,MATCH("End Year",Inputs!$B:$B,0))*12,-Inputs!C102,0)} -> 0 | AG36: {=IF(AG$3=INDEX(Inputs!$C:$C,MATCH("End Year",Inputs!$B:$B,0))*12,-Inputs!C102,0)} -> 0 | AH36: {=IF(AH$3=INDEX(Inputs!$C:$C,MATCH("End Year",Inputs!$B:$B,0))*12,-Inputs!C102,0)} -> 0 | AI36: {=IF(AI$3=INDEX(Inputs!$C:$C,MATCH("End Year",Inputs!$B:$B,0))*12,-Inputs!C102,0)} -> 0 | AJ36: {=IF(AJ$3=INDEX(Inputs!$C:$C,MATCH("End Year",Inputs!$B:$B,0))*12,-Inputs!C102,0)} -> 0 | AK36: {=IF(AK$3=INDEX(Inputs!$C:$C,MATCH("End Year",Inputs!$B:$B,0))*12,-Inputs!C102,0)} -> 0 | AL36: {=IF(AL$3=INDEX(Inputs!$C:$C,MATCH("End Year",Inputs!$B:$B,0))*12,-Inputs!C102,0)} -> 0 | AM36: {=IF(AM$3=INDEX(Inputs!$C:$C,MATCH("End Year",Inputs!$B:$B,0))*12,-Inputs!C102,0)} -> 0 | AN36: {=IF(AN$3=INDEX(Inputs!$C:$C,MATCH("End Year",Inputs!$B:$B,0))*12,-Inputs!C102,0)} -> 0 | AO36: {=IF(AO$3=INDEX(Inputs!$C:$C,MATCH("End Year",Inputs!$B:$B,0))*12,-Inputs!C102,0)} -> 0 | AP36: {=IF(AP$3=INDEX(Inputs!$C:$C,MATCH("End Year",Inputs!$B:$B,0))*12,-Inputs!C102,0)} -> 0 | AQ36: {=IF(AQ$3=INDEX(Inputs!$C:$C,MATCH("End Year",Inputs!$B:$B,0))*12,-Inputs!C102,0)} -> 0 | AR36: {=IF(AR$3=INDEX(Inputs!$C:$C,MATCH("End Year",Inputs!$B:$B,0))*12,-Inputs!C102,0)} -> 0 | AS36: {=IF(AS$3=INDEX(Inputs!$C:$C,MATCH("End Year",Inputs!$B:$B,0))*12,-Inputs!C102,0)} -> 0 | AT36: {=IF(AT$3=INDEX(Inputs!$C:$C,MATCH("End Year",Inputs!$B:$B,0))*12,-Inputs!C102,0)} -> 0 | AU36: {=IF(AU$3=INDEX(Inputs!$C:$C,MATCH("End Year",Inputs!$B:$B,0))*12,-Inputs!C102,0)} -> 0 | AV36: {=IF(AV$3=INDEX(Inputs!$C:$C,MATCH("End Year",Inputs!$B:$B,0))*12,-Inputs!C102,0)} -> 0 | AW36: {=IF(AW$3=INDEX(Inputs!$C:$C,MATCH("End Year",Inputs!$B:$B,0))*12,-Inputs!C102,0)} -> 0 | AX36: {=IF(AX$3=INDEX(Inputs!$C:$C,MATCH("End Year",Inputs!$B:$B,0))*12,-Inputs!C102,0)} -> 0 | AY36: {=IF(AY$3=INDEX(Inputs!$C:$C,MATCH("End Year",Inputs!$B:$B,0))*12,-Inputs!C102,0)} -> 0 | AZ36: {=IF(AZ$3=INDEX(Inputs!$C:$C,MATCH("End Year",Inputs!$B:$B,0))*12,-Inputs!C102,0)} -> 0 | BA36: {=IF(BA$3=INDEX(Inputs!$C:$C,MATCH("End Year",Inputs!$B:$B,0))*12,-Inputs!C102,0)} -> 0 | BB36: {=IF(BB$3=INDEX(Inputs!$C:$C,MATCH("End Year",Inputs!$B:$B,0))*12,-Inputs!C102,0)} -> 0 | BC36: {=IF(BC$3=INDEX(Inputs!$C:$C,MATCH("End Year",Inputs!$B:$B,0))*12,-Inputs!C102,0)} -> 0 | BD36: {=IF(BD$3=INDEX(Inputs!$C:$C,MATCH("End Year",Inputs!$B:$B,0))*12,-Inputs!C102,0)} -> 0 | BE36: {=IF(BE$3=INDEX(Inputs!$C:$C,MATCH("End Year",Inputs!$B:$B,0))*12,-Inputs!C102,0)} -> 0 | BF36: {=IF(BF$3=INDEX(Inputs!$C:$C,MATCH("End Year",Inputs!$B:$B,0))*12,-Inputs!C102,0)} -> 0 | BG36: {=IF(BG$3=INDEX(Inputs!$C:$C,MATCH("End Year",Inputs!$B:$B,0))*12,-Inputs!C102,0)} -> 0 | BH36: {=IF(BH$3=INDEX(Inputs!$C:$C,MATCH("End Year",Inputs!$B:$B,0))*12,-Inputs!C102,0)} -> 0 | BI36: {=IF(BI$3=INDEX(Inputs!$C:$C,MATCH("End Year",Inputs!$B:$B,0))*12,-Inputs!C102,0)} -> 0 | BJ36: {=IF(BJ$3=INDEX(Inputs!$C:$C,MATCH("End Year",Inputs!$B:$B,0))*12,-Inputs!C102,0)} -> 0 | BK36: {=IF(BK$3=INDEX(Inputs!$C:$C,MATCH("End Year",Inputs!$B:$B,0))*12,-Inputs!C102,0)} -> 0 | BL36: {=IF(BL$3=INDEX(Inputs!$C:$C,MATCH("End Year",Inputs!$B:$B,0))*12,-Inputs!C102,0)} -> 0 | BM36: {=IF(BM$3=INDEX(Inputs!$C:$C,MATCH("End Year",Inputs!$B:$B,0))*12,-Inputs!C102,0)} -> 0 | BN36: {=IF(BN$3=INDEX(Inputs!$C:$C,MATCH("End Year",Inputs!$B:$B,0))*12,-Inputs!C102,0)} -> 0 | BO36: {=IF(BO$3=INDEX(Inputs!$C:$C,MATCH("End Year",Inputs!$B:$B,0))*12,-Inputs!C102,0)} -> 0 | BP36: {=IF(BP$3=INDEX(Inputs!$C:$C,MATCH("End Year",Inputs!$B:$B,0))*12,-Inputs!C102,0)} -> 0 | BQ36: {=IF(BQ$3=INDEX(Inputs!$C:$C,MATCH("End Year",Inputs!$B:$B,0))*12,-Inputs!C102,0)} -> 0 | BR36: {=IF(BR$3=INDEX(Inputs!$C:$C,MATCH("End Year",Inputs!$B:$B,0))*12,-Inputs!C102,0)} -> 0 | BS36: {=IF(BS$3=INDEX(Inputs!$C:$C,MATCH("End Year",Inputs!$B:$B,0))*12,-Inputs!C102,0)} -> 0 | BT36: {=IF(BT$3=INDEX(Inputs!$C:$C,MATCH("End Year",Inputs!$B:$B,0))*12,-Inputs!C102,0)} -> 0 | BU36: {=IF(BU$3=INDEX(Inputs!$C:$C,MATCH("End Year",Inputs!$B:$B,0))*12,-Inputs!C102,0)} -> 0 | BV36: {=IF(BV$3=INDEX(Inputs!$C:$C,MATCH("End Year",Inputs!$B:$B,0))*12,-Inputs!C102,0)} -> 0 | BW36: {=IF(BW$3=INDEX(Inputs!$C:$C,MATCH("End Year",Inputs!$B:$B,0))*12,-Inputs!C102,0)} -> 0 | BX36: {=IF(BX$3=INDEX(Inputs!$C:$C,MATCH("End Year",Inputs!$B:$B,0))*12,-Inputs!C102,0)} -> 0 | BY36: {=IF(BY$3=INDEX(Inputs!$C:$C,MATCH("End Year",Inputs!$B:$B,0))*12,-Inputs!C102,0)} -> 0 | BZ36: {=IF(BZ$3=INDEX(Inputs!$C:$C,MATCH("End Year",Inputs!$B:$B,0))*12,-Inputs!C102,0)} -> 0 | CA36: {=IF(CA$3=INDEX(Inputs!$C:$C,MATCH("End Year",Inputs!$B:$B,0))*12,-Inputs!C102,0)} -> 0 | CB36: {=IF(CB$3=INDEX(Inputs!$C:$C,MATCH("End Year",Inputs!$B:$B,0))*12,-Inputs!C102,0)} -> 0 | CC36: {=IF(CC$3=INDEX(Inputs!$C:$C,MATCH("End Year",Inputs!$B:$B,0))*12,-Inputs!C102,0)} -> 0 | CD36: {=IF(CD$3=INDEX(Inputs!$C:$C,MATCH("End Year",Inputs!$B:$B,0))*12,-Inputs!C102,0)} -> 0 | CE36: {=IF(CE$3=INDEX(Inputs!$C:$C,MATCH("End Year",Inputs!$B:$B,0))*12,-Inputs!C102,0)} -> 0 | CF36: {=IF(CF$3=INDEX(Inputs!$C:$C,MATCH("End Year",Inputs!$B:$B,0))*12,-Inputs!C102,0)} -> 0 | CG36: {=IF(CG$3=INDEX(Inputs!$C:$C,MATCH("End Year",Inputs!$B:$B,0))*12,-Inputs!C102,0)} -> 0 | CH36: {=IF(CH$3=INDEX(Inputs!$C:$C,MATCH("End Year",Inputs!$B:$B,0))*12,-Inputs!C102,0)} -> 0 | CI36: {=IF(CI$3=INDEX(Inputs!$C:$C,MATCH("End Year",Inputs!$B:$B,0))*12,-Inputs!C102,0)} -> 0 | CJ36: {=IF(CJ$3=INDEX(Inputs!$C:$C,MATCH("End Year",Inputs!$B:$B,0))*12,-Inputs!C102,0)} -> 0 | CK36: {=IF(CK$3=INDEX(Inputs!$C:$C,MATCH("End Year",Inputs!$B:$B,0))*12,-Inputs!C102,0)} -> 0 | CL36: {=IF(CL$3=INDEX(Inputs!$C:$C,MATCH("End Year",Inputs!$B:$B,0))*12,-Inputs!C102,0)} -> 0 | CM36: {=IF(CM$3=INDEX(Inputs!$C:$C,MATCH("End Year",Inputs!$B:$B,0))*12,-Inputs!C102,0)} -> 0 | CN36: {=IF(CN$3=INDEX(Inputs!$C:$C,MATCH("End Year",Inputs!$B:$B,0))*12,-Inputs!C102,0)} -> 0 | CO36: {=IF(CO$3=INDEX(Inputs!$C:$C,MATCH("End Year",Inputs!$B:$B,0))*12,-Inputs!C102,0)} -> 0 | CP36: {=IF(CP$3=INDEX(Inputs!$C:$C,MATCH("End Year",Inputs!$B:$B,0))*12,-Inputs!C102,0)} -> 0 | CQ36: {=IF(CQ$3=INDEX(Inputs!$C:$C,MATCH("End Year",Inputs!$B:$B,0))*12,-Inputs!C102,0)} -> 0 | CR36: {=IF(CR$3=INDEX(Inputs!$C:$C,MATCH("End Year",Inputs!$B:$B,0))*12,-Inputs!C102,0)} -> 0 | CS36: {=IF(CS$3=INDEX(Inputs!$C:$C,MATCH("End Year",Inputs!$B:$B,0))*12,-Inputs!C102,0)} -> 0 | CT36: {=IF(CT$3=INDEX(Inputs!$C:$C,MATCH("End Year",Inputs!$B:$B,0))*12,-Inputs!C102,0)} -> 0 | CU36: {=IF(CU$3=INDEX(Inputs!$C:$C,MATCH("End Year",Inputs!$B:$B,0))*12,-Inputs!C102,0)} -> 0 | CV36: {=IF(CV$3=INDEX(Inputs!$C:$C,MATCH("End Year",Inputs!$B:$B,0))*12,-Inputs!C102,0)} -> 0 | CW36: {=IF(CW$3=INDEX(Inputs!$C:$C,MATCH("End Year",Inputs!$B:$B,0))*12,-Inputs!C102,0)} -> 0 | CX36: {=IF(CX$3=INDEX(Inputs!$C:$C,MATCH("End Year",Inputs!$B:$B,0))*12,-Inputs!C102,0)} -> 0 | CY36: {=IF(CY$3=INDEX(Inputs!$C:$C,MATCH("End Year",Inputs!$B:$B,0))*12,-Inputs!C102,0)} -> 0 | CZ36: {=IF(CZ$3=INDEX(Inputs!$C:$C,MATCH("End Year",Inputs!$B:$B,0))*12,-Inputs!C102,0)} -> 0 | DA36: {=IF(DA$3=INDEX(Inputs!$C:$C,MATCH("End Year",Inputs!$B:$B,0))*12,-Inputs!C102,0)} -> 0 | DB36: {=IF(DB$3=INDEX(Inputs!$C:$C,MATCH("End Year",Inputs!$B:$B,0))*12,-Inputs!C102,0)} -> 0 | DC36: {=IF(DC$3=INDEX(Inputs!$C:$C,MATCH("End Year",Inputs!$B:$B,0))*12,-Inputs!C102,0)} -> 0 | DD36: {=IF(DD$3=INDEX(Inputs!$C:$C,MATCH("End Year",Inputs!$B:$B,0))*12,-Inputs!C102,0)} -> 0 | DE36: {=IF(DE$3=INDEX(Inputs!$C:$C,MATCH("End Year",Inputs!$B:$B,0))*12,-Inputs!C102,0)} -> 0 | DF36: {=IF(DF$3=INDEX(Inputs!$C:$C,MATCH("End Year",Inputs!$B:$B,0))*12,-Inputs!C102,0)} -> 0 | DG36: {=IF(DG$3=INDEX(Inputs!$C:$C,MATCH("End Year",Inputs!$B:$B,0))*12,-Inputs!C102,0)} -> 0 | DH36: {=IF(DH$3=INDEX(Inputs!$C:$C,MATCH("End Year",Inputs!$B:$B,0))*12,-Inputs!C102,0)} -> 0 | DI36: {=IF(DI$3=INDEX(Inputs!$C:$C,MATCH("End Year",Inputs!$B:$B,0))*12,-Inputs!C102,0)} -> 0 | DJ36: {=IF(DJ$3=INDEX(Inputs!$C:$C,MATCH("End Year",Inputs!$B:$B,0))*12,-Inputs!C102,0)} -> 0 | DK36: {=IF(DK$3=INDEX(Inputs!$C:$C,MATCH("End Year",Inputs!$B:$B,0))*12,-Inputs!C102,0)} -> 0 | DL36: {=IF(DL$3=INDEX(Inputs!$C:$C,MATCH("End Year",Inputs!$B:$B,0))*12,-Inputs!C102,0)} -> 0 | DM36: {=IF(DM$3=INDEX(Inputs!$C:$C,MATCH("End Year",Inputs!$B:$B,0))*12,-Inputs!C102,0)} -> 0 | DN36: {=IF(DN$3=INDEX(Inputs!$C:$C,MATCH("End Year",Inputs!$B:$B,0))*12,-Inputs!C102,0)} -> 0 | DO36: {=IF(DO$3=INDEX(Inputs!$C:$C,MATCH("End Year",Inputs!$B:$B,0))*12,-Inputs!C102,0)} -> 0 | DP36: {=IF(DP$3=INDEX(Inputs!$C:$C,MATCH("End Year",Inputs!$B:$B,0))*12,-Inputs!C102,0)} -> 0 | DQ36: {=IF(DQ$3=INDEX(Inputs!$C:$C,MATCH("End Year",Inputs!$B:$B,0))*12,-Inputs!C102,0)} -> 0 | DR36: {=IF(DR$3=INDEX(Inputs!$C:$C,MATCH("End Year",Inputs!$B:$B,0))*12,-Inputs!C102,0)} -> 0 | DS36: {=IF(DS$3=INDEX(Inputs!$C:$C,MATCH("End Year",Inputs!$B:$B,0))*12,-Inputs!C102,0)} -> 0
B37: NET SALE PROCEEDS | C37: =C35+C36 -> 0 | D37: =D35+D36 -> 0 | E37: =E35+E36 -> 0 | F37: =F35+F36 -> 0 | G37: =G35+G36 -> 0 | H37: =H35+H36 -> 0 | I37: =I35+I36 -> 0 | J37: =J35+J36 -> 0 | ... DS37: =DS35+DS36 -> 0
B39: CASHFLOW BEFORE DEBT SERVICE | C39: =C20+C23+C32+C37 -> -5000 | D39: =D20+D23+D32+D37 -> 0 | E39: =E20+E23+E32+E37 -> 0 | F39: =F20+F23+F32+F37 -> 0 | G39: =G20+G23+G32+G37 -> 0 | H39: =H20+H23+H32+H37 -> 0 | I39: =I20+I23+I32+I37 -> 0 | J39: =J20+J23+J32+J37 -> 0 | ... DS39: =DS20+DS23+DS32+DS37 -> 0
B41: DEBT SERVICE — SELLER FINANCE
B42: Beginning Balance | C42: 0 | D42: {=IF(D$3<=INDEX(Inputs!$C:$C,MATCH("End Year",Inputs!$B:$B,0))*12,IF(D$3<=INDEX(Inputs!$C:$C,MATCH("*Seller Finance Origination Month*",Inputs!$B:$B,0)),0,C47),0)} -> 0 | E42: {=IF(E$3<=INDEX(Inputs!$C:$C,MATCH("End Year",Inputs!$B:$B,0))*12,IF(E$3<=INDEX(Inputs!$C:$C,MATCH("*Seller Finance Origination Month*",Inputs!$B:$B,0)),0,D47),0)} -> 0 | F42: {=IF(F$3<=INDEX(Inputs!$C:$C,MATCH("End Year",Inputs!$B:$B,0))*12,IF(F$3<=INDEX(Inputs!$C:$C,MATCH("*Seller Finance Origination Month*",Inputs!$B:$B,0)),0,E47),0)} -> 0 | G42: {=IF(G$3<=INDEX(Inputs!$C:$C,MATCH("End Year",Inputs!$B:$B,0))*12,IF(G$3<=INDEX(Inputs!$C:$C,MATCH("*Seller Finance Origination Month*",Inputs!$B:$B,0)),0,F47),0)} -> 0 | H42: {=IF(H$3<=INDEX(Inputs!$C:$C,MATCH("End Year",Inputs!$B:$B,0))*12,IF(H$3<=INDEX(Inputs!$C:$C,MATCH("*Seller Finance Origination Month*",Inputs!$B:$B,0)),0,G47),0)} -> 0 | I42: {=IF(I$3<=INDEX(Inputs!$C:$C,MATCH("End Year",Inputs!$B:$B,0))*12,IF(I$3<=INDEX(Inputs!$C:$C,MATCH("*Seller Finance Origination Month*",Inputs!$B:$B,0)),0,H47),0)} -> 0 | J42: {=IF(J$3<=INDEX(Inputs!$C:$C,MATCH("End Year",Inputs!$B:$B,0))*12,IF(J$3<=INDEX(Inputs!$C:$C,MATCH("*Seller Finance Origination Month*",Inputs!$B:$B,0)),0,I47),0)} -> 0 | K42: {=IF(K$3<=INDEX(Inputs!$C:$C,MATCH("End Year",Inputs!$B:$B,0))*12,IF(K$3<=INDEX(Inputs!$C:$C,MATCH("*Seller Finance Origination Month*",Inputs!$B:$B,0)),0,J47),0)} -> 0 | ... DS42: {=IF(DS$3<=INDEX(Inputs!$C:$C,MATCH("End Year",Inputs!$B:$B,0))*12,IF(DS$3<=INDEX(Inputs!$C:$C,MATCH("*Seller Finance Origination Month*",Inputs!$B:$B,0)),0,DR47),0)} -> 0
B43: Loan Funding | C43: {=IF(C$3<=INDEX(Inputs!$C:$C,MATCH("End Year",Inputs!$B:$B,0))*12,IF(C$3=INDEX(Inputs!$C:$C,MATCH("*Seller Finance Origination Month*",Inputs!$B:$B,0)),INDEX(Inputs!$C:$C,MATCH("*Seller Finance Amount*",Inputs!$B:$B,0)),0),0)} -> 0 | D43: {=IF(D$3<=INDEX(Inputs!$C:$C,MATCH("End Year",Inputs!$B:$B,0))*12,IF(D$3=INDEX(Inputs!$C:$C,MATCH("*Seller Finance Origination Month*",Inputs!$B:$B,0)),INDEX(Inputs!$C:$C,MATCH("*Seller Finance Amount*",Inputs!$B:$B,0)),0),0)} -> 0 | E43: {=IF(E$3<=INDEX(Inputs!$C:$C,MATCH("End Year",Inputs!$B:$B,0))*12,IF(E$3=INDEX(Inputs!$C:$C,MATCH("*Seller Finance Origination Month*",Inputs!$B:$B,0)),INDEX(Inputs!$C:$C,MATCH("*Seller Finance Amount*",Inputs!$B:$B,0)),0),0)} -> 0 | F43: {=IF(F$3<=INDEX(Inputs!$C:$C,MATCH("End Year",Inputs!$B:$B,0))*12,IF(F$3=INDEX(Inputs!$C:$C,MATCH("*Seller Finance Origination Month*",Inputs!$B:$B,0)),INDEX(Inputs!$C:$C,MATCH("*Seller Finance Amount*",Inputs!$B:$B,0)),0),0)} -> 0 | G43: {=IF(G$3<=INDEX(Inputs!$C:$C,MATCH("End Year",Inputs!$B:$B,0))*12,IF(G$3=INDEX(Inputs!$C:$C,MATCH("*Seller Finance Origination Month*",Inputs!$B:$B,0)),INDEX(Inputs!$C:$C,MATCH("*Seller Finance Amount*",Inputs!$B:$B,0)),0),0)} -> 0 | H43: {=IF(H$3<=INDEX(Inputs!$C:$C,MATCH("End Year",Inputs!$B:$B,0))*12,IF(H$3=INDEX(Inputs!$C:$C,MATCH("*Seller Finance Origination Month*",Inputs!$B:$B,0)),INDEX(Inputs!$C:$C,MATCH("*Seller Finance Amount*",Inputs!$B:$B,0)),0),0)} -> 0 | I43: {=IF(I$3<=INDEX(Inputs!$C:$C,MATCH("End Year",Inputs!$B:$B,0))*12,IF(I$3=INDEX(Inputs!$C:$C,MATCH("*Seller Finance Origination Month*",Inputs!$B:$B,0)),INDEX(Inputs!$C:$C,MATCH("*Seller Finance Amount*",Inputs!$B:$B,0)),0),0)} -> 0 | J43: {=IF(J$3<=INDEX(Inputs!$C:$C,MATCH("End Year",Inputs!$B:$B,0))*12,IF(J$3=INDEX(Inputs!$C:$C,MATCH("*Seller Finance Origination Month*",Inputs!$B:$B,0)),INDEX(Inputs!$C:$C,MATCH("*Seller Finance Amount*",Inputs!$B:$B,0)),0),0)} -> 0 | ... DS43: {=IF(DS$3<=INDEX(Inputs!$C:$C,MATCH("End Year",Inputs!$B:$B,0))*12,IF(DS$3=INDEX(Inputs!$C:$C,MATCH("*Seller Finance Origination Month*",Inputs!$B:$B,0)),INDEX(Inputs!$C:$C,MATCH("*Seller Finance Amount*",Inputs!$B:$B,0)),0),0)} -> 0
B44: Interest Payment | C44: {=IF(C$3<=INDEX(Inputs!$C:$C,MATCH("End Year",Inputs!$B:$B,0))*12,IF(OR(C42=0,C$3<INDEX(Inputs!$C:$C,MATCH("*Seller Finance PMT Start Month*",Inputs!$B:$B,0))),0,-C42*INDEX(Inputs!$C:$C,MATCH("*Seller Finance Interest Rate*",Inputs!$B:$B,0))/12),0)} -> 0 | D44: {=IF(D$3<=INDEX(Inputs!$C:$C,MATCH("End Year",Inputs!$B:$B,0))*12,IF(OR(D42=0,D$3<INDEX(Inputs!$C:$C,MATCH("*Seller Finance PMT Start Month*",Inputs!$B:$B,0))),0,-D42*INDEX(Inputs!$C:$C,MATCH("*Seller Finance Interest Rate*",Inputs!$B:$B,0))/12),0)} -> 0 | E44: {=IF(E$3<=INDEX(Inputs!$C:$C,MATCH("End Year",Inputs!$B:$B,0))*12,IF(OR(E42=0,E$3<INDEX(Inputs!$C:$C,MATCH("*Seller Finance PMT Start Month*",Inputs!$B:$B,0))),0,-E42*INDEX(Inputs!$C:$C,MATCH("*Seller Finance Interest Rate*",Inputs!$B:$B,0))/12),0)} -> 0 | F44: {=IF(F$3<=INDEX(Inputs!$C:$C,MATCH("End Year",Inputs!$B:$B,0))*12,IF(OR(F42=0,F$3<INDEX(Inputs!$C:$C,MATCH("*Seller Finance PMT Start Month*",Inputs!$B:$B,0))),0,-F42*INDEX(Inputs!$C:$C,MATCH("*Seller Finance Interest Rate*",Inputs!$B:$B,0))/12),0)} -> 0 | G44: {=IF(G$3<=INDEX(Inputs!$C:$C,MATCH("End Year",Inputs!$B:$B,0))*12,IF(OR(G42=0,G$3<INDEX(Inputs!$C:$C,MATCH("*Seller Finance PMT Start Month*",Inputs!$B:$B,0))),0,-G42*INDEX(Inputs!$C:$C,MATCH("*Seller Finance Interest Rate*",Inputs!$B:$B,0))/12),0)} -> 0 | H44: {=IF(H$3<=INDEX(Inputs!$C:$C,MATCH("End Year",Inputs!$B:$B,0))*12,IF(OR(H42=0,H$3<INDEX(Inputs!$C:$C,MATCH("*Seller Finance PMT Start Month*",Inputs!$B:$B,0))),0,-H42*INDEX(Inputs!$C:$C,MATCH("*Seller Finance Interest Rate*",Inputs!$B:$B,0))/12),0)} -> 0 | I44: {=IF(I$3<=INDEX(Inputs!$C:$C,MATCH("End Year",Inputs!$B:$B,0))*12,IF(OR(I42=0,I$3<INDEX(Inputs!$C:$C,MATCH("*Seller Finance PMT Start Month*",Inputs!$B:$B,0))),0,-I42*INDEX(Inputs!$C:$C,MATCH("*Seller Finance Interest Rate*",Inputs!$B:$B,0))/12),0)} -> 0 | J44: {=IF(J$3<=INDEX(Inputs!$C:$C,MATCH("End Year",Inputs!$B:$B,0))*12,IF(OR(J42=0,J$3<INDEX(Inputs!$C:$C,MATCH("*Seller Finance PMT Start Month*",Inputs!$B:$B,0))),0,-J42*INDEX(Inputs!$C:$C,MATCH("*Seller Finance Interest Rate*",Inputs!$B:$B,0))/12),0)} -> 0 | ... DS44: {=IF(DS$3<=INDEX(Inputs!$C:$C,MATCH("End Year",Inputs!$B:$B,0))*12,IF(OR(DS42=0,DS$3<INDEX(Inputs!$C:$C,MATCH("*Seller Finance PMT Start Month*",Inputs!$B:$B,0))),0,-DS42*INDEX(Inputs!$C:$C,MATCH("*Seller Finance Interest Rate*",Inputs!$B:$B,0))/12),0)} -> 0
B45: Principal Payment | C45: {=IF(C$3<=INDEX(Inputs!$C:$C,MATCH("End Year",Inputs!$B:$B,0))*12,IF(OR(C42=0,C$3<INDEX(Inputs!$C:$C,MATCH("*Seller Finance PMT Start Month*",Inputs!$B:$B,0))),0,IF(C$3-INDEX(Inputs!$C:$C,MATCH("*Seller Finance PMT Start Month*",Inputs!$B:$B,0))+1<=INDEX(Inputs!$C:$C,MATCH("*Seller Finance IO Period*",Inputs!$B:$B,0)),0,MIN(PMT(INDEX(Inputs!$C:$C,MATCH("*Seller Finance Interest Rate*",Inputs!$B:$B,0))/12,INDEX(Inputs!$C:$C,MATCH("*Seller Finance Amortization*",Inputs!$B:$B,0))*12,-INDEX(Inputs!$C:$C,MATCH("*Seller Finance Amount*",Inputs!$B:$B,0)))-C42*INDEX(Inputs!$C:$C,MATCH("*Seller Finance Interest Rate*",Inputs!$B:$B,0))/12,C42))),0)} -> 0 | D45: {=IF(D$3<=INDEX(Inputs!$C:$C,MATCH("End Year",Inputs!$B:$B,0))*12,IF(OR(D42=0,D$3<INDEX(Inputs!$C:$C,MATCH("*Seller Finance PMT Start Month*",Inputs!$B:$B,0))),0,IF(D$3-INDEX(Inputs!$C:$C,MATCH("*Seller Finance PMT Start Month*",Inputs!$B:$B,0))+1<=INDEX(Inputs!$C:$C,MATCH("*Seller Finance IO Period*",Inputs!$B:$B,0)),0,MIN(PMT(INDEX(Inputs!$C:$C,MATCH("*Seller Finance Interest Rate*",Inputs!$B:$B,0))/12,INDEX(Inputs!$C:$C,MATCH("*Seller Finance Amortization*",Inputs!$B:$B,0))*12,-INDEX(Inputs!$C:$C,MATCH("*Seller Finance Amount*",Inputs!$B:$B,0)))-D42*INDEX(Inputs!$C:$C,MATCH("*Seller Finance Interest Rate*",Inputs!$B:$B,0))/12,D42))),0)} -> 0 | E45: {=IF(E$3<=INDEX(Inputs!$C:$C,MATCH("End Year",Inputs!$B:$B,0))*12,IF(OR(E42=0,E$3<INDEX(Inputs!$C:$C,MATCH("*Seller Finance PMT Start Month*",Inputs!$B:$B,0))),0,IF(E$3-INDEX(Inputs!$C:$C,MATCH("*Seller Finance PMT Start Month*",Inputs!$B:$B,0))+1<=INDEX(Inputs!$C:$C,MATCH("*Seller Finance IO Period*",Inputs!$B:$B,0)),0,MIN(PMT(INDEX(Inputs!$C:$C,MATCH("*Seller Finance Interest Rate*",Inputs!$B:$B,0))/12,INDEX(Inputs!$C:$C,MATCH("*Seller Finance Amortization*",Inputs!$B:$B,0))*12,-INDEX(Inputs!$C:$C,MATCH("*Seller Finance Amount*",Inputs!$B:$B,0)))-E42*INDEX(Inputs!$C:$C,MATCH("*Seller Finance Interest Rate*",Inputs!$B:$B,0))/12,E42))),0)} -> 0 | F45: {=IF(F$3<=INDEX(Inputs!$C:$C,MATCH("End Year",Inputs!$B:$B,0))*12,IF(OR(F42=0,F$3<INDEX(Inputs!$C:$C,MATCH("*Seller Finance PMT Start Month*",Inputs!$B:$B,0))),0,IF(F$3-INDEX(Inputs!$C:$C,MATCH("*Seller Finance PMT Start Month*",Inputs!$B:$B,0))+1<=INDEX(Inputs!$C:$C,MATCH("*Seller Finance IO Period*",Inputs!$B:$B,0)),0,MIN(PMT(INDEX(Inputs!$C:$C,MATCH("*Seller Finance Interest Rate*",Inputs!$B:$B,0))/12,INDEX(Inputs!$C:$C,MATCH("*Seller Finance Amortization*",Inputs!$B:$B,0))*12,-INDEX(Inputs!$C:$C,MATCH("*Seller Finance Amount*",Inputs!$B:$B,0)))-F42*INDEX(Inputs!$C:$C,MATCH("*Seller Finance Interest Rate*",Inputs!$B:$B,0))/12,F42))),0)} -> 0 | G45: {=IF(G$3<=INDEX(Inputs!$C:$C,MATCH("End Year",Inputs!$B:$B,0))*12,IF(OR(G42=0,G$3<INDEX(Inputs!$C:$C,MATCH("*Seller Finance PMT Start Month*",Inputs!$B:$B,0))),0,IF(G$3-INDEX(Inputs!$C:$C,MATCH("*Seller Finance PMT Start Month*",Inputs!$B:$B,0))+1<=INDEX(Inputs!$C:$C,MATCH("*Seller Finance IO Period*",Inputs!$B:$B,0)),0,MIN(PMT(INDEX(Inputs!$C:$C,MATCH("*Seller Finance Interest Rate*",Inputs!$B:$B,0))/12,INDEX(Inputs!$C:$C,MATCH("*Seller Finance Amortization*",Inputs!$B:$B,0))*12,-INDEX(Inputs!$C:$C,MATCH("*Seller Finance Amount*",Inputs!$B:$B,0)))-G42*INDEX(Inputs!$C:$C,MATCH("*Seller Finance Interest Rate*",Inputs!$B:$B,0))/12,G42))),0)} -> 0 | H45: {=IF(H$3<=INDEX(Inputs!$C:$C,MATCH("End Year",Inputs!$B:$B,0))*12,IF(OR(H42=0,H$3<INDEX(Inputs!$C:$C,MATCH("*Seller Finance PMT Start Month*",Inputs!$B:$B,0))),0,IF(H$3-INDEX(Inputs!$C:$C,MATCH("*Seller Finance PMT Start Month*",Inputs!$B:$B,0))+1<=INDEX(Inputs!$C:$C,MATCH("*Seller Finance IO Period*",Inputs!$B:$B,0)),0,MIN(PMT(INDEX(Inputs!$C:$C,MATCH("*Seller Finance Interest Rate*",Inputs!$B:$B,0))/12,INDEX(Inputs!$C:$C,MATCH("*Seller Finance Amortization*",Inputs!$B:$B,0))*12,-INDEX(Inputs!$C:$C,MATCH("*Seller Finance Amount*",Inputs!$B:$B,0)))-H42*INDEX(Inputs!$C:$C,MATCH("*Seller Finance Interest Rate*",Inputs!$B:$B,0))/12,H42))),0)} -> 0 | I45: {=IF(I$3<=INDEX(Inputs!$C:$C,MATCH("End Year",Inputs!$B:$B,0))*12,IF(OR(I42=0,I$3<INDEX(Inputs!$C:$C,MATCH("*Seller Finance PMT Start Month*",Inputs!$B:$B,0))),0,IF(I$3-INDEX(Inputs!$C:$C,MATCH("*Seller Finance PMT Start Month*",Inputs!$B:$B,0))+1<=INDEX(Inputs!$C:$C,MATCH("*Seller Finance IO Period*",Inputs!$B:$B,0)),0,MIN(PMT(INDEX(Inputs!$C:$C,MATCH("*Seller Finance Interest Rate*",Inputs!$B:$B,0))/12,INDEX(Inputs!$C:$C,MATCH("*Seller Finance Amortization*",Inputs!$B:$B,0))*12,-INDEX(Inputs!$C:$C,MATCH("*Seller Finance Amount*",Inputs!$B:$B,0)))-I42*INDEX(Inputs!$C:$C,MATCH("*Seller Finance Interest Rate*",Inputs!$B:$B,0))/12,I42))),0)} -> 0 | J45: {=IF(J$3<=INDEX(Inputs!$C:$C,MATCH("End Year",Inputs!$B:$B,0))*12,IF(OR(J42=0,J$3<INDEX(Inputs!$C:$C,MATCH("*Seller Finance PMT Start Month*",Inputs!$B:$B,0))),0,IF(J$3-INDEX(Inputs!$C:$C,MATCH("*Seller Finance PMT Start Month*",Inputs!$B:$B,0))+1<=INDEX(Inputs!$C:$C,MATCH("*Seller Finance IO Period*",Inputs!$B:$B,0)),0,MIN(PMT(INDEX(Inputs!$C:$C,MATCH("*Seller Finance Interest Rate*",Inputs!$B:$B,0))/12,INDEX(Inputs!$C:$C,MATCH("*Seller Finance Amortization*",Inputs!$B:$B,0))*12,-INDEX(Inputs!$C:$C,MATCH("*Seller Finance Amount*",Inputs!$B:$B,0)))-J42*INDEX(Inputs!$C:$C,MATCH("*Seller Finance Interest Rate*",Inputs!$B:$B,0))/12,J42))),0)} -> 0 | ... DS45: {=IF(DS$3<=INDEX(Inputs!$C:$C,MATCH("End Year",Inputs!$B:$B,0))*12,IF(OR(DS42=0,DS$3<INDEX(Inputs!$C:$C,MATCH("*Seller Finance PMT Start Month*",Inputs!$B:$B,0))),0,IF(DS$3-INDEX(Inputs!$C:$C,MATCH("*Seller Finance PMT Start Month*",Inputs!$B:$B,0))+1<=INDEX(Inputs!$C:$C,MATCH("*Seller Finance IO Period*",Inputs!$B:$B,0)),0,MIN(PMT(INDEX(Inputs!$C:$C,MATCH("*Seller Finance Interest Rate*",Inputs!$B:$B,0))/12,INDEX(Inputs!$C:$C,MATCH("*Seller Finance Amortization*",Inputs!$B:$B,0))*12,-INDEX(Inputs!$C:$C,MATCH("*Seller Finance Amount*",Inputs!$B:$B,0)))-DS42*INDEX(Inputs!$C:$C,MATCH("*Seller Finance Interest Rate*",Inputs!$B:$B,0))/12,DS42))),0)} -> 0
B46: Loan Payoff | C46: {=IF(C$3<=INDEX(Inputs!$C:$C,MATCH("End Year",Inputs!$B:$B,0))*12,IF(OR(C$3=INDEX(Inputs!$C:$C,MATCH("*Seller Finance Balloon*",Inputs!$B:$B,0))*12,C$3=INDEX(Inputs!$C:$C,MATCH("End Year",Inputs!$B:$B,0))*12),-MAX(C42+C43-C45,0),0),0)} -> 0 | D46: {=IF(D$3<=INDEX(Inputs!$C:$C,MATCH("End Year",Inputs!$B:$B,0))*12,IF(OR(D$3=INDEX(Inputs!$C:$C,MATCH("*Seller Finance Balloon*",Inputs!$B:$B,0))*12,D$3=INDEX(Inputs!$C:$C,MATCH("End Year",Inputs!$B:$B,0))*12),-MAX(D42+D43-D45,0),0),0)} -> 0 | E46: {=IF(E$3<=INDEX(Inputs!$C:$C,MATCH("End Year",Inputs!$B:$B,0))*12,IF(OR(E$3=INDEX(Inputs!$C:$C,MATCH("*Seller Finance Balloon*",Inputs!$B:$B,0))*12,E$3=INDEX(Inputs!$C:$C,MATCH("End Year",Inputs!$B:$B,0))*12),-MAX(E42+E43-E45,0),0),0)} -> 0 | F46: {=IF(F$3<=INDEX(Inputs!$C:$C,MATCH("End Year",Inputs!$B:$B,0))*12,IF(OR(F$3=INDEX(Inputs!$C:$C,MATCH("*Seller Finance Balloon*",Inputs!$B:$B,0))*12,F$3=INDEX(Inputs!$C:$C,MATCH("End Year",Inputs!$B:$B,0))*12),-MAX(F42+F43-F45,0),0),0)} -> 0 | G46: {=IF(G$3<=INDEX(Inputs!$C:$C,MATCH("End Year",Inputs!$B:$B,0))*12,IF(OR(G$3=INDEX(Inputs!$C:$C,MATCH("*Seller Finance Balloon*",Inputs!$B:$B,0))*12,G$3=INDEX(Inputs!$C:$C,MATCH("End Year",Inputs!$B:$B,0))*12),-MAX(G42+G43-G45,0),0),0)} -> 0 | H46: {=IF(H$3<=INDEX(Inputs!$C:$C,MATCH("End Year",Inputs!$B:$B,0))*12,IF(OR(H$3=INDEX(Inputs!$C:$C,MATCH("*Seller Finance Balloon*",Inputs!$B:$B,0))*12,H$3=INDEX(Inputs!$C:$C,MATCH("End Year",Inputs!$B:$B,0))*12),-MAX(H42+H43-H45,0),0),0)} -> 0 | I46: {=IF(I$3<=INDEX(Inputs!$C:$C,MATCH("End Year",Inputs!$B:$B,0))*12,IF(OR(I$3=INDEX(Inputs!$C:$C,MATCH("*Seller Finance Balloon*",Inputs!$B:$B,0))*12,I$3=INDEX(Inputs!$C:$C,MATCH("End Year",Inputs!$B:$B,0))*12),-MAX(I42+I43-I45,0),0),0)} -> 0 | J46: {=IF(J$3<=INDEX(Inputs!$C:$C,MATCH("End Year",Inputs!$B:$B,0))*12,IF(OR(J$3=INDEX(Inputs!$C:$C,MATCH("*Seller Finance Balloon*",Inputs!$B:$B,0))*12,J$3=INDEX(Inputs!$C:$C,MATCH("End Year",Inputs!$B:$B,0))*12),-MAX(J42+J43-J45,0),0),0)} -> 0 | ... DS46: {=IF(DS$3<=INDEX(Inputs!$C:$C,MATCH("End Year",Inputs!$B:$B,0))*12,IF(OR(DS$3=INDEX(Inputs!$C:$C,MATCH("*Seller Finance Balloon*",Inputs!$B:$B,0))*12,DS$3=INDEX(Inputs!$C:$C,MATCH("End Year",Inputs!$B:$B,0))*12),-MAX(DS42+DS43-DS45,0),0),0)} -> 0
B47: Ending Balance | C47: {=IF(C$3<=INDEX(Inputs!$C:$C,MATCH("End Year",Inputs!$B:$B,0))*12,MAX(C42+C43-C45+C46,0),0)} -> 0 | D47: {=IF(D$3<=INDEX(Inputs!$C:$C,MATCH("End Year",Inputs!$B:$B,0))*12,MAX(D42+D43-D45+D46,0),0)} -> 0 | E47: {=IF(E$3<=INDEX(Inputs!$C:$C,MATCH("End Year",Inputs!$B:$B,0))*12,MAX(E42+E43-E45+E46,0),0)} -> 0 | F47: {=IF(F$3<=INDEX(Inputs!$C:$C,MATCH("End Year",Inputs!$B:$B,0))*12,MAX(F42+F43-F45+F46,0),0)} -> 0 | G47: {=IF(G$3<=INDEX(Inputs!$C:$C,MATCH("End Year",Inputs!$B:$B,0))*12,MAX(G42+G43-G45+G46,0),0)} -> 0 | H47: {=IF(H$3<=INDEX(Inputs!$C:$C,MATCH("End Year",Inputs!$B:$B,0))*12,MAX(H42+H43-H45+H46,0),0)} -> 0 | I47: {=IF(I$3<=INDEX(Inputs!$C:$C,MATCH("End Year",Inputs!$B:$B,0))*12,MAX(I42+I43-I45+I46,0),0)} -> 0 | J47: {=IF(J$3<=INDEX(Inputs!$C:$C,MATCH("End Year",Inputs!$B:$B,0))*12,MAX(J42+J43-J45+J46,0),0)} -> 0 | ... DS47: {=IF(DS$3<=INDEX(Inputs!$C:$C,MATCH("End Year",Inputs!$B:$B,0))*12,MAX(DS42+DS43-DS45+DS46,0),0)} -> 0
B48: Total Debt Service (SF) | C48: {=IF(C$3<=INDEX(Inputs!$C:$C,MATCH("End Year",Inputs!$B:$B,0))*12,C44-C45+C46,0)} -> 0 | D48: {=IF(D$3<=INDEX(Inputs!$C:$C,MATCH("End Year",Inputs!$B:$B,0))*12,D44-D45+D46,0)} -> 0 | E48: {=IF(E$3<=INDEX(Inputs!$C:$C,MATCH("End Year",Inputs!$B:$B,0))*12,E44-E45+E46,0)} -> 0 | F48: {=IF(F$3<=INDEX(Inputs!$C:$C,MATCH("End Year",Inputs!$B:$B,0))*12,F44-F45+F46,0)} -> 0 | G48: {=IF(G$3<=INDEX(Inputs!$C:$C,MATCH("End Year",Inputs!$B:$B,0))*12,G44-G45+G46,0)} -> 0 | H48: {=IF(H$3<=INDEX(Inputs!$C:$C,MATCH("End Year",Inputs!$B:$B,0))*12,H44-H45+H46,0)} -> 0 | I48: {=IF(I$3<=INDEX(Inputs!$C:$C,MATCH("End Year",Inputs!$B:$B,0))*12,I44-I45+I46,0)} -> 0 | J48: {=IF(J$3<=INDEX(Inputs!$C:$C,MATCH("End Year",Inputs!$B:$B,0))*12,J44-J45+J46,0)} -> 0 | ... DS48: {=IF(DS$3<=INDEX(Inputs!$C:$C,MATCH("End Year",Inputs!$B:$B,0))*12,DS44-DS45+DS46,0)} -> 0
B50: DEBT SERVICE — BANK LOAN
B51: Beginning Balance | C51: 0 | D51: {=IF(D$3<=INDEX(Inputs!$C:$C,MATCH("End Year",Inputs!$B:$B,0))*12,IF(D$3<=INDEX(Inputs!$C:$C,MATCH("*Bank Loan Origination Month*",Inputs!$B:$B,0)),0,C56),0)} -> 0 | E51: {=IF(E$3<=INDEX(Inputs!$C:$C,MATCH("End Year",Inputs!$B:$B,0))*12,IF(E$3<=INDEX(Inputs!$C:$C,MATCH("*Bank Loan Origination Month*",Inputs!$B:$B,0)),0,D56),0)} -> 0 | F51: {=IF(F$3<=INDEX(Inputs!$C:$C,MATCH("End Year",Inputs!$B:$B,0))*12,IF(F$3<=INDEX(Inputs!$C:$C,MATCH("*Bank Loan Origination Month*",Inputs!$B:$B,0)),0,E56),0)} -> 0 | G51: {=IF(G$3<=INDEX(Inputs!$C:$C,MATCH("End Year",Inputs!$B:$B,0))*12,IF(G$3<=INDEX(Inputs!$C:$C,MATCH("*Bank Loan Origination Month*",Inputs!$B:$B,0)),0,F56),0)} -> 0 | H51: {=IF(H$3<=INDEX(Inputs!$C:$C,MATCH("End Year",Inputs!$B:$B,0))*12,IF(H$3<=INDEX(Inputs!$C:$C,MATCH("*Bank Loan Origination Month*",Inputs!$B:$B,0)),0,G56),0)} -> 0 | I51: {=IF(I$3<=INDEX(Inputs!$C:$C,MATCH("End Year",Inputs!$B:$B,0))*12,IF(I$3<=INDEX(Inputs!$C:$C,MATCH("*Bank Loan Origination Month*",Inputs!$B:$B,0)),0,H56),0)} -> 0 | J51: {=IF(J$3<=INDEX(Inputs!$C:$C,MATCH("End Year",Inputs!$B:$B,0))*12,IF(J$3<=INDEX(Inputs!$C:$C,MATCH("*Bank Loan Origination Month*",Inputs!$B:$B,0)),0,I56),0)} -> 0 | K51: {=IF(K$3<=INDEX(Inputs!$C:$C,MATCH("End Year",Inputs!$B:$B,0))*12,IF(K$3<=INDEX(Inputs!$C:$C,MATCH("*Bank Loan Origination Month*",Inputs!$B:$B,0)),0,J56),0)} -> 0 | ... DS51: {=IF(DS$3<=INDEX(Inputs!$C:$C,MATCH("End Year",Inputs!$B:$B,0))*12,IF(DS$3<=INDEX(Inputs!$C:$C,MATCH("*Bank Loan Origination Month*",Inputs!$B:$B,0)),0,DR56),0)} -> 0
B52: Loan Funding | C52: {=IF(C$3<=INDEX(Inputs!$C:$C,MATCH("End Year",Inputs!$B:$B,0))*12,IF(C$3=INDEX(Inputs!$C:$C,MATCH("*Bank Loan Origination Month*",Inputs!$B:$B,0)),INDEX(Inputs!$C:$C,MATCH("*Bank Loan Amount*",Inputs!$B:$B,0)),0),0)} -> 0 | D52: {=IF(D$3<=INDEX(Inputs!$C:$C,MATCH("End Year",Inputs!$B:$B,0))*12,IF(D$3=INDEX(Inputs!$C:$C,MATCH("*Bank Loan Origination Month*",Inputs!$B:$B,0)),INDEX(Inputs!$C:$C,MATCH("*Bank Loan Amount*",Inputs!$B:$B,0)),0),0)} -> 0 | E52: {=IF(E$3<=INDEX(Inputs!$C:$C,MATCH("End Year",Inputs!$B:$B,0))*12,IF(E$3=INDEX(Inputs!$C:$C,MATCH("*Bank Loan Origination Month*",Inputs!$B:$B,0)),INDEX(Inputs!$C:$C,MATCH("*Bank Loan Amount*",Inputs!$B:$B,0)),0),0)} -> 0 | F52: {=IF(F$3<=INDEX(Inputs!$C:$C,MATCH("End Year",Inputs!$B:$B,0))*12,IF(F$3=INDEX(Inputs!$C:$C,MATCH("*Bank Loan Origination Month*",Inputs!$B:$B,0)),INDEX(Inputs!$C:$C,MATCH("*Bank Loan Amount*",Inputs!$B:$B,0)),0),0)} -> 0 | G52: {=IF(G$3<=INDEX(Inputs!$C:$C,MATCH("End Year",Inputs!$B:$B,0))*12,IF(G$3=INDEX(Inputs!$C:$C,MATCH("*Bank Loan Origination Month*",Inputs!$B:$B,0)),INDEX(Inputs!$C:$C,MATCH("*Bank Loan Amount*",Inputs!$B:$B,0)),0),0)} -> 0 | H52: {=IF(H$3<=INDEX(Inputs!$C:$C,MATCH("End Year",Inputs!$B:$B,0))*12,IF(H$3=INDEX(Inputs!$C:$C,MATCH("*Bank Loan Origination Month*",Inputs!$B:$B,0)),INDEX(Inputs!$C:$C,MATCH("*Bank Loan Amount*",Inputs!$B:$B,0)),0),0)} -> 0 | I52: {=IF(I$3<=INDEX(Inputs!$C:$C,MATCH("End Year",Inputs!$B:$B,0))*12,IF(I$3=INDEX(Inputs!$C:$C,MATCH("*Bank Loan Origination Month*",Inputs!$B:$B,0)),INDEX(Inputs!$C:$C,MATCH("*Bank Loan Amount*",Inputs!$B:$B,0)),0),0)} -> 0 | J52: {=IF(J$3<=INDEX(Inputs!$C:$C,MATCH("End Year",Inputs!$B:$B,0))*12,IF(J$3=INDEX(Inputs!$C:$C,MATCH("*Bank Loan Origination Month*",Inputs!$B:$B,0)),INDEX(Inputs!$C:$C,MATCH("*Bank Loan Amount*",Inputs!$B:$B,0)),0),0)} -> 0 | ... DS52: {=IF(DS$3<=INDEX(Inputs!$C:$C,MATCH("End Year",Inputs!$B:$B,0))*12,IF(DS$3=INDEX(Inputs!$C:$C,MATCH("*Bank Loan Origination Month*",Inputs!$B:$B,0)),INDEX(Inputs!$C:$C,MATCH("*Bank Loan Amount*",Inputs!$B:$B,0)),0),0)} -> 0
B53: Interest Payment | C53: {=IF(C$3<=INDEX(Inputs!$C:$C,MATCH("End Year",Inputs!$B:$B,0))*12,IF(OR(C51=0,C$3<INDEX(Inputs!$C:$C,MATCH("*Bank Loan PMT Start Month*",Inputs!$B:$B,0))),0,-C51*INDEX(Inputs!$C:$C,MATCH("*Bank Loan Interest Rate*",Inputs!$B:$B,0))/12),0)} -> 0 | D53: {=IF(D$3<=INDEX(Inputs!$C:$C,MATCH("End Year",Inputs!$B:$B,0))*12,IF(OR(D51=0,D$3<INDEX(Inputs!$C:$C,MATCH("*Bank Loan PMT Start Month*",Inputs!$B:$B,0))),0,-D51*INDEX(Inputs!$C:$C,MATCH("*Bank Loan Interest Rate*",Inputs!$B:$B,0))/12),0)} -> 0 | E53: {=IF(E$3<=INDEX(Inputs!$C:$C,MATCH("End Year",Inputs!$B:$B,0))*12,IF(OR(E51=0,E$3<INDEX(Inputs!$C:$C,MATCH("*Bank Loan PMT Start Month*",Inputs!$B:$B,0))),0,-E51*INDEX(Inputs!$C:$C,MATCH("*Bank Loan Interest Rate*",Inputs!$B:$B,0))/12),0)} -> 0 | F53: {=IF(F$3<=INDEX(Inputs!$C:$C,MATCH("End Year",Inputs!$B:$B,0))*12,IF(OR(F51=0,F$3<INDEX(Inputs!$C:$C,MATCH("*Bank Loan PMT Start Month*",Inputs!$B:$B,0))),0,-F51*INDEX(Inputs!$C:$C,MATCH("*Bank Loan Interest Rate*",Inputs!$B:$B,0))/12),0)} -> 0 | G53: {=IF(G$3<=INDEX(Inputs!$C:$C,MATCH("End Year",Inputs!$B:$B,0))*12,IF(OR(G51=0,G$3<INDEX(Inputs!$C:$C,MATCH("*Bank Loan PMT Start Month*",Inputs!$B:$B,0))),0,-G51*INDEX(Inputs!$C:$C,MATCH("*Bank Loan Interest Rate*",Inputs!$B:$B,0))/12),0)} -> 0 | H53: {=IF(H$3<=INDEX(Inputs!$C:$C,MATCH("End Year",Inputs!$B:$B,0))*12,IF(OR(H51=0,H$3<INDEX(Inputs!$C:$C,MATCH("*Bank Loan PMT Start Month*",Inputs!$B:$B,0))),0,-H51*INDEX(Inputs!$C:$C,MATCH("*Bank Loan Interest Rate*",Inputs!$B:$B,0))/12),0)} -> 0 | I53: {=IF(I$3<=INDEX(Inputs!$C:$C,MATCH("End Year",Inputs!$B:$B,0))*12,IF(OR(I51=0,I$3<INDEX(Inputs!$C:$C,MATCH("*Bank Loan PMT Start Month*",Inputs!$B:$B,0))),0,-I51*INDEX(Inputs!$C:$C,MATCH("*Bank Loan Interest Rate*",Inputs!$B:$B,0))/12),0)} -> 0 | J53: {=IF(J$3<=INDEX(Inputs!$C:$C,MATCH("End Year",Inputs!$B:$B,0))*12,IF(OR(J51=0,J$3<INDEX(Inputs!$C:$C,MATCH("*Bank Loan PMT Start Month*",Inputs!$B:$B,0))),0,-J51*INDEX(Inputs!$C:$C,MATCH("*Bank Loan Interest Rate*",Inputs!$B:$B,0))/12),0)} -> 0 | ... DS53: {=IF(DS$3<=INDEX(Inputs!$C:$C,MATCH("End Year",Inputs!$B:$B,0))*12,IF(OR(DS51=0,DS$3<INDEX(Inputs!$C:$C,MATCH("*Bank Loan PMT Start Month*",Inputs!$B:$B,0))),0,-DS51*INDEX(Inputs!$C:$C,MATCH("*Bank Loan Interest Rate*",Inputs!$B:$B,0))/12),0)} -> 0
B54: Principal Payment | C54: {=IF(C$3<=INDEX(Inputs!$C:$C,MATCH("End Year",Inputs!$B:$B,0))*12,IF(OR(C51=0,C$3<INDEX(Inputs!$C:$C,MATCH("*Bank Loan PMT Start Month*",Inputs!$B:$B,0))),0,IF(C$3-INDEX(Inputs!$C:$C,MATCH("*Bank Loan PMT Start Month*",Inputs!$B:$B,0))+1<=INDEX(Inputs!$C:$C,MATCH("*Bank Loan IO Period*",Inputs!$B:$B,0)),0,MIN(PMT(INDEX(Inputs!$C:$C,MATCH("*Bank Loan Interest Rate*",Inputs!$B:$B,0))/12,INDEX(Inputs!$C:$C,MATCH("*Bank Loan Amortization*",Inputs!$B:$B,0))*12,-INDEX(Inputs!$C:$C,MATCH("*Bank Loan Amount*",Inputs!$B:$B,0)))-C51*INDEX(Inputs!$C:$C,MATCH("*Bank Loan Interest Rate*",Inputs!$B:$B,0))/12,C51))),0)} -> 0 | D54: {=IF(D$3<=INDEX(Inputs!$C:$C,MATCH("End Year",Inputs!$B:$B,0))*12,IF(OR(D51=0,D$3<INDEX(Inputs!$C:$C,MATCH("*Bank Loan PMT Start Month*",Inputs!$B:$B,0))),0,IF(D$3-INDEX(Inputs!$C:$C,MATCH("*Bank Loan PMT Start Month*",Inputs!$B:$B,0))+1<=INDEX(Inputs!$C:$C,MATCH("*Bank Loan IO Period*",Inputs!$B:$B,0)),0,MIN(PMT(INDEX(Inputs!$C:$C,MATCH("*Bank Loan Interest Rate*",Inputs!$B:$B,0))/12,INDEX(Inputs!$C:$C,MATCH("*Bank Loan Amortization*",Inputs!$B:$B,0))*12,-INDEX(Inputs!$C:$C,MATCH("*Bank Loan Amount*",Inputs!$B:$B,0)))-D51*INDEX(Inputs!$C:$C,MATCH("*Bank Loan Interest Rate*",Inputs!$B:$B,0))/12,D51))),0)} -> 0 | E54: {=IF(E$3<=INDEX(Inputs!$C:$C,MATCH("End Year",Inputs!$B:$B,0))*12,IF(OR(E51=0,E$3<INDEX(Inputs!$C:$C,MATCH("*Bank Loan PMT Start Month*",Inputs!$B:$B,0))),0,IF(E$3-INDEX(Inputs!$C:$C,MATCH("*Bank Loan PMT Start Month*",Inputs!$B:$B,0))+1<=INDEX(Inputs!$C:$C,MATCH("*Bank Loan IO Period*",Inputs!$B:$B,0)),0,MIN(PMT(INDEX(Inputs!$C:$C,MATCH("*Bank Loan Interest Rate*",Inputs!$B:$B,0))/12,INDEX(Inputs!$C:$C,MATCH("*Bank Loan Amortization*",Inputs!$B:$B,0))*12,-INDEX(Inputs!$C:$C,MATCH("*Bank Loan Amount*",Inputs!$B:$B,0)))-E51*INDEX(Inputs!$C:$C,MATCH("*Bank Loan Interest Rate*",Inputs!$B:$B,0))/12,E51))),0)} -> 0 | F54: {=IF(F$3<=INDEX(Inputs!$C:$C,MATCH("End Year",Inputs!$B:$B,0))*12,IF(OR(F51=0,F$3<INDEX(Inputs!$C:$C,MATCH("*Bank Loan PMT Start Month*",Inputs!$B:$B,0))),0,IF(F$3-INDEX(Inputs!$C:$C,MATCH("*Bank Loan PMT Start Month*",Inputs!$B:$B,0))+1<=INDEX(Inputs!$C:$C,MATCH("*Bank Loan IO Period*",Inputs!$B:$B,0)),0,MIN(PMT(INDEX(Inputs!$C:$C,MATCH("*Bank Loan Interest Rate*",Inputs!$B:$B,0))/12,INDEX(Inputs!$C:$C,MATCH("*Bank Loan Amortization*",Inputs!$B:$B,0))*12,-INDEX(Inputs!$C:$C,MATCH("*Bank Loan Amount*",Inputs!$B:$B,0)))-F51*INDEX(Inputs!$C:$C,MATCH("*Bank Loan Interest Rate*",Inputs!$B:$B,0))/12,F51))),0)} -> 0 | G54: {=IF(G$3<=INDEX(Inputs!$C:$C,MATCH("End Year",Inputs!$B:$B,0))*12,IF(OR(G51=0,G$3<INDEX(Inputs!$C:$C,MATCH("*Bank Loan PMT Start Month*",Inputs!$B:$B,0))),0,IF(G$3-INDEX(Inputs!$C:$C,MATCH("*Bank Loan PMT Start Month*",Inputs!$B:$B,0))+1<=INDEX(Inputs!$C:$C,MATCH("*Bank Loan IO Period*",Inputs!$B:$B,0)),0,MIN(PMT(INDEX(Inputs!$C:$C,MATCH("*Bank Loan Interest Rate*",Inputs!$B:$B,0))/12,INDEX(Inputs!$C:$C,MATCH("*Bank Loan Amortization*",Inputs!$B:$B,0))*12,-INDEX(Inputs!$C:$C,MATCH("*Bank Loan Amount*",Inputs!$B:$B,0)))-G51*INDEX(Inputs!$C:$C,MATCH("*Bank Loan Interest Rate*",Inputs!$B:$B,0))/12,G51))),0)} -> 0 | H54: {=IF(H$3<=INDEX(Inputs!$C:$C,MATCH("End Year",Inputs!$B:$B,0))*12,IF(OR(H51=0,H$3<INDEX(Inputs!$C:$C,MATCH("*Bank Loan PMT Start Month*",Inputs!$B:$B,0))),0,IF(H$3-INDEX(Inputs!$C:$C,MATCH("*Bank Loan PMT Start Month*",Inputs!$B:$B,0))+1<=INDEX(Inputs!$C:$C,MATCH("*Bank Loan IO Period*",Inputs!$B:$B,0)),0,MIN(PMT(INDEX(Inputs!$C:$C,MATCH("*Bank Loan Interest Rate*",Inputs!$B:$B,0))/12,INDEX(Inputs!$C:$C,MATCH("*Bank Loan Amortization*",Inputs!$B:$B,0))*12,-INDEX(Inputs!$C:$C,MATCH("*Bank Loan Amount*",Inputs!$B:$B,0)))-H51*INDEX(Inputs!$C:$C,MATCH("*Bank Loan Interest Rate*",Inputs!$B:$B,0))/12,H51))),0)} -> 0 | I54: {=IF(I$3<=INDEX(Inputs!$C:$C,MATCH("End Year",Inputs!$B:$B,0))*12,IF(OR(I51=0,I$3<INDEX(Inputs!$C:$C,MATCH("*Bank Loan PMT Start Month*",Inputs!$B:$B,0))),0,IF(I$3-INDEX(Inputs!$C:$C,MATCH("*Bank Loan PMT Start Month*",Inputs!$B:$B,0))+1<=INDEX(Inputs!$C:$C,MATCH("*Bank Loan IO Period*",Inputs!$B:$B,0)),0,MIN(PMT(INDEX(Inputs!$C:$C,MATCH("*Bank Loan Interest Rate*",Inputs!$B:$B,0))/12,INDEX(Inputs!$C:$C,MATCH("*Bank Loan Amortization*",Inputs!$B:$B,0))*12,-INDEX(Inputs!$C:$C,MATCH("*Bank Loan Amount*",Inputs!$B:$B,0)))-I51*INDEX(Inputs!$C:$C,MATCH("*Bank Loan Interest Rate*",Inputs!$B:$B,0))/12,I51))),0)} -> 0 | J54: {=IF(J$3<=INDEX(Inputs!$C:$C,MATCH("End Year",Inputs!$B:$B,0))*12,IF(OR(J51=0,J$3<INDEX(Inputs!$C:$C,MATCH("*Bank Loan PMT Start Month*",Inputs!$B:$B,0))),0,IF(J$3-INDEX(Inputs!$C:$C,MATCH("*Bank Loan PMT Start Month*",Inputs!$B:$B,0))+1<=INDEX(Inputs!$C:$C,MATCH("*Bank Loan IO Period*",Inputs!$B:$B,0)),0,MIN(PMT(INDEX(Inputs!$C:$C,MATCH("*Bank Loan Interest Rate*",Inputs!$B:$B,0))/12,INDEX(Inputs!$C:$C,MATCH("*Bank Loan Amortization*",Inputs!$B:$B,0))*12,-INDEX(Inputs!$C:$C,MATCH("*Bank Loan Amount*",Inputs!$B:$B,0)))-J51*INDEX(Inputs!$C:$C,MATCH("*Bank Loan Interest Rate*",Inputs!$B:$B,0))/12,J51))),0)} -> 0 | ... DS54: {=IF(DS$3<=INDEX(Inputs!$C:$C,MATCH("End Year",Inputs!$B:$B,0))*12,IF(OR(DS51=0,DS$3<INDEX(Inputs!$C:$C,MATCH("*Bank Loan PMT Start Month*",Inputs!$B:$B,0))),0,IF(DS$3-INDEX(Inputs!$C:$C,MATCH("*Bank Loan PMT Start Month*",Inputs!$B:$B,0))+1<=INDEX(Inputs!$C:$C,MATCH("*Bank Loan IO Period*",Inputs!$B:$B,0)),0,MIN(PMT(INDEX(Inputs!$C:$C,MATCH("*Bank Loan Interest Rate*",Inputs!$B:$B,0))/12,INDEX(Inputs!$C:$C,MATCH("*Bank Loan Amortization*",Inputs!$B:$B,0))*12,-INDEX(Inputs!$C:$C,MATCH("*Bank Loan Amount*",Inputs!$B:$B,0)))-DS51*INDEX(Inputs!$C:$C,MATCH("*Bank Loan Interest Rate*",Inputs!$B:$B,0))/12,DS51))),0)} -> 0
B55: Loan Payoff / Refi Payoff | C55: {=IF(C$3<=INDEX(Inputs!$C:$C,MATCH("End Year",Inputs!$B:$B,0))*12,IF(OR(C$3=INDEX(Inputs!$C:$C,MATCH("*Bank Loan Balloon*",Inputs!$B:$B,0))*12,C$3=INDEX(Inputs!$C:$C,MATCH("End Year",Inputs!$B:$B,0))*12),-MAX(C51+C52-C54,0),0),0)} -> 0 | D55: {=IF(D$3<=INDEX(Inputs!$C:$C,MATCH("End Year",Inputs!$B:$B,0))*12,IF(OR(D$3=INDEX(Inputs!$C:$C,MATCH("*Bank Loan Balloon*",Inputs!$B:$B,0))*12,D$3=INDEX(Inputs!$C:$C,MATCH("End Year",Inputs!$B:$B,0))*12),-MAX(D51+D52-D54,0),0),0)} -> 0 | E55: {=IF(E$3<=INDEX(Inputs!$C:$C,MATCH("End Year",Inputs!$B:$B,0))*12,IF(OR(E$3=INDEX(Inputs!$C:$C,MATCH("*Bank Loan Balloon*",Inputs!$B:$B,0))*12,E$3=INDEX(Inputs!$C:$C,MATCH("End Year",Inputs!$B:$B,0))*12),-MAX(E51+E52-E54,0),0),0)} -> 0 | F55: {=IF(F$3<=INDEX(Inputs!$C:$C,MATCH("End Year",Inputs!$B:$B,0))*12,IF(OR(F$3=INDEX(Inputs!$C:$C,MATCH("*Bank Loan Balloon*",Inputs!$B:$B,0))*12,F$3=INDEX(Inputs!$C:$C,MATCH("End Year",Inputs!$B:$B,0))*12),-MAX(F51+F52-F54,0),0),0)} -> 0 | G55: {=IF(G$3<=INDEX(Inputs!$C:$C,MATCH("End Year",Inputs!$B:$B,0))*12,IF(OR(G$3=INDEX(Inputs!$C:$C,MATCH("*Bank Loan Balloon*",Inputs!$B:$B,0))*12,G$3=INDEX(Inputs!$C:$C,MATCH("End Year",Inputs!$B:$B,0))*12),-MAX(G51+G52-G54,0),0),0)} -> 0 | H55: {=IF(H$3<=INDEX(Inputs!$C:$C,MATCH("End Year",Inputs!$B:$B,0))*12,IF(OR(H$3=INDEX(Inputs!$C:$C,MATCH("*Bank Loan Balloon*",Inputs!$B:$B,0))*12,H$3=INDEX(Inputs!$C:$C,MATCH("End Year",Inputs!$B:$B,0))*12),-MAX(H51+H52-H54,0),0),0)} -> 0 | I55: {=IF(I$3<=INDEX(Inputs!$C:$C,MATCH("End Year",Inputs!$B:$B,0))*12,IF(OR(I$3=INDEX(Inputs!$C:$C,MATCH("*Bank Loan Balloon*",Inputs!$B:$B,0))*12,I$3=INDEX(Inputs!$C:$C,MATCH("End Year",Inputs!$B:$B,0))*12),-MAX(I51+I52-I54,0),0),0)} -> 0 | J55: {=IF(J$3<=INDEX(Inputs!$C:$C,MATCH("End Year",Inputs!$B:$B,0))*12,IF(OR(J$3=INDEX(Inputs!$C:$C,MATCH("*Bank Loan Balloon*",Inputs!$B:$B,0))*12,J$3=INDEX(Inputs!$C:$C,MATCH("End Year",Inputs!$B:$B,0))*12),-MAX(J51+J52-J54,0),0),0)} -> 0 | ... DS55: {=IF(DS$3<=INDEX(Inputs!$C:$C,MATCH("End Year",Inputs!$B:$B,0))*12,IF(OR(DS$3=INDEX(Inputs!$C:$C,MATCH("*Bank Loan Balloon*",Inputs!$B:$B,0))*12,DS$3=INDEX(Inputs!$C:$C,MATCH("End Year",Inputs!$B:$B,0))*12),-MAX(DS51+DS52-DS54,0),0),0)} -> 0
B56: Ending Balance | C56: {=IF(C$3<=INDEX(Inputs!$C:$C,MATCH("End Year",Inputs!$B:$B,0))*12,MAX(C51+C52-C54+C55,0),0)} -> 0 | D56: {=IF(D$3<=INDEX(Inputs!$C:$C,MATCH("End Year",Inputs!$B:$B,0))*12,MAX(D51+D52-D54+D55,0),0)} -> 0 | E56: {=IF(E$3<=INDEX(Inputs!$C:$C,MATCH("End Year",Inputs!$B:$B,0))*12,MAX(E51+E52-E54+E55,0),0)} -> 0 | F56: {=IF(F$3<=INDEX(Inputs!$C:$C,MATCH("End Year",Inputs!$B:$B,0))*12,MAX(F51+F52-F54+F55,0),0)} -> 0 | G56: {=IF(G$3<=INDEX(Inputs!$C:$C,MATCH("End Year",Inputs!$B:$B,0))*12,MAX(G51+G52-G54+G55,0),0)} -> 0 | H56: {=IF(H$3<=INDEX(Inputs!$C:$C,MATCH("End Year",Inputs!$B:$B,0))*12,MAX(H51+H52-H54+H55,0),0)} -> 0 | I56: {=IF(I$3<=INDEX(Inputs!$C:$C,MATCH("End Year",Inputs!$B:$B,0))*12,MAX(I51+I52-I54+I55,0),0)} -> 0 | J56: {=IF(J$3<=INDEX(Inputs!$C:$C,MATCH("End Year",Inputs!$B:$B,0))*12,MAX(J51+J52-J54+J55,0),0)} -> 0 | ... DS56: {=IF(DS$3<=INDEX(Inputs!$C:$C,MATCH("End Year",Inputs!$B:$B,0))*12,MAX(DS51+DS52-DS54+DS55,0),0)} -> 0
B57: Total Debt Service (BL) | C57: {=IF(C$3<=INDEX(Inputs!$C:$C,MATCH("End Year",Inputs!$B:$B,0))*12,C53-C54+C55,0)} -> 0 | D57: {=IF(D$3<=INDEX(Inputs!$C:$C,MATCH("End Year",Inputs!$B:$B,0))*12,D53-D54+D55,0)} -> 0 | E57: {=IF(E$3<=INDEX(Inputs!$C:$C,MATCH("End Year",Inputs!$B:$B,0))*12,E53-E54+E55,0)} -> 0 | F57: {=IF(F$3<=INDEX(Inputs!$C:$C,MATCH("End Year",Inputs!$B:$B,0))*12,F53-F54+F55,0)} -> 0 | G57: {=IF(G$3<=INDEX(Inputs!$C:$C,MATCH("End Year",Inputs!$B:$B,0))*12,G53-G54+G55,0)} -> 0 | H57: {=IF(H$3<=INDEX(Inputs!$C:$C,MATCH("End Year",Inputs!$B:$B,0))*12,H53-H54+H55,0)} -> 0 | I57: {=IF(I$3<=INDEX(Inputs!$C:$C,MATCH("End Year",Inputs!$B:$B,0))*12,I53-I54+I55,0)} -> 0 | J57: {=IF(J$3<=INDEX(Inputs!$C:$C,MATCH("End Year",Inputs!$B:$B,0))*12,J53-J54+J55,0)} -> 0 | ... DS57: {=IF(DS$3<=INDEX(Inputs!$C:$C,MATCH("End Year",Inputs!$B:$B,0))*12,DS53-DS54+DS55,0)} -> 0
B59: DEBT SERVICE — REFINANCE LOAN
B60: Beginning Balance | C60: 0 | D60: {=IF(D$3<=INDEX(Inputs!$C:$C,MATCH("End Year",Inputs!$B:$B,0))*12,IF(D$3<=INDEX(Inputs!$C:$C,MATCH("Refi Year",Inputs!$B:$B,0))*12,0,C65),0)} -> 0 | E60: {=IF(E$3<=INDEX(Inputs!$C:$C,MATCH("End Year",Inputs!$B:$B,0))*12,IF(E$3<=INDEX(Inputs!$C:$C,MATCH("Refi Year",Inputs!$B:$B,0))*12,0,D65),0)} -> 0 | F60: {=IF(F$3<=INDEX(Inputs!$C:$C,MATCH("End Year",Inputs!$B:$B,0))*12,IF(F$3<=INDEX(Inputs!$C:$C,MATCH("Refi Year",Inputs!$B:$B,0))*12,0,E65),0)} -> 0 | G60: {=IF(G$3<=INDEX(Inputs!$C:$C,MATCH("End Year",Inputs!$B:$B,0))*12,IF(G$3<=INDEX(Inputs!$C:$C,MATCH("Refi Year",Inputs!$B:$B,0))*12,0,F65),0)} -> 0 | H60: {=IF(H$3<=INDEX(Inputs!$C:$C,MATCH("End Year",Inputs!$B:$B,0))*12,IF(H$3<=INDEX(Inputs!$C:$C,MATCH("Refi Year",Inputs!$B:$B,0))*12,0,G65),0)} -> 0 | I60: {=IF(I$3<=INDEX(Inputs!$C:$C,MATCH("End Year",Inputs!$B:$B,0))*12,IF(I$3<=INDEX(Inputs!$C:$C,MATCH("Refi Year",Inputs!$B:$B,0))*12,0,H65),0)} -> 0 | J60: {=IF(J$3<=INDEX(Inputs!$C:$C,MATCH("End Year",Inputs!$B:$B,0))*12,IF(J$3<=INDEX(Inputs!$C:$C,MATCH("Refi Year",Inputs!$B:$B,0))*12,0,I65),0)} -> 0 | K60: {=IF(K$3<=INDEX(Inputs!$C:$C,MATCH("End Year",Inputs!$B:$B,0))*12,IF(K$3<=INDEX(Inputs!$C:$C,MATCH("Refi Year",Inputs!$B:$B,0))*12,0,J65),0)} -> 0 | ... DS60: {=IF(DS$3<=INDEX(Inputs!$C:$C,MATCH("End Year",Inputs!$B:$B,0))*12,IF(DS$3<=INDEX(Inputs!$C:$C,MATCH("Refi Year",Inputs!$B:$B,0))*12,0,DR65),0)} -> 0
B61: Loan Funding | C61: {=IF(C$3<=INDEX(Inputs!$C:$C,MATCH("End Year",Inputs!$B:$B,0))*12,IF(C$3=INDEX(Inputs!$C:$C,MATCH("Refi Year",Inputs!$B:$B,0))*12+1,INDEX(Inputs!$C:$C,MATCH("*Refi Loan Amount*",Inputs!$B:$B,0)),0),0)} -> 0 | D61: {=IF(D$3<=INDEX(Inputs!$C:$C,MATCH("End Year",Inputs!$B:$B,0))*12,IF(D$3=INDEX(Inputs!$C:$C,MATCH("Refi Year",Inputs!$B:$B,0))*12+1,INDEX(Inputs!$C:$C,MATCH("*Refi Loan Amount*",Inputs!$B:$B,0)),0),0)} -> 0 | E61: {=IF(E$3<=INDEX(Inputs!$C:$C,MATCH("End Year",Inputs!$B:$B,0))*12,IF(E$3=INDEX(Inputs!$C:$C,MATCH("Refi Year",Inputs!$B:$B,0))*12+1,INDEX(Inputs!$C:$C,MATCH("*Refi Loan Amount*",Inputs!$B:$B,0)),0),0)} -> 0 | F61: {=IF(F$3<=INDEX(Inputs!$C:$C,MATCH("End Year",Inputs!$B:$B,0))*12,IF(F$3=INDEX(Inputs!$C:$C,MATCH("Refi Year",Inputs!$B:$B,0))*12+1,INDEX(Inputs!$C:$C,MATCH("*Refi Loan Amount*",Inputs!$B:$B,0)),0),0)} -> 0 | G61: {=IF(G$3<=INDEX(Inputs!$C:$C,MATCH("End Year",Inputs!$B:$B,0))*12,IF(G$3=INDEX(Inputs!$C:$C,MATCH("Refi Year",Inputs!$B:$B,0))*12+1,INDEX(Inputs!$C:$C,MATCH("*Refi Loan Amount*",Inputs!$B:$B,0)),0),0)} -> 0 | H61: {=IF(H$3<=INDEX(Inputs!$C:$C,MATCH("End Year",Inputs!$B:$B,0))*12,IF(H$3=INDEX(Inputs!$C:$C,MATCH("Refi Year",Inputs!$B:$B,0))*12+1,INDEX(Inputs!$C:$C,MATCH("*Refi Loan Amount*",Inputs!$B:$B,0)),0),0)} -> 0 | I61: {=IF(I$3<=INDEX(Inputs!$C:$C,MATCH("End Year",Inputs!$B:$B,0))*12,IF(I$3=INDEX(Inputs!$C:$C,MATCH("Refi Year",Inputs!$B:$B,0))*12+1,INDEX(Inputs!$C:$C,MATCH("*Refi Loan Amount*",Inputs!$B:$B,0)),0),0)} -> 0 | J61: {=IF(J$3<=INDEX(Inputs!$C:$C,MATCH("End Year",Inputs!$B:$B,0))*12,IF(J$3=INDEX(Inputs!$C:$C,MATCH("Refi Year",Inputs!$B:$B,0))*12+1,INDEX(Inputs!$C:$C,MATCH("*Refi Loan Amount*",Inputs!$B:$B,0)),0),0)} -> 0 | ... DS61: {=IF(DS$3<=INDEX(Inputs!$C:$C,MATCH("End Year",Inputs!$B:$B,0))*12,IF(DS$3=INDEX(Inputs!$C:$C,MATCH("Refi Year",Inputs!$B:$B,0))*12+1,INDEX(Inputs!$C:$C,MATCH("*Refi Loan Amount*",Inputs!$B:$B,0)),0),0)} -> 0
B62: Interest Payment | C62: {=IF(C$3<=INDEX(Inputs!$C:$C,MATCH("End Year",Inputs!$B:$B,0))*12,IF(C60=0,0,-C60*INDEX(Inputs!$C:$C,MATCH("*Refi Interest Rate*",Inputs!$B:$B,0))/12),0)} -> 0 | D62: {=IF(D$3<=INDEX(Inputs!$C:$C,MATCH("End Year",Inputs!$B:$B,0))*12,IF(D60=0,0,-D60*INDEX(Inputs!$C:$C,MATCH("*Refi Interest Rate*",Inputs!$B:$B,0))/12),0)} -> 0 | E62: {=IF(E$3<=INDEX(Inputs!$C:$C,MATCH("End Year",Inputs!$B:$B,0))*12,IF(E60=0,0,-E60*INDEX(Inputs!$C:$C,MATCH("*Refi Interest Rate*",Inputs!$B:$B,0))/12),0)} -> 0 | F62: {=IF(F$3<=INDEX(Inputs!$C:$C,MATCH("End Year",Inputs!$B:$B,0))*12,IF(F60=0,0,-F60*INDEX(Inputs!$C:$C,MATCH("*Refi Interest Rate*",Inputs!$B:$B,0))/12),0)} -> 0 | G62: {=IF(G$3<=INDEX(Inputs!$C:$C,MATCH("End Year",Inputs!$B:$B,0))*12,IF(G60=0,0,-G60*INDEX(Inputs!$C:$C,MATCH("*Refi Interest Rate*",Inputs!$B:$B,0))/12),0)} -> 0 | H62: {=IF(H$3<=INDEX(Inputs!$C:$C,MATCH("End Year",Inputs!$B:$B,0))*12,IF(H60=0,0,-H60*INDEX(Inputs!$C:$C,MATCH("*Refi Interest Rate*",Inputs!$B:$B,0))/12),0)} -> 0 | I62: {=IF(I$3<=INDEX(Inputs!$C:$C,MATCH("End Year",Inputs!$B:$B,0))*12,IF(I60=0,0,-I60*INDEX(Inputs!$C:$C,MATCH("*Refi Interest Rate*",Inputs!$B:$B,0))/12),0)} -> 0 | J62: {=IF(J$3<=INDEX(Inputs!$C:$C,MATCH("End Year",Inputs!$B:$B,0))*12,IF(J60=0,0,-J60*INDEX(Inputs!$C:$C,MATCH("*Refi Interest Rate*",Inputs!$B:$B,0))/12),0)} -> 0 | ... DS62: {=IF(DS$3<=INDEX(Inputs!$C:$C,MATCH("End Year",Inputs!$B:$B,0))*12,IF(DS60=0,0,-DS60*INDEX(Inputs!$C:$C,MATCH("*Refi Interest Rate*",Inputs!$B:$B,0))/12),0)} -> 0
B63: Principal Payment | C63: {=IF(C$3<=INDEX(Inputs!$C:$C,MATCH("End Year",Inputs!$B:$B,0))*12,IF(C60=0,0,IF(C$3-INDEX(Inputs!$C:$C,MATCH("Refi Year",Inputs!$B:$B,0))*12<=INDEX(Inputs!$C:$C,MATCH("*Refi IO Period*",Inputs!$B:$B,0)),0,MIN(IFERROR(PMT(INDEX(Inputs!$C:$C,MATCH("*Refi Interest Rate*",Inputs!$B:$B,0))/12,INDEX(Inputs!$C:$C,MATCH("*Refi Amortization*",Inputs!$B:$B,0))*12,-INDEX(Inputs!$C:$C,MATCH("*Refi Loan Amount*",Inputs!$B:$B,0))),0)-C60*INDEX(Inputs!$C:$C,MATCH("*Refi Interest Rate*",Inputs!$B:$B,0))/12,C60))),0)} -> 0 | D63: {=IF(D$3<=INDEX(Inputs!$C:$C,MATCH("End Year",Inputs!$B:$B,0))*12,IF(D60=0,0,IF(D$3-INDEX(Inputs!$C:$C,MATCH("Refi Year",Inputs!$B:$B,0))*12<=INDEX(Inputs!$C:$C,MATCH("*Refi IO Period*",Inputs!$B:$B,0)),0,MIN(IFERROR(PMT(INDEX(Inputs!$C:$C,MATCH("*Refi Interest Rate*",Inputs!$B:$B,0))/12,INDEX(Inputs!$C:$C,MATCH("*Refi Amortization*",Inputs!$B:$B,0))*12,-INDEX(Inputs!$C:$C,MATCH("*Refi Loan Amount*",Inputs!$B:$B,0))),0)-D60*INDEX(Inputs!$C:$C,MATCH("*Refi Interest Rate*",Inputs!$B:$B,0))/12,D60))),0)} -> 0 | E63: {=IF(E$3<=INDEX(Inputs!$C:$C,MATCH("End Year",Inputs!$B:$B,0))*12,IF(E60=0,0,IF(E$3-INDEX(Inputs!$C:$C,MATCH("Refi Year",Inputs!$B:$B,0))*12<=INDEX(Inputs!$C:$C,MATCH("*Refi IO Period*",Inputs!$B:$B,0)),0,MIN(IFERROR(PMT(INDEX(Inputs!$C:$C,MATCH("*Refi Interest Rate*",Inputs!$B:$B,0))/12,INDEX(Inputs!$C:$C,MATCH("*Refi Amortization*",Inputs!$B:$B,0))*12,-INDEX(Inputs!$C:$C,MATCH("*Refi Loan Amount*",Inputs!$B:$B,0))),0)-E60*INDEX(Inputs!$C:$C,MATCH("*Refi Interest Rate*",Inputs!$B:$B,0))/12,E60))),0)} -> 0 | F63: {=IF(F$3<=INDEX(Inputs!$C:$C,MATCH("End Year",Inputs!$B:$B,0))*12,IF(F60=0,0,IF(F$3-INDEX(Inputs!$C:$C,MATCH("Refi Year",Inputs!$B:$B,0))*12<=INDEX(Inputs!$C:$C,MATCH("*Refi IO Period*",Inputs!$B:$B,0)),0,MIN(IFERROR(PMT(INDEX(Inputs!$C:$C,MATCH("*Refi Interest Rate*",Inputs!$B:$B,0))/12,INDEX(Inputs!$C:$C,MATCH("*Refi Amortization*",Inputs!$B:$B,0))*12,-INDEX(Inputs!$C:$C,MATCH("*Refi Loan Amount*",Inputs!$B:$B,0))),0)-F60*INDEX(Inputs!$C:$C,MATCH("*Refi Interest Rate*",Inputs!$B:$B,0))/12,F60))),0)} -> 0 | G63: {=IF(G$3<=INDEX(Inputs!$C:$C,MATCH("End Year",Inputs!$B:$B,0))*12,IF(G60=0,0,IF(G$3-INDEX(Inputs!$C:$C,MATCH("Refi Year",Inputs!$B:$B,0))*12<=INDEX(Inputs!$C:$C,MATCH("*Refi IO Period*",Inputs!$B:$B,0)),0,MIN(IFERROR(PMT(INDEX(Inputs!$C:$C,MATCH("*Refi Interest Rate*",Inputs!$B:$B,0))/12,INDEX(Inputs!$C:$C,MATCH("*Refi Amortization*",Inputs!$B:$B,0))*12,-INDEX(Inputs!$C:$C,MATCH("*Refi Loan Amount*",Inputs!$B:$B,0))),0)-G60*INDEX(Inputs!$C:$C,MATCH("*Refi Interest Rate*",Inputs!$B:$B,0))/12,G60))),0)} -> 0 | H63: {=IF(H$3<=INDEX(Inputs!$C:$C,MATCH("End Year",Inputs!$B:$B,0))*12,IF(H60=0,0,IF(H$3-INDEX(Inputs!$C:$C,MATCH("Refi Year",Inputs!$B:$B,0))*12<=INDEX(Inputs!$C:$C,MATCH("*Refi IO Period*",Inputs!$B:$B,0)),0,MIN(IFERROR(PMT(INDEX(Inputs!$C:$C,MATCH("*Refi Interest Rate*",Inputs!$B:$B,0))/12,INDEX(Inputs!$C:$C,MATCH("*Refi Amortization*",Inputs!$B:$B,0))*12,-INDEX(Inputs!$C:$C,MATCH("*Refi Loan Amount*",Inputs!$B:$B,0))),0)-H60*INDEX(Inputs!$C:$C,MATCH("*Refi Interest Rate*",Inputs!$B:$B,0))/12,H60))),0)} -> 0 | I63: {=IF(I$3<=INDEX(Inputs!$C:$C,MATCH("End Year",Inputs!$B:$B,0))*12,IF(I60=0,0,IF(I$3-INDEX(Inputs!$C:$C,MATCH("Refi Year",Inputs!$B:$B,0))*12<=INDEX(Inputs!$C:$C,MATCH("*Refi IO Period*",Inputs!$B:$B,0)),0,MIN(IFERROR(PMT(INDEX(Inputs!$C:$C,MATCH("*Refi Interest Rate*",Inputs!$B:$B,0))/12,INDEX(Inputs!$C:$C,MATCH("*Refi Amortization*",Inputs!$B:$B,0))*12,-INDEX(Inputs!$C:$C,MATCH("*Refi Loan Amount*",Inputs!$B:$B,0))),0)-I60*INDEX(Inputs!$C:$C,MATCH("*Refi Interest Rate*",Inputs!$B:$B,0))/12,I60))),0)} -> 0 | J63: {=IF(J$3<=INDEX(Inputs!$C:$C,MATCH("End Year",Inputs!$B:$B,0))*12,IF(J60=0,0,IF(J$3-INDEX(Inputs!$C:$C,MATCH("Refi Year",Inputs!$B:$B,0))*12<=INDEX(Inputs!$C:$C,MATCH("*Refi IO Period*",Inputs!$B:$B,0)),0,MIN(IFERROR(PMT(INDEX(Inputs!$C:$C,MATCH("*Refi Interest Rate*",Inputs!$B:$B,0))/12,INDEX(Inputs!$C:$C,MATCH("*Refi Amortization*",Inputs!$B:$B,0))*12,-INDEX(Inputs!$C:$C,MATCH("*Refi Loan Amount*",Inputs!$B:$B,0))),0)-J60*INDEX(Inputs!$C:$C,MATCH("*Refi Interest Rate*",Inputs!$B:$B,0))/12,J60))),0)} -> 0 | ... DS63: {=IF(DS$3<=INDEX(Inputs!$C:$C,MATCH("End Year",Inputs!$B:$B,0))*12,IF(DS60=0,0,IF(DS$3-INDEX(Inputs!$C:$C,MATCH("Refi Year",Inputs!$B:$B,0))*12<=INDEX(Inputs!$C:$C,MATCH("*Refi IO Period*",Inputs!$B:$B,0)),0,MIN(IFERROR(PMT(INDEX(Inputs!$C:$C,MATCH("*Refi Interest Rate*",Inputs!$B:$B,0))/12,INDEX(Inputs!$C:$C,MATCH("*Refi Amortization*",Inputs!$B:$B,0))*12,-INDEX(Inputs!$C:$C,MATCH("*Refi Loan Amount*",Inputs!$B:$B,0))),0)-DS60*INDEX(Inputs!$C:$C,MATCH("*Refi Interest Rate*",Inputs!$B:$B,0))/12,DS60))),0)} -> 0
B64: Loan Payoff | C64: {=IF(C$3<=INDEX(Inputs!$C:$C,MATCH("End Year",Inputs!$B:$B,0))*12,IF(OR(C$3=(INDEX(Inputs!$C:$C,MATCH("Refi Year",Inputs!$B:$B,0))+INDEX(Inputs!$C:$C,MATCH("*Refi Term*",Inputs!$B:$B,0)))*12,C$3=INDEX(Inputs!$C:$C,MATCH("End Year",Inputs!$B:$B,0))*12),-MAX(C60+C61-C63,0),0),0)} -> 0 | D64: {=IF(D$3<=INDEX(Inputs!$C:$C,MATCH("End Year",Inputs!$B:$B,0))*12,IF(OR(D$3=(INDEX(Inputs!$C:$C,MATCH("Refi Year",Inputs!$B:$B,0))+INDEX(Inputs!$C:$C,MATCH("*Refi Term*",Inputs!$B:$B,0)))*12,D$3=INDEX(Inputs!$C:$C,MATCH("End Year",Inputs!$B:$B,0))*12),-MAX(D60+D61-D63,0),0),0)} -> 0 | E64: {=IF(E$3<=INDEX(Inputs!$C:$C,MATCH("End Year",Inputs!$B:$B,0))*12,IF(OR(E$3=(INDEX(Inputs!$C:$C,MATCH("Refi Year",Inputs!$B:$B,0))+INDEX(Inputs!$C:$C,MATCH("*Refi Term*",Inputs!$B:$B,0)))*12,E$3=INDEX(Inputs!$C:$C,MATCH("End Year",Inputs!$B:$B,0))*12),-MAX(E60+E61-E63,0),0),0)} -> 0 | F64: {=IF(F$3<=INDEX(Inputs!$C:$C,MATCH("End Year",Inputs!$B:$B,0))*12,IF(OR(F$3=(INDEX(Inputs!$C:$C,MATCH("Refi Year",Inputs!$B:$B,0))+INDEX(Inputs!$C:$C,MATCH("*Refi Term*",Inputs!$B:$B,0)))*12,F$3=INDEX(Inputs!$C:$C,MATCH("End Year",Inputs!$B:$B,0))*12),-MAX(F60+F61-F63,0),0),0)} -> 0 | G64: {=IF(G$3<=INDEX(Inputs!$C:$C,MATCH("End Year",Inputs!$B:$B,0))*12,IF(OR(G$3=(INDEX(Inputs!$C:$C,MATCH("Refi Year",Inputs!$B:$B,0))+INDEX(Inputs!$C:$C,MATCH("*Refi Term*",Inputs!$B:$B,0)))*12,G$3=INDEX(Inputs!$C:$C,MATCH("End Year",Inputs!$B:$B,0))*12),-MAX(G60+G61-G63,0),0),0)} -> 0 | H64: {=IF(H$3<=INDEX(Inputs!$C:$C,MATCH("End Year",Inputs!$B:$B,0))*12,IF(OR(H$3=(INDEX(Inputs!$C:$C,MATCH("Refi Year",Inputs!$B:$B,0))+INDEX(Inputs!$C:$C,MATCH("*Refi Term*",Inputs!$B:$B,0)))*12,H$3=INDEX(Inputs!$C:$C,MATCH("End Year",Inputs!$B:$B,0))*12),-MAX(H60+H61-H63,0),0),0)} -> 0 | I64: {=IF(I$3<=INDEX(Inputs!$C:$C,MATCH("End Year",Inputs!$B:$B,0))*12,IF(OR(I$3=(INDEX(Inputs!$C:$C,MATCH("Refi Year",Inputs!$B:$B,0))+INDEX(Inputs!$C:$C,MATCH("*Refi Term*",Inputs!$B:$B,0)))*12,I$3=INDEX(Inputs!$C:$C,MATCH("End Year",Inputs!$B:$B,0))*12),-MAX(I60+I61-I63,0),0),0)} -> 0 | J64: {=IF(J$3<=INDEX(Inputs!$C:$C,MATCH("End Year",Inputs!$B:$B,0))*12,IF(OR(J$3=(INDEX(Inputs!$C:$C,MATCH("Refi Year",Inputs!$B:$B,0))+INDEX(Inputs!$C:$C,MATCH("*Refi Term*",Inputs!$B:$B,0)))*12,J$3=INDEX(Inputs!$C:$C,MATCH("End Year",Inputs!$B:$B,0))*12),-MAX(J60+J61-J63,0),0),0)} -> 0 | ... DS64: {=IF(DS$3<=INDEX(Inputs!$C:$C,MATCH("End Year",Inputs!$B:$B,0))*12,IF(OR(DS$3=(INDEX(Inputs!$C:$C,MATCH("Refi Year",Inputs!$B:$B,0))+INDEX(Inputs!$C:$C,MATCH("*Refi Term*",Inputs!$B:$B,0)))*12,DS$3=INDEX(Inputs!$C:$C,MATCH("End Year",Inputs!$B:$B,0))*12),-MAX(DS60+DS61-DS63,0),0),0)} -> 0
B65: Ending Balance | C65: {=IF(C$3<=INDEX(Inputs!$C:$C,MATCH("End Year",Inputs!$B:$B,0))*12,MAX(C60+C61-C63+C64,0),0)} -> 0 | D65: {=IF(D$3<=INDEX(Inputs!$C:$C,MATCH("End Year",Inputs!$B:$B,0))*12,MAX(D60+D61-D63+D64,0),0)} -> 0 | E65: {=IF(E$3<=INDEX(Inputs!$C:$C,MATCH("End Year",Inputs!$B:$B,0))*12,MAX(E60+E61-E63+E64,0),0)} -> 0 | F65: {=IF(F$3<=INDEX(Inputs!$C:$C,MATCH("End Year",Inputs!$B:$B,0))*12,MAX(F60+F61-F63+F64,0),0)} -> 0 | G65: {=IF(G$3<=INDEX(Inputs!$C:$C,MATCH("End Year",Inputs!$B:$B,0))*12,MAX(G60+G61-G63+G64,0),0)} -> 0 | H65: {=IF(H$3<=INDEX(Inputs!$C:$C,MATCH("End Year",Inputs!$B:$B,0))*12,MAX(H60+H61-H63+H64,0),0)} -> 0 | I65: {=IF(I$3<=INDEX(Inputs!$C:$C,MATCH("End Year",Inputs!$B:$B,0))*12,MAX(I60+I61-I63+I64,0),0)} -> 0 | J65: {=IF(J$3<=INDEX(Inputs!$C:$C,MATCH("End Year",Inputs!$B:$B,0))*12,MAX(J60+J61-J63+J64,0),0)} -> 0 | ... DS65: {=IF(DS$3<=INDEX(Inputs!$C:$C,MATCH("End Year",Inputs!$B:$B,0))*12,MAX(DS60+DS61-DS63+DS64,0),0)} -> 0
B66: Total Debt Service (Refi) | C66: {=IF(C$3<=INDEX(Inputs!$C:$C,MATCH("End Year",Inputs!$B:$B,0))*12,C62-C63+C64,0)} -> 0 | D66: {=IF(D$3<=INDEX(Inputs!$C:$C,MATCH("End Year",Inputs!$B:$B,0))*12,D62-D63+D64,0)} -> 0 | E66: {=IF(E$3<=INDEX(Inputs!$C:$C,MATCH("End Year",Inputs!$B:$B,0))*12,E62-E63+E64,0)} -> 0 | F66: {=IF(F$3<=INDEX(Inputs!$C:$C,MATCH("End Year",Inputs!$B:$B,0))*12,F62-F63+F64,0)} -> 0 | G66: {=IF(G$3<=INDEX(Inputs!$C:$C,MATCH("End Year",Inputs!$B:$B,0))*12,G62-G63+G64,0)} -> 0 | H66: {=IF(H$3<=INDEX(Inputs!$C:$C,MATCH("End Year",Inputs!$B:$B,0))*12,H62-H63+H64,0)} -> 0 | I66: {=IF(I$3<=INDEX(Inputs!$C:$C,MATCH("End Year",Inputs!$B:$B,0))*12,I62-I63+I64,0)} -> 0 | J66: {=IF(J$3<=INDEX(Inputs!$C:$C,MATCH("End Year",Inputs!$B:$B,0))*12,J62-J63+J64,0)} -> 0 | ... DS66: {=IF(DS$3<=INDEX(Inputs!$C:$C,MATCH("End Year",Inputs!$B:$B,0))*12,DS62-DS63+DS64,0)} -> 0
B68: Equity Contribution (Inflow) | C68: =IF(C$3=1,Inputs!C87,0) -> -345000 | D68: =IF(D$3=1,Inputs!C87,0) -> 0 | E68: =IF(E$3=1,Inputs!C87,0) -> 0 | F68: =IF(F$3=1,Inputs!C87,0) -> 0 | G68: =IF(G$3=1,Inputs!C87,0) -> 0 | H68: =IF(H$3=1,Inputs!C87,0) -> 0 | I68: =IF(I$3=1,Inputs!C87,0) -> 0 | J68: =IF(J$3=1,Inputs!C87,0) -> 0 | K68: =IF(K$3=1,Inputs!C87,0) -> 0 | L68: =IF(L$3=1,Inputs!C87,0) -> 0 | M68: =IF(M$3=1,Inputs!C87,0) -> 0 | N68: =IF(N$3=1,Inputs!C87,0) -> 0 | O68: =IF(O$3=1,Inputs!C87,0) -> 0 | P68: =IF(P$3=1,Inputs!C87,0) -> 0 | Q68: =IF(Q$3=1,Inputs!C87,0) -> 0 | R68: =IF(R$3=1,Inputs!C87,0) -> 0 | S68: =IF(S$3=1,Inputs!C87,0) -> 0 | T68: =IF(T$3=1,Inputs!C87,0) -> 0 | U68: =IF(U$3=1,Inputs!C87,0) -> 0 | V68: =IF(V$3=1,Inputs!C87,0) -> 0 | W68: =IF(W$3=1,Inputs!C87,0) -> 0 | X68: =IF(X$3=1,Inputs!C87,0) -> 0 | Y68: =IF(Y$3=1,Inputs!C87,0) -> 0 | Z68: =IF(Z$3=1,Inputs!C87,0) -> 0 | AA68: =IF(AA$3=1,Inputs!C87,0) -> 0 | AB68: =IF(AB$3=1,Inputs!C87,0) -> 0 | AC68: =IF(AC$3=1,Inputs!C87,0) -> 0 | AD68: =IF(AD$3=1,Inputs!C87,0) -> 0 | AE68: =IF(AE$3=1,Inputs!C87,0) -> 0 | AF68: =IF(AF$3=1,Inputs!C87,0) -> 0 | AG68: =IF(AG$3=1,Inputs!C87,0) -> 0 | AH68: =IF(AH$3=1,Inputs!C87,0) -> 0 | AI68: =IF(AI$3=1,Inputs!C87,0) -> 0 | AJ68: =IF(AJ$3=1,Inputs!C87,0) -> 0 | AK68: =IF(AK$3=1,Inputs!C87,0) -> 0 | AL68: =IF(AL$3=1,Inputs!C87,0) -> 0 | AM68: =IF(AM$3=1,Inputs!C87,0) -> 0 | AN68: =IF(AN$3=1,Inputs!C87,0) -> 0 | AO68: =IF(AO$3=1,Inputs!C87,0) -> 0 | AP68: =IF(AP$3=1,Inputs!C87,0) -> 0 | AQ68: =IF(AQ$3=1,Inputs!C87,0) -> 0 | AR68: =IF(AR$3=1,Inputs!C87,0) -> 0 | AS68: =IF(AS$3=1,Inputs!C87,0) -> 0 | AT68: =IF(AT$3=1,Inputs!C87,0) -> 0 | AU68: =IF(AU$3=1,Inputs!C87,0) -> 0 | AV68: =IF(AV$3=1,Inputs!C87,0) -> 0 | AW68: =IF(AW$3=1,Inputs!C87,0) -> 0 | AX68: =IF(AX$3=1,Inputs!C87,0) -> 0 | AY68: =IF(AY$3=1,Inputs!C87,0) -> 0 | AZ68: =IF(AZ$3=1,Inputs!C87,0) -> 0 | BA68: =IF(BA$3=1,Inputs!C87,0) -> 0 | BB68: =IF(BB$3=1,Inputs!C87,0) -> 0 | BC68: =IF(BC$3=1,Inputs!C87,0) -> 0 | BD68: =IF(BD$3=1,Inputs!C87,0) -> 0 | BE68: =IF(BE$3=1,Inputs!C87,0) -> 0 | BF68: =IF(BF$3=1,Inputs!C87,0) -> 0 | BG68: =IF(BG$3=1,Inputs!C87,0) -> 0 | BH68: =IF(BH$3=1,Inputs!C87,0) -> 0 | BI68: =IF(BI$3=1,Inputs!C87,0) -> 0 | BJ68: =IF(BJ$3=1,Inputs!C87,0) -> 0 | BK68: =IF(BK$3=1,Inputs!C87,0) -> 0 | BL68: =IF(BL$3=1,Inputs!C87,0) -> 0 | BM68: =IF(BM$3=1,Inputs!C87,0) -> 0 | BN68: =IF(BN$3=1,Inputs!C87,0) -> 0 | BO68: =IF(BO$3=1,Inputs!C87,0) -> 0 | BP68: =IF(BP$3=1,Inputs!C87,0) -> 0 | BQ68: =IF(BQ$3=1,Inputs!C87,0) -> 0 | BR68: =IF(BR$3=1,Inputs!C87,0) -> 0 | BS68: =IF(BS$3=1,Inputs!C87,0) -> 0 | BT68: =IF(BT$3=1,Inputs!C87,0) -> 0 | BU68: =IF(BU$3=1,Inputs!C87,0) -> 0 | BV68: =IF(BV$3=1,Inputs!C87,0) -> 0 | BW68: =IF(BW$3=1,Inputs!C87,0) -> 0 | BX68: =IF(BX$3=1,Inputs!C87,0) -> 0 | BY68: =IF(BY$3=1,Inputs!C87,0) -> 0 | BZ68: =IF(BZ$3=1,Inputs!C87,0) -> 0 | CA68: =IF(CA$3=1,Inputs!C87,0) -> 0 | CB68: =IF(CB$3=1,Inputs!C87,0) -> 0 | CC68: =IF(CC$3=1,Inputs!C87,0) -> 0 | CD68: =IF(CD$3=1,Inputs!C87,0) -> 0 | CE68: =IF(CE$3=1,Inputs!C87,0) -> 0 | CF68: =IF(CF$3=1,Inputs!C87,0) -> 0 | CG68: =IF(CG$3=1,Inputs!C87,0) -> 0 | CH68: =IF(CH$3=1,Inputs!C87,0) -> 0 | CI68: =IF(CI$3=1,Inputs!C87,0) -> 0 | CJ68: =IF(CJ$3=1,Inputs!C87,0) -> 0 | CK68: =IF(CK$3=1,Inputs!C87,0) -> 0 | CL68: =IF(CL$3=1,Inputs!C87,0) -> 0 | CM68: =IF(CM$3=1,Inputs!C87,0) -> 0 | CN68: =IF(CN$3=1,Inputs!C87,0) -> 0 | CO68: =IF(CO$3=1,Inputs!C87,0) -> 0 | CP68: =IF(CP$3=1,Inputs!C87,0) -> 0 | CQ68: =IF(CQ$3=1,Inputs!C87,0) -> 0 | CR68: =IF(CR$3=1,Inputs!C87,0) -> 0 | CS68: =IF(CS$3=1,Inputs!C87,0) -> 0 | CT68: =IF(CT$3=1,Inputs!C87,0) -> 0 | CU68: =IF(CU$3=1,Inputs!C87,0) -> 0 | CV68: =IF(CV$3=1,Inputs!C87,0) -> 0 | CW68: =IF(CW$3=1,Inputs!C87,0) -> 0 | CX68: =IF(CX$3=1,Inputs!C87,0) -> 0 | CY68: =IF(CY$3=1,Inputs!C87,0) -> 0 | CZ68: =IF(CZ$3=1,Inputs!C87,0) -> 0 | DA68: =IF(DA$3=1,Inputs!C87,0) -> 0 | DB68: =IF(DB$3=1,Inputs!C87,0) -> 0 | DC68: =IF(DC$3=1,Inputs!C87,0) -> 0 | DD68: =IF(DD$3=1,Inputs!C87,0) -> 0 | DE68: =IF(DE$3=1,Inputs!C87,0) -> 0 | DF68: =IF(DF$3=1,Inputs!C87,0) -> 0 | DG68: =IF(DG$3=1,Inputs!C87,0) -> 0 | DH68: =IF(DH$3=1,Inputs!C87,0) -> 0 | DI68: =IF(DI$3=1,Inputs!C87,0) -> 0 | DJ68: =IF(DJ$3=1,Inputs!C87,0) -> 0 | DK68: =IF(DK$3=1,Inputs!C87,0) -> 0 | DL68: =IF(DL$3=1,Inputs!C87,0) -> 0 | DM68: =IF(DM$3=1,Inputs!C87,0) -> 0 | DN68: =IF(DN$3=1,Inputs!C87,0) -> 0 | DO68: =IF(DO$3=1,Inputs!C87,0) -> 0 | DP68: =IF(DP$3=1,Inputs!C87,0) -> 0 | DQ68: =IF(DQ$3=1,Inputs!C87,0) -> 0 | DR68: =IF(DR$3=1,Inputs!C87,0) -> 0 | DS68: =IF(DS$3=1,Inputs!C87,0) -> 0
B69: Refi Proceeds (Net) | C69: {=IF(C$3<=INDEX(Inputs!$C:$C,MATCH("End Year",Inputs!$B:$B,0))*12,IF(C$3=INDEX(Inputs!$C:$C,MATCH("Refi Year",Inputs!$B:$B,0))*12+1,C61+C55-INDEX(Inputs!$C:$C,MATCH("*Refi Closing Costs ($)*",Inputs!$B:$B,0)),0),0)} -> 0 | D69: {=IF(D$3<=INDEX(Inputs!$C:$C,MATCH("End Year",Inputs!$B:$B,0))*12,IF(D$3=INDEX(Inputs!$C:$C,MATCH("Refi Year",Inputs!$B:$B,0))*12+1,D61+D55-INDEX(Inputs!$C:$C,MATCH("*Refi Closing Costs ($)*",Inputs!$B:$B,0)),0),0)} -> 0 | E69: {=IF(E$3<=INDEX(Inputs!$C:$C,MATCH("End Year",Inputs!$B:$B,0))*12,IF(E$3=INDEX(Inputs!$C:$C,MATCH("Refi Year",Inputs!$B:$B,0))*12+1,E61+E55-INDEX(Inputs!$C:$C,MATCH("*Refi Closing Costs ($)*",Inputs!$B:$B,0)),0),0)} -> 0 | F69: {=IF(F$3<=INDEX(Inputs!$C:$C,MATCH("End Year",Inputs!$B:$B,0))*12,IF(F$3=INDEX(Inputs!$C:$C,MATCH("Refi Year",Inputs!$B:$B,0))*12+1,F61+F55-INDEX(Inputs!$C:$C,MATCH("*Refi Closing Costs ($)*",Inputs!$B:$B,0)),0),0)} -> 0 | G69: {=IF(G$3<=INDEX(Inputs!$C:$C,MATCH("End Year",Inputs!$B:$B,0))*12,IF(G$3=INDEX(Inputs!$C:$C,MATCH("Refi Year",Inputs!$B:$B,0))*12+1,G61+G55-INDEX(Inputs!$C:$C,MATCH("*Refi Closing Costs ($)*",Inputs!$B:$B,0)),0),0)} -> 0 | H69: {=IF(H$3<=INDEX(Inputs!$C:$C,MATCH("End Year",Inputs!$B:$B,0))*12,IF(H$3=INDEX(Inputs!$C:$C,MATCH("Refi Year",Inputs!$B:$B,0))*12+1,H61+H55-INDEX(Inputs!$C:$C,MATCH("*Refi Closing Costs ($)*",Inputs!$B:$B,0)),0),0)} -> 0 | I69: {=IF(I$3<=INDEX(Inputs!$C:$C,MATCH("End Year",Inputs!$B:$B,0))*12,IF(I$3=INDEX(Inputs!$C:$C,MATCH("Refi Year",Inputs!$B:$B,0))*12+1,I61+I55-INDEX(Inputs!$C:$C,MATCH("*Refi Closing Costs ($)*",Inputs!$B:$B,0)),0),0)} -> 0 | J69: {=IF(J$3<=INDEX(Inputs!$C:$C,MATCH("End Year",Inputs!$B:$B,0))*12,IF(J$3=INDEX(Inputs!$C:$C,MATCH("Refi Year",Inputs!$B:$B,0))*12+1,J61+J55-INDEX(Inputs!$C:$C,MATCH("*Refi Closing Costs ($)*",Inputs!$B:$B,0)),0),0)} -> 0 | ... DS69: {=IF(DS$3<=INDEX(Inputs!$C:$C,MATCH("End Year",Inputs!$B:$B,0))*12,IF(DS$3=INDEX(Inputs!$C:$C,MATCH("Refi Year",Inputs!$B:$B,0))*12+1,DS61+DS55-INDEX(Inputs!$C:$C,MATCH("*Refi Closing Costs ($)*",Inputs!$B:$B,0)),0),0)} -> 0
B70: Loan Proceeds (Inflow) | C70: {=IF(C$3<=INDEX(Inputs!$C:$C,MATCH("End Year",Inputs!$B:$B,0))*12,C43+C52,0)} -> 0 | D70: {=IF(D$3<=INDEX(Inputs!$C:$C,MATCH("End Year",Inputs!$B:$B,0))*12,D43+D52,0)} -> 0 | E70: {=IF(E$3<=INDEX(Inputs!$C:$C,MATCH("End Year",Inputs!$B:$B,0))*12,E43+E52,0)} -> 0 | F70: {=IF(F$3<=INDEX(Inputs!$C:$C,MATCH("End Year",Inputs!$B:$B,0))*12,F43+F52,0)} -> 0 | G70: {=IF(G$3<=INDEX(Inputs!$C:$C,MATCH("End Year",Inputs!$B:$B,0))*12,G43+G52,0)} -> 0 | H70: {=IF(H$3<=INDEX(Inputs!$C:$C,MATCH("End Year",Inputs!$B:$B,0))*12,H43+H52,0)} -> 0 | I70: {=IF(I$3<=INDEX(Inputs!$C:$C,MATCH("End Year",Inputs!$B:$B,0))*12,I43+I52,0)} -> 0 | J70: {=IF(J$3<=INDEX(Inputs!$C:$C,MATCH("End Year",Inputs!$B:$B,0))*12,J43+J52,0)} -> 0 | ... DS70: {=IF(DS$3<=INDEX(Inputs!$C:$C,MATCH("End Year",Inputs!$B:$B,0))*12,DS43+DS52,0)} -> 0
B72: TOTAL DEBT SERVICE | C72: =C48+C57+C66 -> 0 | D72: =D48+D57+D66 -> 0 | E72: =E48+E57+E66 -> 0 | F72: =F48+F57+F66 -> 0 | G72: =G48+G57+G66 -> 0 | H72: =H48+H57+H66 -> 0 | I72: =I48+I57+I66 -> 0 | J72: =J48+J57+J66 -> 0 | ... DS72: =DS48+DS57+DS66 -> 0
B74: CASHFLOW AFTER DEBT SERVICE | C74: =C39+C72+C68+C69+C70 -> -350000 | D74: =D39+D72+D68+D69+D70 -> 0 | E74: =E39+E72+E68+E69+E70 -> 0 | F74: =F39+F72+F68+F69+F70 -> 0 | G74: =G39+G72+G68+G69+G70 -> 0 | H74: =H39+H72+H68+H69+H70 -> 0 | I74: =I39+I72+I68+I69+I70 -> 0 | J74: =J39+J72+J68+J69+J70 -> 0 | ... DS74: =DS39+DS72+DS68+DS69+DS70 -> 0
B75: Cumulative Cashflow | C75: =C74 -> -350000 | D75: =C75+D74 -> -350000 | E75: =D75+E74 -> -350000 | F75: =E75+F74 -> -350000 | G75: =F75+G74 -> -350000 | H75: =G75+H74 -> -350000 | I75: =H75+I74 -> -350000 | J75: =I75+J74 -> -350000 | K75: =J75+K74 -> -350000 | ... DS75: =DR75+DS74 -> -350000
B77: MEMBER DISTRIBUTIONS
B78: Less: Asset Management Fee | C78: {=IF(C$3<=INDEX(Inputs!$C:$C,MATCH("End Year",Inputs!$B:$B,0))*12,IF(C39+C72<=0,0,-C11*Inputs!C92),0)} -> 0 | D78: {=IF(D$3<=INDEX(Inputs!$C:$C,MATCH("End Year",Inputs!$B:$B,0))*12,IF(D39+D72<=0,0,-D11*Inputs!C92),0)} -> 0 | E78: {=IF(E$3<=INDEX(Inputs!$C:$C,MATCH("End Year",Inputs!$B:$B,0))*12,IF(E39+E72<=0,0,-E11*Inputs!C92),0)} -> 0 | F78: {=IF(F$3<=INDEX(Inputs!$C:$C,MATCH("End Year",Inputs!$B:$B,0))*12,IF(F39+F72<=0,0,-F11*Inputs!C92),0)} -> 0 | G78: {=IF(G$3<=INDEX(Inputs!$C:$C,MATCH("End Year",Inputs!$B:$B,0))*12,IF(G39+G72<=0,0,-G11*Inputs!C92),0)} -> 0 | H78: {=IF(H$3<=INDEX(Inputs!$C:$C,MATCH("End Year",Inputs!$B:$B,0))*12,IF(H39+H72<=0,0,-H11*Inputs!C92),0)} -> 0 | I78: {=IF(I$3<=INDEX(Inputs!$C:$C,MATCH("End Year",Inputs!$B:$B,0))*12,IF(I39+I72<=0,0,-I11*Inputs!C92),0)} -> 0 | J78: {=IF(J$3<=INDEX(Inputs!$C:$C,MATCH("End Year",Inputs!$B:$B,0))*12,IF(J39+J72<=0,0,-J11*Inputs!C92),0)} -> 0 | K78: {=IF(K$3<=INDEX(Inputs!$C:$C,MATCH("End Year",Inputs!$B:$B,0))*12,IF(K39+K72<=0,0,-K11*Inputs!C92),0)} -> 0 | L78: {=IF(L$3<=INDEX(Inputs!$C:$C,MATCH("End Year",Inputs!$B:$B,0))*12,IF(L39+L72<=0,0,-L11*Inputs!C92),0)} -> 0 | M78: {=IF(M$3<=INDEX(Inputs!$C:$C,MATCH("End Year",Inputs!$B:$B,0))*12,IF(M39+M72<=0,0,-M11*Inputs!C92),0)} -> 0 | N78: {=IF(N$3<=INDEX(Inputs!$C:$C,MATCH("End Year",Inputs!$B:$B,0))*12,IF(N39+N72<=0,0,-N11*Inputs!C92),0)} -> 0 | O78: {=IF(O$3<=INDEX(Inputs!$C:$C,MATCH("End Year",Inputs!$B:$B,0))*12,IF(O39+O72<=0,0,-O11*Inputs!C92),0)} -> 0 | P78: {=IF(P$3<=INDEX(Inputs!$C:$C,MATCH("End Year",Inputs!$B:$B,0))*12,IF(P39+P72<=0,0,-P11*Inputs!C92),0)} -> 0 | Q78: {=IF(Q$3<=INDEX(Inputs!$C:$C,MATCH("End Year",Inputs!$B:$B,0))*12,IF(Q39+Q72<=0,0,-Q11*Inputs!C92),0)} -> 0 | R78: {=IF(R$3<=INDEX(Inputs!$C:$C,MATCH("End Year",Inputs!$B:$B,0))*12,IF(R39+R72<=0,0,-R11*Inputs!C92),0)} -> 0 | S78: {=IF(S$3<=INDEX(Inputs!$C:$C,MATCH("End Year",Inputs!$B:$B,0))*12,IF(S39+S72<=0,0,-S11*Inputs!C92),0)} -> 0 | T78: {=IF(T$3<=INDEX(Inputs!$C:$C,MATCH("End Year",Inputs!$B:$B,0))*12,IF(T39+T72<=0,0,-T11*Inputs!C92),0)} -> 0 | U78: {=IF(U$3<=INDEX(Inputs!$C:$C,MATCH("End Year",Inputs!$B:$B,0))*12,IF(U39+U72<=0,0,-U11*Inputs!C92),0)} -> 0 | V78: {=IF(V$3<=INDEX(Inputs!$C:$C,MATCH("End Year",Inputs!$B:$B,0))*12,IF(V39+V72<=0,0,-V11*Inputs!C92),0)} -> 0 | W78: {=IF(W$3<=INDEX(Inputs!$C:$C,MATCH("End Year",Inputs!$B:$B,0))*12,IF(W39+W72<=0,0,-W11*Inputs!C92),0)} -> 0 | X78: {=IF(X$3<=INDEX(Inputs!$C:$C,MATCH("End Year",Inputs!$B:$B,0))*12,IF(X39+X72<=0,0,-X11*Inputs!C92),0)} -> 0 | Y78: {=IF(Y$3<=INDEX(Inputs!$C:$C,MATCH("End Year",Inputs!$B:$B,0))*12,IF(Y39+Y72<=0,0,-Y11*Inputs!C92),0)} -> 0 | Z78: {=IF(Z$3<=INDEX(Inputs!$C:$C,MATCH("End Year",Inputs!$B:$B,0))*12,IF(Z39+Z72<=0,0,-Z11*Inputs!C92),0)} -> 0 | AA78: {=IF(AA$3<=INDEX(Inputs!$C:$C,MATCH("End Year",Inputs!$B:$B,0))*12,IF(AA39+AA72<=0,0,-AA11*Inputs!C92),0)} -> 0 | AB78: {=IF(AB$3<=INDEX(Inputs!$C:$C,MATCH("End Year",Inputs!$B:$B,0))*12,IF(AB39+AB72<=0,0,-AB11*Inputs!C92),0)} -> 0 | AC78: {=IF(AC$3<=INDEX(Inputs!$C:$C,MATCH("End Year",Inputs!$B:$B,0))*12,IF(AC39+AC72<=0,0,-AC11*Inputs!C92),0)} -> 0 | AD78: {=IF(AD$3<=INDEX(Inputs!$C:$C,MATCH("End Year",Inputs!$B:$B,0))*12,IF(AD39+AD72<=0,0,-AD11*Inputs!C92),0)} -> 0 | AE78: {=IF(AE$3<=INDEX(Inputs!$C:$C,MATCH("End Year",Inputs!$B:$B,0))*12,IF(AE39+AE72<=0,0,-AE11*Inputs!C92),0)} -> 0 | AF78: {=IF(AF$3<=INDEX(Inputs!$C:$C,MATCH("End Year",Inputs!$B:$B,0))*12,IF(AF39+AF72<=0,0,-AF11*Inputs!C92),0)} -> 0 | AG78: {=IF(AG$3<=INDEX(Inputs!$C:$C,MATCH("End Year",Inputs!$B:$B,0))*12,IF(AG39+AG72<=0,0,-AG11*Inputs!C92),0)} -> 0 | AH78: {=IF(AH$3<=INDEX(Inputs!$C:$C,MATCH("End Year",Inputs!$B:$B,0))*12,IF(AH39+AH72<=0,0,-AH11*Inputs!C92),0)} -> 0 | AI78: {=IF(AI$3<=INDEX(Inputs!$C:$C,MATCH("End Year",Inputs!$B:$B,0))*12,IF(AI39+AI72<=0,0,-AI11*Inputs!C92),0)} -> 0 | AJ78: {=IF(AJ$3<=INDEX(Inputs!$C:$C,MATCH("End Year",Inputs!$B:$B,0))*12,IF(AJ39+AJ72<=0,0,-AJ11*Inputs!C92),0)} -> 0 | AK78: {=IF(AK$3<=INDEX(Inputs!$C:$C,MATCH("End Year",Inputs!$B:$B,0))*12,IF(AK39+AK72<=0,0,-AK11*Inputs!C92),0)} -> 0 | AL78: {=IF(AL$3<=INDEX(Inputs!$C:$C,MATCH("End Year",Inputs!$B:$B,0))*12,IF(AL39+AL72<=0,0,-AL11*Inputs!C92),0)} -> 0 | AM78: {=IF(AM$3<=INDEX(Inputs!$C:$C,MATCH("End Year",Inputs!$B:$B,0))*12,IF(AM39+AM72<=0,0,-AM11*Inputs!C92),0)} -> 0 | AN78: {=IF(AN$3<=INDEX(Inputs!$C:$C,MATCH("End Year",Inputs!$B:$B,0))*12,IF(AN39+AN72<=0,0,-AN11*Inputs!C92),0)} -> 0 | AO78: {=IF(AO$3<=INDEX(Inputs!$C:$C,MATCH("End Year",Inputs!$B:$B,0))*12,IF(AO39+AO72<=0,0,-AO11*Inputs!C92),0)} -> 0 | AP78: {=IF(AP$3<=INDEX(Inputs!$C:$C,MATCH("End Year",Inputs!$B:$B,0))*12,IF(AP39+AP72<=0,0,-AP11*Inputs!C92),0)} -> 0 | AQ78: {=IF(AQ$3<=INDEX(Inputs!$C:$C,MATCH("End Year",Inputs!$B:$B,0))*12,IF(AQ39+AQ72<=0,0,-AQ11*Inputs!C92),0)} -> 0 | AR78: {=IF(AR$3<=INDEX(Inputs!$C:$C,MATCH("End Year",Inputs!$B:$B,0))*12,IF(AR39+AR72<=0,0,-AR11*Inputs!C92),0)} -> 0 | AS78: {=IF(AS$3<=INDEX(Inputs!$C:$C,MATCH("End Year",Inputs!$B:$B,0))*12,IF(AS39+AS72<=0,0,-AS11*Inputs!C92),0)} -> 0 | AT78: {=IF(AT$3<=INDEX(Inputs!$C:$C,MATCH("End Year",Inputs!$B:$B,0))*12,IF(AT39+AT72<=0,0,-AT11*Inputs!C92),0)} -> 0 | AU78: {=IF(AU$3<=INDEX(Inputs!$C:$C,MATCH("End Year",Inputs!$B:$B,0))*12,IF(AU39+AU72<=0,0,-AU11*Inputs!C92),0)} -> 0 | AV78: {=IF(AV$3<=INDEX(Inputs!$C:$C,MATCH("End Year",Inputs!$B:$B,0))*12,IF(AV39+AV72<=0,0,-AV11*Inputs!C92),0)} -> 0 | AW78: {=IF(AW$3<=INDEX(Inputs!$C:$C,MATCH("End Year",Inputs!$B:$B,0))*12,IF(AW39+AW72<=0,0,-AW11*Inputs!C92),0)} -> 0 | AX78: {=IF(AX$3<=INDEX(Inputs!$C:$C,MATCH("End Year",Inputs!$B:$B,0))*12,IF(AX39+AX72<=0,0,-AX11*Inputs!C92),0)} -> 0 | AY78: {=IF(AY$3<=INDEX(Inputs!$C:$C,MATCH("End Year",Inputs!$B:$B,0))*12,IF(AY39+AY72<=0,0,-AY11*Inputs!C92),0)} -> 0 | AZ78: {=IF(AZ$3<=INDEX(Inputs!$C:$C,MATCH("End Year",Inputs!$B:$B,0))*12,IF(AZ39+AZ72<=0,0,-AZ11*Inputs!C92),0)} -> 0 | BA78: {=IF(BA$3<=INDEX(Inputs!$C:$C,MATCH("End Year",Inputs!$B:$B,0))*12,IF(BA39+BA72<=0,0,-BA11*Inputs!C92),0)} -> 0 | BB78: {=IF(BB$3<=INDEX(Inputs!$C:$C,MATCH("End Year",Inputs!$B:$B,0))*12,IF(BB39+BB72<=0,0,-BB11*Inputs!C92),0)} -> 0 | BC78: {=IF(BC$3<=INDEX(Inputs!$C:$C,MATCH("End Year",Inputs!$B:$B,0))*12,IF(BC39+BC72<=0,0,-BC11*Inputs!C92),0)} -> 0 | BD78: {=IF(BD$3<=INDEX(Inputs!$C:$C,MATCH("End Year",Inputs!$B:$B,0))*12,IF(BD39+BD72<=0,0,-BD11*Inputs!C92),0)} -> 0 | BE78: {=IF(BE$3<=INDEX(Inputs!$C:$C,MATCH("End Year",Inputs!$B:$B,0))*12,IF(BE39+BE72<=0,0,-BE11*Inputs!C92),0)} -> 0 | BF78: {=IF(BF$3<=INDEX(Inputs!$C:$C,MATCH("End Year",Inputs!$B:$B,0))*12,IF(BF39+BF72<=0,0,-BF11*Inputs!C92),0)} -> 0 | BG78: {=IF(BG$3<=INDEX(Inputs!$C:$C,MATCH("End Year",Inputs!$B:$B,0))*12,IF(BG39+BG72<=0,0,-BG11*Inputs!C92),0)} -> 0 | BH78: {=IF(BH$3<=INDEX(Inputs!$C:$C,MATCH("End Year",Inputs!$B:$B,0))*12,IF(BH39+BH72<=0,0,-BH11*Inputs!C92),0)} -> 0 | BI78: {=IF(BI$3<=INDEX(Inputs!$C:$C,MATCH("End Year",Inputs!$B:$B,0))*12,IF(BI39+BI72<=0,0,-BI11*Inputs!C92),0)} -> 0 | BJ78: {=IF(BJ$3<=INDEX(Inputs!$C:$C,MATCH("End Year",Inputs!$B:$B,0))*12,IF(BJ39+BJ72<=0,0,-BJ11*Inputs!C92),0)} -> 0 | BK78: {=IF(BK$3<=INDEX(Inputs!$C:$C,MATCH("End Year",Inputs!$B:$B,0))*12,IF(BK39+BK72<=0,0,-BK11*Inputs!C92),0)} -> 0 | BL78: {=IF(BL$3<=INDEX(Inputs!$C:$C,MATCH("End Year",Inputs!$B:$B,0))*12,IF(BL39+BL72<=0,0,-BL11*Inputs!C92),0)} -> 0 | BM78: {=IF(BM$3<=INDEX(Inputs!$C:$C,MATCH("End Year",Inputs!$B:$B,0))*12,IF(BM39+BM72<=0,0,-BM11*Inputs!C92),0)} -> 0 | BN78: {=IF(BN$3<=INDEX(Inputs!$C:$C,MATCH("End Year",Inputs!$B:$B,0))*12,IF(BN39+BN72<=0,0,-BN11*Inputs!C92),0)} -> 0 | BO78: {=IF(BO$3<=INDEX(Inputs!$C:$C,MATCH("End Year",Inputs!$B:$B,0))*12,IF(BO39+BO72<=0,0,-BO11*Inputs!C92),0)} -> 0 | BP78: {=IF(BP$3<=INDEX(Inputs!$C:$C,MATCH("End Year",Inputs!$B:$B,0))*12,IF(BP39+BP72<=0,0,-BP11*Inputs!C92),0)} -> 0 | BQ78: {=IF(BQ$3<=INDEX(Inputs!$C:$C,MATCH("End Year",Inputs!$B:$B,0))*12,IF(BQ39+BQ72<=0,0,-BQ11*Inputs!C92),0)} -> 0 | BR78: {=IF(BR$3<=INDEX(Inputs!$C:$C,MATCH("End Year",Inputs!$B:$B,0))*12,IF(BR39+BR72<=0,0,-BR11*Inputs!C92),0)} -> 0 | BS78: {=IF(BS$3<=INDEX(Inputs!$C:$C,MATCH("End Year",Inputs!$B:$B,0))*12,IF(BS39+BS72<=0,0,-BS11*Inputs!C92),0)} -> 0 | BT78: {=IF(BT$3<=INDEX(Inputs!$C:$C,MATCH("End Year",Inputs!$B:$B,0))*12,IF(BT39+BT72<=0,0,-BT11*Inputs!C92),0)} -> 0 | BU78: {=IF(BU$3<=INDEX(Inputs!$C:$C,MATCH("End Year",Inputs!$B:$B,0))*12,IF(BU39+BU72<=0,0,-BU11*Inputs!C92),0)} -> 0 | BV78: {=IF(BV$3<=INDEX(Inputs!$C:$C,MATCH("End Year",Inputs!$B:$B,0))*12,IF(BV39+BV72<=0,0,-BV11*Inputs!C92),0)} -> 0 | BW78: {=IF(BW$3<=INDEX(Inputs!$C:$C,MATCH("End Year",Inputs!$B:$B,0))*12,IF(BW39+BW72<=0,0,-BW11*Inputs!C92),0)} -> 0 | BX78: {=IF(BX$3<=INDEX(Inputs!$C:$C,MATCH("End Year",Inputs!$B:$B,0))*12,IF(BX39+BX72<=0,0,-BX11*Inputs!C92),0)} -> 0 | BY78: {=IF(BY$3<=INDEX(Inputs!$C:$C,MATCH("End Year",Inputs!$B:$B,0))*12,IF(BY39+BY72<=0,0,-BY11*Inputs!C92),0)} -> 0 | BZ78: {=IF(BZ$3<=INDEX(Inputs!$C:$C,MATCH("End Year",Inputs!$B:$B,0))*12,IF(BZ39+BZ72<=0,0,-BZ11*Inputs!C92),0)} -> 0 | CA78: {=IF(CA$3<=INDEX(Inputs!$C:$C,MATCH("End Year",Inputs!$B:$B,0))*12,IF(CA39+CA72<=0,0,-CA11*Inputs!C92),0)} -> 0 | CB78: {=IF(CB$3<=INDEX(Inputs!$C:$C,MATCH("End Year",Inputs!$B:$B,0))*12,IF(CB39+CB72<=0,0,-CB11*Inputs!C92),0)} -> 0 | CC78: {=IF(CC$3<=INDEX(Inputs!$C:$C,MATCH("End Year",Inputs!$B:$B,0))*12,IF(CC39+CC72<=0,0,-CC11*Inputs!C92),0)} -> 0 | CD78: {=IF(CD$3<=INDEX(Inputs!$C:$C,MATCH("End Year",Inputs!$B:$B,0))*12,IF(CD39+CD72<=0,0,-CD11*Inputs!C92),0)} -> 0 | CE78: {=IF(CE$3<=INDEX(Inputs!$C:$C,MATCH("End Year",Inputs!$B:$B,0))*12,IF(CE39+CE72<=0,0,-CE11*Inputs!C92),0)} -> 0 | CF78: {=IF(CF$3<=INDEX(Inputs!$C:$C,MATCH("End Year",Inputs!$B:$B,0))*12,IF(CF39+CF72<=0,0,-CF11*Inputs!C92),0)} -> 0 | CG78: {=IF(CG$3<=INDEX(Inputs!$C:$C,MATCH("End Year",Inputs!$B:$B,0))*12,IF(CG39+CG72<=0,0,-CG11*Inputs!C92),0)} -> 0 | CH78: {=IF(CH$3<=INDEX(Inputs!$C:$C,MATCH("End Year",Inputs!$B:$B,0))*12,IF(CH39+CH72<=0,0,-CH11*Inputs!C92),0)} -> 0 | CI78: {=IF(CI$3<=INDEX(Inputs!$C:$C,MATCH("End Year",Inputs!$B:$B,0))*12,IF(CI39+CI72<=0,0,-CI11*Inputs!C92),0)} -> 0 | CJ78: {=IF(CJ$3<=INDEX(Inputs!$C:$C,MATCH("End Year",Inputs!$B:$B,0))*12,IF(CJ39+CJ72<=0,0,-CJ11*Inputs!C92),0)} -> 0 | CK78: {=IF(CK$3<=INDEX(Inputs!$C:$C,MATCH("End Year",Inputs!$B:$B,0))*12,IF(CK39+CK72<=0,0,-CK11*Inputs!C92),0)} -> 0 | CL78: {=IF(CL$3<=INDEX(Inputs!$C:$C,MATCH("End Year",Inputs!$B:$B,0))*12,IF(CL39+CL72<=0,0,-CL11*Inputs!C92),0)} -> 0 | CM78: {=IF(CM$3<=INDEX(Inputs!$C:$C,MATCH("End Year",Inputs!$B:$B,0))*12,IF(CM39+CM72<=0,0,-CM11*Inputs!C92),0)} -> 0 | CN78: {=IF(CN$3<=INDEX(Inputs!$C:$C,MATCH("End Year",Inputs!$B:$B,0))*12,IF(CN39+CN72<=0,0,-CN11*Inputs!C92),0)} -> 0 | CO78: {=IF(CO$3<=INDEX(Inputs!$C:$C,MATCH("End Year",Inputs!$B:$B,0))*12,IF(CO39+CO72<=0,0,-CO11*Inputs!C92),0)} -> 0 | CP78: {=IF(CP$3<=INDEX(Inputs!$C:$C,MATCH("End Year",Inputs!$B:$B,0))*12,IF(CP39+CP72<=0,0,-CP11*Inputs!C92),0)} -> 0 | CQ78: {=IF(CQ$3<=INDEX(Inputs!$C:$C,MATCH("End Year",Inputs!$B:$B,0))*12,IF(CQ39+CQ72<=0,0,-CQ11*Inputs!C92),0)} -> 0 | CR78: {=IF(CR$3<=INDEX(Inputs!$C:$C,MATCH("End Year",Inputs!$B:$B,0))*12,IF(CR39+CR72<=0,0,-CR11*Inputs!C92),0)} -> 0 | CS78: {=IF(CS$3<=INDEX(Inputs!$C:$C,MATCH("End Year",Inputs!$B:$B,0))*12,IF(CS39+CS72<=0,0,-CS11*Inputs!C92),0)} -> 0 | CT78: {=IF(CT$3<=INDEX(Inputs!$C:$C,MATCH("End Year",Inputs!$B:$B,0))*12,IF(CT39+CT72<=0,0,-CT11*Inputs!C92),0)} -> 0 | CU78: {=IF(CU$3<=INDEX(Inputs!$C:$C,MATCH("End Year",Inputs!$B:$B,0))*12,IF(CU39+CU72<=0,0,-CU11*Inputs!C92),0)} -> 0 | CV78: {=IF(CV$3<=INDEX(Inputs!$C:$C,MATCH("End Year",Inputs!$B:$B,0))*12,IF(CV39+CV72<=0,0,-CV11*Inputs!C92),0)} -> 0 | CW78: {=IF(CW$3<=INDEX(Inputs!$C:$C,MATCH("End Year",Inputs!$B:$B,0))*12,IF(CW39+CW72<=0,0,-CW11*Inputs!C92),0)} -> 0 | CX78: {=IF(CX$3<=INDEX(Inputs!$C:$C,MATCH("End Year",Inputs!$B:$B,0))*12,IF(CX39+CX72<=0,0,-CX11*Inputs!C92),0)} -> 0 | CY78: {=IF(CY$3<=INDEX(Inputs!$C:$C,MATCH("End Year",Inputs!$B:$B,0))*12,IF(CY39+CY72<=0,0,-CY11*Inputs!C92),0)} -> 0 | CZ78: {=IF(CZ$3<=INDEX(Inputs!$C:$C,MATCH("End Year",Inputs!$B:$B,0))*12,IF(CZ39+CZ72<=0,0,-CZ11*Inputs!C92),0)} -> 0 | DA78: {=IF(DA$3<=INDEX(Inputs!$C:$C,MATCH("End Year",Inputs!$B:$B,0))*12,IF(DA39+DA72<=0,0,-DA11*Inputs!C92),0)} -> 0 | DB78: {=IF(DB$3<=INDEX(Inputs!$C:$C,MATCH("End Year",Inputs!$B:$B,0))*12,IF(DB39+DB72<=0,0,-DB11*Inputs!C92),0)} -> 0 | DC78: {=IF(DC$3<=INDEX(Inputs!$C:$C,MATCH("End Year",Inputs!$B:$B,0))*12,IF(DC39+DC72<=0,0,-DC11*Inputs!C92),0)} -> 0 | DD78: {=IF(DD$3<=INDEX(Inputs!$C:$C,MATCH("End Year",Inputs!$B:$B,0))*12,IF(DD39+DD72<=0,0,-DD11*Inputs!C92),0)} -> 0 | DE78: {=IF(DE$3<=INDEX(Inputs!$C:$C,MATCH("End Year",Inputs!$B:$B,0))*12,IF(DE39+DE72<=0,0,-DE11*Inputs!C92),0)} -> 0 | DF78: {=IF(DF$3<=INDEX(Inputs!$C:$C,MATCH("End Year",Inputs!$B:$B,0))*12,IF(DF39+DF72<=0,0,-DF11*Inputs!C92),0)} -> 0 | DG78: {=IF(DG$3<=INDEX(Inputs!$C:$C,MATCH("End Year",Inputs!$B:$B,0))*12,IF(DG39+DG72<=0,0,-DG11*Inputs!C92),0)} -> 0 | DH78: {=IF(DH$3<=INDEX(Inputs!$C:$C,MATCH("End Year",Inputs!$B:$B,0))*12,IF(DH39+DH72<=0,0,-DH11*Inputs!C92),0)} -> 0 | DI78: {=IF(DI$3<=INDEX(Inputs!$C:$C,MATCH("End Year",Inputs!$B:$B,0))*12,IF(DI39+DI72<=0,0,-DI11*Inputs!C92),0)} -> 0 | DJ78: {=IF(DJ$3<=INDEX(Inputs!$C:$C,MATCH("End Year",Inputs!$B:$B,0))*12,IF(DJ39+DJ72<=0,0,-DJ11*Inputs!C92),0)} -> 0 | DK78: {=IF(DK$3<=INDEX(Inputs!$C:$C,MATCH("End Year",Inputs!$B:$B,0))*12,IF(DK39+DK72<=0,0,-DK11*Inputs!C92),0)} -> 0 | DL78: {=IF(DL$3<=INDEX(Inputs!$C:$C,MATCH("End Year",Inputs!$B:$B,0))*12,IF(DL39+DL72<=0,0,-DL11*Inputs!C92),0)} -> 0 | DM78: {=IF(DM$3<=INDEX(Inputs!$C:$C,MATCH("End Year",Inputs!$B:$B,0))*12,IF(DM39+DM72<=0,0,-DM11*Inputs!C92),0)} -> 0 | DN78: {=IF(DN$3<=INDEX(Inputs!$C:$C,MATCH("End Year",Inputs!$B:$B,0))*12,IF(DN39+DN72<=0,0,-DN11*Inputs!C92),0)} -> 0 | DO78: {=IF(DO$3<=INDEX(Inputs!$C:$C,MATCH("End Year",Inputs!$B:$B,0))*12,IF(DO39+DO72<=0,0,-DO11*Inputs!C92),0)} -> 0 | DP78: {=IF(DP$3<=INDEX(Inputs!$C:$C,MATCH("End Year",Inputs!$B:$B,0))*12,IF(DP39+DP72<=0,0,-DP11*Inputs!C92),0)} -> 0 | DQ78: {=IF(DQ$3<=INDEX(Inputs!$C:$C,MATCH("End Year",Inputs!$B:$B,0))*12,IF(DQ39+DQ72<=0,0,-DQ11*Inputs!C92),0)} -> 0 | DR78: {=IF(DR$3<=INDEX(Inputs!$C:$C,MATCH("End Year",Inputs!$B:$B,0))*12,IF(DR39+DR72<=0,0,-DR11*Inputs!C92),0)} -> 0 | DS78: {=IF(DS$3<=INDEX(Inputs!$C:$C,MATCH("End Year",Inputs!$B:$B,0))*12,IF(DS39+DS72<=0,0,-DS11*Inputs!C92),0)} -> 0
B79: Cash Available for Members | C79: =MAX(C39+C72+C78-C81,0) -> 0 | D79: =MAX(D39+D72+D78-D81,0) -> 0 | E79: =MAX(E39+E72+E78-E81,0) -> 0 | F79: =MAX(F39+F72+F78-F81,0) -> 0 | G79: =MAX(G39+G72+G78-G81,0) -> 0 | H79: =MAX(H39+H72+H78-H81,0) -> 0 | I79: =MAX(I39+I72+I78-I81,0) -> 0 | J79: =MAX(J39+J72+J78-J81,0) -> 0 | ... DS79: =MAX(DS39+DS72+DS78-DS81,0) -> 0
B80: =" Capital Partner ("&TEXT(Inputs!C90,"0.0%")&")" -> Capital Partner (-24.6%) | C80: =C79*Inputs!C90 -> 0 | D80: =D79*Inputs!C90 -> 0 | E80: =E79*Inputs!C90 -> 0 | F80: =F79*Inputs!C90 -> 0 | G80: =G79*Inputs!C90 -> 0 | H80: =H79*Inputs!C90 -> 0 | I80: =I79*Inputs!C90 -> 0 | J80: =J79*Inputs!C90 -> 0 | K80: =K79*Inputs!C90 -> 0 | L80: =L79*Inputs!C90 -> 0 | M80: =M79*Inputs!C90 -> 0 | N80: =N79*Inputs!C90 -> 0 | O80: =O79*Inputs!C90 -> 0 | P80: =P79*Inputs!C90 -> 0 | Q80: =Q79*Inputs!C90 -> 0 | R80: =R79*Inputs!C90 -> 0 | S80: =S79*Inputs!C90 -> 0 | T80: =T79*Inputs!C90 -> 0 | U80: =U79*Inputs!C90 -> 0 | V80: =V79*Inputs!C90 -> 0 | W80: =W79*Inputs!C90 -> 0 | X80: =X79*Inputs!C90 -> 0 | Y80: =Y79*Inputs!C90 -> 0 | Z80: =Z79*Inputs!C90 -> 0 | AA80: =AA79*Inputs!C90 -> 0 | AB80: =AB79*Inputs!C90 -> 0 | AC80: =AC79*Inputs!C90 -> 0 | AD80: =AD79*Inputs!C90 -> 0 | AE80: =AE79*Inputs!C90 -> 0 | AF80: =AF79*Inputs!C90 -> 0 | AG80: =AG79*Inputs!C90 -> 0 | AH80: =AH79*Inputs!C90 -> 0 | AI80: =AI79*Inputs!C90 -> 0 | AJ80: =AJ79*Inputs!C90 -> 0 | AK80: =AK79*Inputs!C90 -> 0 | AL80: =AL79*Inputs!C90 -> 0 | AM80: =AM79*Inputs!C90 -> 0 | AN80: =AN79*Inputs!C90 -> 0 | AO80: =AO79*Inputs!C90 -> 0 | AP80: =AP79*Inputs!C90 -> 0 | AQ80: =AQ79*Inputs!C90 -> 0 | AR80: =AR79*Inputs!C90 -> 0 | AS80: =AS79*Inputs!C90 -> 0 | AT80: =AT79*Inputs!C90 -> 0 | AU80: =AU79*Inputs!C90 -> 0 | AV80: =AV79*Inputs!C90 -> 0 | AW80: =AW79*Inputs!C90 -> 0 | AX80: =AX79*Inputs!C90 -> 0 | AY80: =AY79*Inputs!C90 -> 0 | AZ80: =AZ79*Inputs!C90 -> 0 | BA80: =BA79*Inputs!C90 -> 0 | BB80: =BB79*Inputs!C90 -> 0 | BC80: =BC79*Inputs!C90 -> 0 | BD80: =BD79*Inputs!C90 -> 0 | BE80: =BE79*Inputs!C90 -> 0 | BF80: =BF79*Inputs!C90 -> 0 | BG80: =BG79*Inputs!C90 -> 0 | BH80: =BH79*Inputs!C90 -> 0 | BI80: =BI79*Inputs!C90 -> 0 | BJ80: =BJ79*Inputs!C90 -> 0 | BK80: =BK79*Inputs!C90 -> 0 | BL80: =BL79*Inputs!C90 -> 0 | BM80: =BM79*Inputs!C90 -> 0 | BN80: =BN79*Inputs!C90 -> 0 | BO80: =BO79*Inputs!C90 -> 0 | BP80: =BP79*Inputs!C90 -> 0 | BQ80: =BQ79*Inputs!C90 -> 0 | BR80: =BR79*Inputs!C90 -> 0 | BS80: =BS79*Inputs!C90 -> 0 | BT80: =BT79*Inputs!C90 -> 0 | BU80: =BU79*Inputs!C90 -> 0 | BV80: =BV79*Inputs!C90 -> 0 | BW80: =BW79*Inputs!C90 -> 0 | BX80: =BX79*Inputs!C90 -> 0 | BY80: =BY79*Inputs!C90 -> 0 | BZ80: =BZ79*Inputs!C90 -> 0 | CA80: =CA79*Inputs!C90 -> 0 | CB80: =CB79*Inputs!C90 -> 0 | CC80: =CC79*Inputs!C90 -> 0 | CD80: =CD79*Inputs!C90 -> 0 | CE80: =CE79*Inputs!C90 -> 0 | CF80: =CF79*Inputs!C90 -> 0 | CG80: =CG79*Inputs!C90 -> 0 | CH80: =CH79*Inputs!C90 -> 0 | CI80: =CI79*Inputs!C90 -> 0 | CJ80: =CJ79*Inputs!C90 -> 0 | CK80: =CK79*Inputs!C90 -> 0 | CL80: =CL79*Inputs!C90 -> 0 | CM80: =CM79*Inputs!C90 -> 0 | CN80: =CN79*Inputs!C90 -> 0 | CO80: =CO79*Inputs!C90 -> 0 | CP80: =CP79*Inputs!C90 -> 0 | CQ80: =CQ79*Inputs!C90 -> 0 | CR80: =CR79*Inputs!C90 -> 0 | CS80: =CS79*Inputs!C90 -> 0 | CT80: =CT79*Inputs!C90 -> 0 | CU80: =CU79*Inputs!C90 -> 0 | CV80: =CV79*Inputs!C90 -> 0 | CW80: =CW79*Inputs!C90 -> 0 | CX80: =CX79*Inputs!C90 -> 0 | CY80: =CY79*Inputs!C90 -> 0 | CZ80: =CZ79*Inputs!C90 -> 0 | DA80: =DA79*Inputs!C90 -> 0 | DB80: =DB79*Inputs!C90 -> 0 | DC80: =DC79*Inputs!C90 -> 0 | DD80: =DD79*Inputs!C90 -> 0 | DE80: =DE79*Inputs!C90 -> 0 | DF80: =DF79*Inputs!C90 -> 0 | DG80: =DG79*Inputs!C90 -> 0 | DH80: =DH79*Inputs!C90 -> 0 | DI80: =DI79*Inputs!C90 -> 0 | DJ80: =DJ79*Inputs!C90 -> 0 | DK80: =DK79*Inputs!C90 -> 0 | DL80: =DL79*Inputs!C90 -> 0 | DM80: =DM79*Inputs!C90 -> 0 | DN80: =DN79*Inputs!C90 -> 0 | DO80: =DO79*Inputs!C90 -> 0 | DP80: =DP79*Inputs!C90 -> 0 | DQ80: =DQ79*Inputs!C90 -> 0 | DR80: =DR79*Inputs!C90 -> 0 | DS80: =DS79*Inputs!C90 -> 0
B81: Return of Capital (Capital Partner) | C81: {=IF(C$3=INDEX(Inputs!$C:$C,MATCH("End Year",Inputs!$B:$B,0))*12,Inputs!C88,0)} -> 0 | D81: {=IF(D$3=INDEX(Inputs!$C:$C,MATCH("End Year",Inputs!$B:$B,0))*12,Inputs!C88,0)} -> 0 | E81: {=IF(E$3=INDEX(Inputs!$C:$C,MATCH("End Year",Inputs!$B:$B,0))*12,Inputs!C88,0)} -> 0 | F81: {=IF(F$3=INDEX(Inputs!$C:$C,MATCH("End Year",Inputs!$B:$B,0))*12,Inputs!C88,0)} -> 0 | G81: {=IF(G$3=INDEX(Inputs!$C:$C,MATCH("End Year",Inputs!$B:$B,0))*12,Inputs!C88,0)} -> 0 | H81: {=IF(H$3=INDEX(Inputs!$C:$C,MATCH("End Year",Inputs!$B:$B,0))*12,Inputs!C88,0)} -> 0 | I81: {=IF(I$3=INDEX(Inputs!$C:$C,MATCH("End Year",Inputs!$B:$B,0))*12,Inputs!C88,0)} -> 0 | J81: {=IF(J$3=INDEX(Inputs!$C:$C,MATCH("End Year",Inputs!$B:$B,0))*12,Inputs!C88,0)} -> 0 | K81: {=IF(K$3=INDEX(Inputs!$C:$C,MATCH("End Year",Inputs!$B:$B,0))*12,Inputs!C88,0)} -> 0 | L81: {=IF(L$3=INDEX(Inputs!$C:$C,MATCH("End Year",Inputs!$B:$B,0))*12,Inputs!C88,0)} -> 0 | M81: {=IF(M$3=INDEX(Inputs!$C:$C,MATCH("End Year",Inputs!$B:$B,0))*12,Inputs!C88,0)} -> 0 | N81: {=IF(N$3=INDEX(Inputs!$C:$C,MATCH("End Year",Inputs!$B:$B,0))*12,Inputs!C88,0)} -> 0 | O81: {=IF(O$3=INDEX(Inputs!$C:$C,MATCH("End Year",Inputs!$B:$B,0))*12,Inputs!C88,0)} -> 0 | P81: {=IF(P$3=INDEX(Inputs!$C:$C,MATCH("End Year",Inputs!$B:$B,0))*12,Inputs!C88,0)} -> 0 | Q81: {=IF(Q$3=INDEX(Inputs!$C:$C,MATCH("End Year",Inputs!$B:$B,0))*12,Inputs!C88,0)} -> 0 | R81: {=IF(R$3=INDEX(Inputs!$C:$C,MATCH("End Year",Inputs!$B:$B,0))*12,Inputs!C88,0)} -> 0 | S81: {=IF(S$3=INDEX(Inputs!$C:$C,MATCH("End Year",Inputs!$B:$B,0))*12,Inputs!C88,0)} -> 0 | T81: {=IF(T$3=INDEX(Inputs!$C:$C,MATCH("End Year",Inputs!$B:$B,0))*12,Inputs!C88,0)} -> 0 | U81: {=IF(U$3=INDEX(Inputs!$C:$C,MATCH("End Year",Inputs!$B:$B,0))*12,Inputs!C88,0)} -> 0 | V81: {=IF(V$3=INDEX(Inputs!$C:$C,MATCH("End Year",Inputs!$B:$B,0))*12,Inputs!C88,0)} -> 0 | W81: {=IF(W$3=INDEX(Inputs!$C:$C,MATCH("End Year",Inputs!$B:$B,0))*12,Inputs!C88,0)} -> 0 | X81: {=IF(X$3=INDEX(Inputs!$C:$C,MATCH("End Year",Inputs!$B:$B,0))*12,Inputs!C88,0)} -> 0 | Y81: {=IF(Y$3=INDEX(Inputs!$C:$C,MATCH("End Year",Inputs!$B:$B,0))*12,Inputs!C88,0)} -> 0 | Z81: {=IF(Z$3=INDEX(Inputs!$C:$C,MATCH("End Year",Inputs!$B:$B,0))*12,Inputs!C88,0)} -> 0 | AA81: {=IF(AA$3=INDEX(Inputs!$C:$C,MATCH("End Year",Inputs!$B:$B,0))*12,Inputs!C88,0)} -> 0 | AB81: {=IF(AB$3=INDEX(Inputs!$C:$C,MATCH("End Year",Inputs!$B:$B,0))*12,Inputs!C88,0)} -> 0 | AC81: {=IF(AC$3=INDEX(Inputs!$C:$C,MATCH("End Year",Inputs!$B:$B,0))*12,Inputs!C88,0)} -> 0 | AD81: {=IF(AD$3=INDEX(Inputs!$C:$C,MATCH("End Year",Inputs!$B:$B,0))*12,Inputs!C88,0)} -> 0 | AE81: {=IF(AE$3=INDEX(Inputs!$C:$C,MATCH("End Year",Inputs!$B:$B,0))*12,Inputs!C88,0)} -> 0 | AF81: {=IF(AF$3=INDEX(Inputs!$C:$C,MATCH("End Year",Inputs!$B:$B,0))*12,Inputs!C88,0)} -> 0 | AG81: {=IF(AG$3=INDEX(Inputs!$C:$C,MATCH("End Year",Inputs!$B:$B,0))*12,Inputs!C88,0)} -> 0 | AH81: {=IF(AH$3=INDEX(Inputs!$C:$C,MATCH("End Year",Inputs!$B:$B,0))*12,Inputs!C88,0)} -> 0 | AI81: {=IF(AI$3=INDEX(Inputs!$C:$C,MATCH("End Year",Inputs!$B:$B,0))*12,Inputs!C88,0)} -> 0 | AJ81: {=IF(AJ$3=INDEX(Inputs!$C:$C,MATCH("End Year",Inputs!$B:$B,0))*12,Inputs!C88,0)} -> 0 | AK81: {=IF(AK$3=INDEX(Inputs!$C:$C,MATCH("End Year",Inputs!$B:$B,0))*12,Inputs!C88,0)} -> 0 | AL81: {=IF(AL$3=INDEX(Inputs!$C:$C,MATCH("End Year",Inputs!$B:$B,0))*12,Inputs!C88,0)} -> 0 | AM81: {=IF(AM$3=INDEX(Inputs!$C:$C,MATCH("End Year",Inputs!$B:$B,0))*12,Inputs!C88,0)} -> 0 | AN81: {=IF(AN$3=INDEX(Inputs!$C:$C,MATCH("End Year",Inputs!$B:$B,0))*12,Inputs!C88,0)} -> 0 | AO81: {=IF(AO$3=INDEX(Inputs!$C:$C,MATCH("End Year",Inputs!$B:$B,0))*12,Inputs!C88,0)} -> 0 | AP81: {=IF(AP$3=INDEX(Inputs!$C:$C,MATCH("End Year",Inputs!$B:$B,0))*12,Inputs!C88,0)} -> 0 | AQ81: {=IF(AQ$3=INDEX(Inputs!$C:$C,MATCH("End Year",Inputs!$B:$B,0))*12,Inputs!C88,0)} -> 0 | AR81: {=IF(AR$3=INDEX(Inputs!$C:$C,MATCH("End Year",Inputs!$B:$B,0))*12,Inputs!C88,0)} -> 0 | AS81: {=IF(AS$3=INDEX(Inputs!$C:$C,MATCH("End Year",Inputs!$B:$B,0))*12,Inputs!C88,0)} -> 0 | AT81: {=IF(AT$3=INDEX(Inputs!$C:$C,MATCH("End Year",Inputs!$B:$B,0))*12,Inputs!C88,0)} -> 0 | AU81: {=IF(AU$3=INDEX(Inputs!$C:$C,MATCH("End Year",Inputs!$B:$B,0))*12,Inputs!C88,0)} -> 0 | AV81: {=IF(AV$3=INDEX(Inputs!$C:$C,MATCH("End Year",Inputs!$B:$B,0))*12,Inputs!C88,0)} -> 0 | AW81: {=IF(AW$3=INDEX(Inputs!$C:$C,MATCH("End Year",Inputs!$B:$B,0))*12,Inputs!C88,0)} -> 0 | AX81: {=IF(AX$3=INDEX(Inputs!$C:$C,MATCH("End Year",Inputs!$B:$B,0))*12,Inputs!C88,0)} -> 0 | AY81: {=IF(AY$3=INDEX(Inputs!$C:$C,MATCH("End Year",Inputs!$B:$B,0))*12,Inputs!C88,0)} -> 0 | AZ81: {=IF(AZ$3=INDEX(Inputs!$C:$C,MATCH("End Year",Inputs!$B:$B,0))*12,Inputs!C88,0)} -> 0 | BA81: {=IF(BA$3=INDEX(Inputs!$C:$C,MATCH("End Year",Inputs!$B:$B,0))*12,Inputs!C88,0)} -> 0 | BB81: {=IF(BB$3=INDEX(Inputs!$C:$C,MATCH("End Year",Inputs!$B:$B,0))*12,Inputs!C88,0)} -> 0 | BC81: {=IF(BC$3=INDEX(Inputs!$C:$C,MATCH("End Year",Inputs!$B:$B,0))*12,Inputs!C88,0)} -> 0 | BD81: {=IF(BD$3=INDEX(Inputs!$C:$C,MATCH("End Year",Inputs!$B:$B,0))*12,Inputs!C88,0)} -> 0 | BE81: {=IF(BE$3=INDEX(Inputs!$C:$C,MATCH("End Year",Inputs!$B:$B,0))*12,Inputs!C88,0)} -> 0 | BF81: {=IF(BF$3=INDEX(Inputs!$C:$C,MATCH("End Year",Inputs!$B:$B,0))*12,Inputs!C88,0)} -> 0 | BG81: {=IF(BG$3=INDEX(Inputs!$C:$C,MATCH("End Year",Inputs!$B:$B,0))*12,Inputs!C88,0)} -> 0 | BH81: {=IF(BH$3=INDEX(Inputs!$C:$C,MATCH("End Year",Inputs!$B:$B,0))*12,Inputs!C88,0)} -> 0 | BI81: {=IF(BI$3=INDEX(Inputs!$C:$C,MATCH("End Year",Inputs!$B:$B,0))*12,Inputs!C88,0)} -> 0 | BJ81: {=IF(BJ$3=INDEX(Inputs!$C:$C,MATCH("End Year",Inputs!$B:$B,0))*12,Inputs!C88,0)} -> 0 | BK81: {=IF(BK$3=INDEX(Inputs!$C:$C,MATCH("End Year",Inputs!$B:$B,0))*12,Inputs!C88,0)} -> 0 | BL81: {=IF(BL$3=INDEX(Inputs!$C:$C,MATCH("End Year",Inputs!$B:$B,0))*12,Inputs!C88,0)} -> 0 | BM81: {=IF(BM$3=INDEX(Inputs!$C:$C,MATCH("End Year",Inputs!$B:$B,0))*12,Inputs!C88,0)} -> 0 | BN81: {=IF(BN$3=INDEX(Inputs!$C:$C,MATCH("End Year",Inputs!$B:$B,0))*12,Inputs!C88,0)} -> 0 | BO81: {=IF(BO$3=INDEX(Inputs!$C:$C,MATCH("End Year",Inputs!$B:$B,0))*12,Inputs!C88,0)} -> 0 | BP81: {=IF(BP$3=INDEX(Inputs!$C:$C,MATCH("End Year",Inputs!$B:$B,0))*12,Inputs!C88,0)} -> 0 | BQ81: {=IF(BQ$3=INDEX(Inputs!$C:$C,MATCH("End Year",Inputs!$B:$B,0))*12,Inputs!C88,0)} -> 0 | BR81: {=IF(BR$3=INDEX(Inputs!$C:$C,MATCH("End Year",Inputs!$B:$B,0))*12,Inputs!C88,0)} -> 0 | BS81: {=IF(BS$3=INDEX(Inputs!$C:$C,MATCH("End Year",Inputs!$B:$B,0))*12,Inputs!C88,0)} -> 0 | BT81: {=IF(BT$3=INDEX(Inputs!$C:$C,MATCH("End Year",Inputs!$B:$B,0))*12,Inputs!C88,0)} -> 0 | BU81: {=IF(BU$3=INDEX(Inputs!$C:$C,MATCH("End Year",Inputs!$B:$B,0))*12,Inputs!C88,0)} -> 0 | BV81: {=IF(BV$3=INDEX(Inputs!$C:$C,MATCH("End Year",Inputs!$B:$B,0))*12,Inputs!C88,0)} -> 0 | BW81: {=IF(BW$3=INDEX(Inputs!$C:$C,MATCH("End Year",Inputs!$B:$B,0))*12,Inputs!C88,0)} -> 0 | BX81: {=IF(BX$3=INDEX(Inputs!$C:$C,MATCH("End Year",Inputs!$B:$B,0))*12,Inputs!C88,0)} -> 0 | BY81: {=IF(BY$3=INDEX(Inputs!$C:$C,MATCH("End Year",Inputs!$B:$B,0))*12,Inputs!C88,0)} -> 0 | BZ81: {=IF(BZ$3=INDEX(Inputs!$C:$C,MATCH("End Year",Inputs!$B:$B,0))*12,Inputs!C88,0)} -> 0 | CA81: {=IF(CA$3=INDEX(Inputs!$C:$C,MATCH("End Year",Inputs!$B:$B,0))*12,Inputs!C88,0)} -> 0 | CB81: {=IF(CB$3=INDEX(Inputs!$C:$C,MATCH("End Year",Inputs!$B:$B,0))*12,Inputs!C88,0)} -> 0 | CC81: {=IF(CC$3=INDEX(Inputs!$C:$C,MATCH("End Year",Inputs!$B:$B,0))*12,Inputs!C88,0)} -> 0 | CD81: {=IF(CD$3=INDEX(Inputs!$C:$C,MATCH("End Year",Inputs!$B:$B,0))*12,Inputs!C88,0)} -> 0 | CE81: {=IF(CE$3=INDEX(Inputs!$C:$C,MATCH("End Year",Inputs!$B:$B,0))*12,Inputs!C88,0)} -> 0 | CF81: {=IF(CF$3=INDEX(Inputs!$C:$C,MATCH("End Year",Inputs!$B:$B,0))*12,Inputs!C88,0)} -> 0 | CG81: {=IF(CG$3=INDEX(Inputs!$C:$C,MATCH("End Year",Inputs!$B:$B,0))*12,Inputs!C88,0)} -> 0 | CH81: {=IF(CH$3=INDEX(Inputs!$C:$C,MATCH("End Year",Inputs!$B:$B,0))*12,Inputs!C88,0)} -> 0 | CI81: {=IF(CI$3=INDEX(Inputs!$C:$C,MATCH("End Year",Inputs!$B:$B,0))*12,Inputs!C88,0)} -> 0 | CJ81: {=IF(CJ$3=INDEX(Inputs!$C:$C,MATCH("End Year",Inputs!$B:$B,0))*12,Inputs!C88,0)} -> 0 | CK81: {=IF(CK$3=INDEX(Inputs!$C:$C,MATCH("End Year",Inputs!$B:$B,0))*12,Inputs!C88,0)} -> 0 | CL81: {=IF(CL$3=INDEX(Inputs!$C:$C,MATCH("End Year",Inputs!$B:$B,0))*12,Inputs!C88,0)} -> 0 | CM81: {=IF(CM$3=INDEX(Inputs!$C:$C,MATCH("End Year",Inputs!$B:$B,0))*12,Inputs!C88,0)} -> 0 | CN81: {=IF(CN$3=INDEX(Inputs!$C:$C,MATCH("End Year",Inputs!$B:$B,0))*12,Inputs!C88,0)} -> 0 | CO81: {=IF(CO$3=INDEX(Inputs!$C:$C,MATCH("End Year",Inputs!$B:$B,0))*12,Inputs!C88,0)} -> 0 | CP81: {=IF(CP$3=INDEX(Inputs!$C:$C,MATCH("End Year",Inputs!$B:$B,0))*12,Inputs!C88,0)} -> 0 | CQ81: {=IF(CQ$3=INDEX(Inputs!$C:$C,MATCH("End Year",Inputs!$B:$B,0))*12,Inputs!C88,0)} -> 0 | CR81: {=IF(CR$3=INDEX(Inputs!$C:$C,MATCH("End Year",Inputs!$B:$B,0))*12,Inputs!C88,0)} -> 0 | CS81: {=IF(CS$3=INDEX(Inputs!$C:$C,MATCH("End Year",Inputs!$B:$B,0))*12,Inputs!C88,0)} -> 0 | CT81: {=IF(CT$3=INDEX(Inputs!$C:$C,MATCH("End Year",Inputs!$B:$B,0))*12,Inputs!C88,0)} -> 0 | CU81: {=IF(CU$3=INDEX(Inputs!$C:$C,MATCH("End Year",Inputs!$B:$B,0))*12,Inputs!C88,0)} -> 0 | CV81: {=IF(CV$3=INDEX(Inputs!$C:$C,MATCH("End Year",Inputs!$B:$B,0))*12,Inputs!C88,0)} -> 0 | CW81: {=IF(CW$3=INDEX(Inputs!$C:$C,MATCH("End Year",Inputs!$B:$B,0))*12,Inputs!C88,0)} -> 0 | CX81: {=IF(CX$3=INDEX(Inputs!$C:$C,MATCH("End Year",Inputs!$B:$B,0))*12,Inputs!C88,0)} -> 0 | CY81: {=IF(CY$3=INDEX(Inputs!$C:$C,MATCH("End Year",Inputs!$B:$B,0))*12,Inputs!C88,0)} -> 0 | CZ81: {=IF(CZ$3=INDEX(Inputs!$C:$C,MATCH("End Year",Inputs!$B:$B,0))*12,Inputs!C88,0)} -> 0 | DA81: {=IF(DA$3=INDEX(Inputs!$C:$C,MATCH("End Year",Inputs!$B:$B,0))*12,Inputs!C88,0)} -> 0 | DB81: {=IF(DB$3=INDEX(Inputs!$C:$C,MATCH("End Year",Inputs!$B:$B,0))*12,Inputs!C88,0)} -> 0 | DC81: {=IF(DC$3=INDEX(Inputs!$C:$C,MATCH("End Year",Inputs!$B:$B,0))*12,Inputs!C88,0)} -> 0 | DD81: {=IF(DD$3=INDEX(Inputs!$C:$C,MATCH("End Year",Inputs!$B:$B,0))*12,Inputs!C88,0)} -> 0 | DE81: {=IF(DE$3=INDEX(Inputs!$C:$C,MATCH("End Year",Inputs!$B:$B,0))*12,Inputs!C88,0)} -> 0 | DF81: {=IF(DF$3=INDEX(Inputs!$C:$C,MATCH("End Year",Inputs!$B:$B,0))*12,Inputs!C88,0)} -> 0 | DG81: {=IF(DG$3=INDEX(Inputs!$C:$C,MATCH("End Year",Inputs!$B:$B,0))*12,Inputs!C88,0)} -> 0 | DH81: {=IF(DH$3=INDEX(Inputs!$C:$C,MATCH("End Year",Inputs!$B:$B,0))*12,Inputs!C88,0)} -> 0 | DI81: {=IF(DI$3=INDEX(Inputs!$C:$C,MATCH("End Year",Inputs!$B:$B,0))*12,Inputs!C88,0)} -> 0 | DJ81: {=IF(DJ$3=INDEX(Inputs!$C:$C,MATCH("End Year",Inputs!$B:$B,0))*12,Inputs!C88,0)} -> 0 | DK81: {=IF(DK$3=INDEX(Inputs!$C:$C,MATCH("End Year",Inputs!$B:$B,0))*12,Inputs!C88,0)} -> 0 | DL81: {=IF(DL$3=INDEX(Inputs!$C:$C,MATCH("End Year",Inputs!$B:$B,0))*12,Inputs!C88,0)} -> 0 | DM81: {=IF(DM$3=INDEX(Inputs!$C:$C,MATCH("End Year",Inputs!$B:$B,0))*12,Inputs!C88,0)} -> 0 | DN81: {=IF(DN$3=INDEX(Inputs!$C:$C,MATCH("End Year",Inputs!$B:$B,0))*12,Inputs!C88,0)} -> 0 | DO81: {=IF(DO$3=INDEX(Inputs!$C:$C,MATCH("End Year",Inputs!$B:$B,0))*12,Inputs!C88,0)} -> 0 | DP81: {=IF(DP$3=INDEX(Inputs!$C:$C,MATCH("End Year",Inputs!$B:$B,0))*12,Inputs!C88,0)} -> 0 | DQ81: {=IF(DQ$3=INDEX(Inputs!$C:$C,MATCH("End Year",Inputs!$B:$B,0))*12,Inputs!C88,0)} -> 0 | DR81: {=IF(DR$3=INDEX(Inputs!$C:$C,MATCH("End Year",Inputs!$B:$B,0))*12,Inputs!C88,0)} -> 0 | DS81: {=IF(DS$3=INDEX(Inputs!$C:$C,MATCH("End Year",Inputs!$B:$B,0))*12,Inputs!C88,0)} -> 85000
B82: =" Manager ("&TEXT(Inputs!C91,"0.0%")&")" -> Manager (124.6%) | C82: =C79*Inputs!C91 -> 0 | D82: =D79*Inputs!C91 -> 0 | E82: =E79*Inputs!C91 -> 0 | F82: =F79*Inputs!C91 -> 0 | G82: =G79*Inputs!C91 -> 0 | H82: =H79*Inputs!C91 -> 0 | I82: =I79*Inputs!C91 -> 0 | J82: =J79*Inputs!C91 -> 0 | K82: =K79*Inputs!C91 -> 0 | L82: =L79*Inputs!C91 -> 0 | M82: =M79*Inputs!C91 -> 0 | N82: =N79*Inputs!C91 -> 0 | O82: =O79*Inputs!C91 -> 0 | P82: =P79*Inputs!C91 -> 0 | Q82: =Q79*Inputs!C91 -> 0 | R82: =R79*Inputs!C91 -> 0 | S82: =S79*Inputs!C91 -> 0 | T82: =T79*Inputs!C91 -> 0 | U82: =U79*Inputs!C91 -> 0 | V82: =V79*Inputs!C91 -> 0 | W82: =W79*Inputs!C91 -> 0 | X82: =X79*Inputs!C91 -> 0 | Y82: =Y79*Inputs!C91 -> 0 | Z82: =Z79*Inputs!C91 -> 0 | AA82: =AA79*Inputs!C91 -> 0 | AB82: =AB79*Inputs!C91 -> 0 | AC82: =AC79*Inputs!C91 -> 0 | AD82: =AD79*Inputs!C91 -> 0 | AE82: =AE79*Inputs!C91 -> 0 | AF82: =AF79*Inputs!C91 -> 0 | AG82: =AG79*Inputs!C91 -> 0 | AH82: =AH79*Inputs!C91 -> 0 | AI82: =AI79*Inputs!C91 -> 0 | AJ82: =AJ79*Inputs!C91 -> 0 | AK82: =AK79*Inputs!C91 -> 0 | AL82: =AL79*Inputs!C91 -> 0 | AM82: =AM79*Inputs!C91 -> 0 | AN82: =AN79*Inputs!C91 -> 0 | AO82: =AO79*Inputs!C91 -> 0 | AP82: =AP79*Inputs!C91 -> 0 | AQ82: =AQ79*Inputs!C91 -> 0 | AR82: =AR79*Inputs!C91 -> 0 | AS82: =AS79*Inputs!C91 -> 0 | AT82: =AT79*Inputs!C91 -> 0 | AU82: =AU79*Inputs!C91 -> 0 | AV82: =AV79*Inputs!C91 -> 0 | AW82: =AW79*Inputs!C91 -> 0 | AX82: =AX79*Inputs!C91 -> 0 | AY82: =AY79*Inputs!C91 -> 0 | AZ82: =AZ79*Inputs!C91 -> 0 | BA82: =BA79*Inputs!C91 -> 0 | BB82: =BB79*Inputs!C91 -> 0 | BC82: =BC79*Inputs!C91 -> 0 | BD82: =BD79*Inputs!C91 -> 0 | BE82: =BE79*Inputs!C91 -> 0 | BF82: =BF79*Inputs!C91 -> 0 | BG82: =BG79*Inputs!C91 -> 0 | BH82: =BH79*Inputs!C91 -> 0 | BI82: =BI79*Inputs!C91 -> 0 | BJ82: =BJ79*Inputs!C91 -> 0 | BK82: =BK79*Inputs!C91 -> 0 | BL82: =BL79*Inputs!C91 -> 0 | BM82: =BM79*Inputs!C91 -> 0 | BN82: =BN79*Inputs!C91 -> 0 | BO82: =BO79*Inputs!C91 -> 0 | BP82: =BP79*Inputs!C91 -> 0 | BQ82: =BQ79*Inputs!C91 -> 0 | BR82: =BR79*Inputs!C91 -> 0 | BS82: =BS79*Inputs!C91 -> 0 | BT82: =BT79*Inputs!C91 -> 0 | BU82: =BU79*Inputs!C91 -> 0 | BV82: =BV79*Inputs!C91 -> 0 | BW82: =BW79*Inputs!C91 -> 0 | BX82: =BX79*Inputs!C91 -> 0 | BY82: =BY79*Inputs!C91 -> 0 | BZ82: =BZ79*Inputs!C91 -> 0 | CA82: =CA79*Inputs!C91 -> 0 | CB82: =CB79*Inputs!C91 -> 0 | CC82: =CC79*Inputs!C91 -> 0 | CD82: =CD79*Inputs!C91 -> 0 | CE82: =CE79*Inputs!C91 -> 0 | CF82: =CF79*Inputs!C91 -> 0 | CG82: =CG79*Inputs!C91 -> 0 | CH82: =CH79*Inputs!C91 -> 0 | CI82: =CI79*Inputs!C91 -> 0 | CJ82: =CJ79*Inputs!C91 -> 0 | CK82: =CK79*Inputs!C91 -> 0 | CL82: =CL79*Inputs!C91 -> 0 | CM82: =CM79*Inputs!C91 -> 0 | CN82: =CN79*Inputs!C91 -> 0 | CO82: =CO79*Inputs!C91 -> 0 | CP82: =CP79*Inputs!C91 -> 0 | CQ82: =CQ79*Inputs!C91 -> 0 | CR82: =CR79*Inputs!C91 -> 0 | CS82: =CS79*Inputs!C91 -> 0 | CT82: =CT79*Inputs!C91 -> 0 | CU82: =CU79*Inputs!C91 -> 0 | CV82: =CV79*Inputs!C91 -> 0 | CW82: =CW79*Inputs!C91 -> 0 | CX82: =CX79*Inputs!C91 -> 0 | CY82: =CY79*Inputs!C91 -> 0 | CZ82: =CZ79*Inputs!C91 -> 0 | DA82: =DA79*Inputs!C91 -> 0 | DB82: =DB79*Inputs!C91 -> 0 | DC82: =DC79*Inputs!C91 -> 0 | DD82: =DD79*Inputs!C91 -> 0 | DE82: =DE79*Inputs!C91 -> 0 | DF82: =DF79*Inputs!C91 -> 0 | DG82: =DG79*Inputs!C91 -> 0 | DH82: =DH79*Inputs!C91 -> 0 | DI82: =DI79*Inputs!C91 -> 0 | DJ82: =DJ79*Inputs!C91 -> 0 | DK82: =DK79*Inputs!C91 -> 0 | DL82: =DL79*Inputs!C91 -> 0 | DM82: =DM79*Inputs!C91 -> 0 | DN82: =DN79*Inputs!C91 -> 0 | DO82: =DO79*Inputs!C91 -> 0 | DP82: =DP79*Inputs!C91 -> 0 | DQ82: =DQ79*Inputs!C91 -> 0 | DR82: =DR79*Inputs!C91 -> 0 | DS82: =DS79*Inputs!C91 -> 0
B83: TOTAL DISTRIBUTIONS | C83: =C80+C81+C82 -> 0 | D83: =D80+D81+D82 -> 0 | E83: =E80+E81+E82 -> 0 | F83: =F80+F81+F82 -> 0 | G83: =G80+G81+G82 -> 0 | H83: =H80+H81+H82 -> 0 | I83: =I80+I81+I82 -> 0 | J83: =J80+J81+J82 -> 0 | ... DS83: =DS80+DS81+DS82 -> 85000
B85: CUMULATIVE METRICS
B86: Cumulative NOI | C86: =C20 -> 0 | D86: =C86+D20 -> 0 | E86: =D86+E20 -> 0 | F86: =E86+F20 -> 0 | G86: =F86+G20 -> 0 | H86: =G86+H20 -> 0 | I86: =H86+I20 -> 0 | J86: =I86+J20 -> 0 | K86: =J86+K20 -> 0 | ... DS86: =DR86+DS20 -> 0
B87: Cumulative CF After Debt | C87: =C74 -> -350000 | D87: =C87+D74 -> -350000 | E87: =D87+E74 -> -350000 | F87: =E87+F74 -> -350000 | G87: =F87+G74 -> -350000 | H87: =G87+H74 -> -350000 | I87: =H87+I74 -> -350000 | J87: =I87+J74 -> -350000 | K87: =J87+K74 -> -350000 | ... DS87: =DR87+DS74 -> -350000
B88: DSCR (NOI / Total DS) | C88: =IF(C72=0,"-",C20/ABS(C72)) -> - | D88: =IF(D72=0,"-",D20/ABS(D72)) -> - | E88: =IF(E72=0,"-",E20/ABS(E72)) -> - | F88: =IF(F72=0,"-",F20/ABS(F72)) -> - | G88: =IF(G72=0,"-",G20/ABS(G72)) -> - | H88: =IF(H72=0,"-",H20/ABS(H72)) -> - | I88: =IF(I72=0,"-",I20/ABS(I72)) -> - | J88: =IF(J72=0,"-",J20/ABS(J72)) -> - | ... DS88: =IF(DS72=0,"-",DS20/ABS(DS72)) -> -

Sheet Quarterly CF
A1: QUARTERLY CASHFLOW SUMMARY
A2: Aggregated from Monthly CF | Q1 = Months 1-3, Q2 = Months 4-6, etc.
B3: Line Item | C3: 1 | D3: 2 | E3: 3 | F3: 4 | G3: 5 | H3: 6 | I3: 7 | J3: 8 | K3: 9 | L3: 10 | M3: 11 | N3: 12 | O3: 13 | P3: 14 | Q3: 15 | R3: 16 | S3: 17 | T3: 18 | U3: 19 | V3: 20 | W3: 21 | X3: 22 | Y3: 23 | Z3: 24 | AA3: 25 | AB3: 26 | AC3: 27 | AD3: 28 | AE3: 29 | AF3: 30 | AG3: 31 | AH3: 32 | AI3: 33 | AJ3: 34 | AK3: 35 | AL3: 36 | AM3: 37 | AN3: 38 | AO3: 39 | AP3: 40
B4: REVENUE
B5: Gross Potential Rent | C5: =SUMIF('Monthly CF'!$C$4:$DR$4,C$3,'Monthly CF'!$C$8:$DR$8) -> 0 | D5: =SUMIF('Monthly CF'!$C$4:$DR$4,D$3,'Monthly CF'!$C$8:$DR$8) -> 0 | E5: =SUMIF('Monthly CF'!$C$4:$DR$4,E$3,'Monthly CF'!$C$8:$DR$8) -> 0 | F5: =SUMIF('Monthly CF'!$C$4:$DR$4,F$3,'Monthly CF'!$C$8:$DR$8) -> 0 | G5: =SUMIF('Monthly CF'!$C$4:$DR$4,G$3,'Monthly CF'!$C$8:$DR$8) -> 0 | H5: =SUMIF('Monthly CF'!$C$4:$DR$4,H$3,'Monthly CF'!$C$8:$DR$8) -> 0 | I5: =SUMIF('Monthly CF'!$C$4:$DR$4,I$3,'Monthly CF'!$C$8:$DR$8) -> 0 | J5: =SUMIF('Monthly CF'!$C$4:$DR$4,J$3,'Monthly CF'!$C$8:$DR$8) -> 0 | ... AQ5: =SUMIF('Monthly CF'!$C$4:$DR$4,AQ$3,'Monthly CF'!$C$8:$DR$8) -> 0
B6: Less: Vacancy | C6: =SUMIF('Monthly CF'!$C$4:$DR$4,C$3,'Monthly CF'!$C$9:$DR$9) -> 0 | D6: =SUMIF('Monthly CF'!$C$4:$DR$4,D$3,'Monthly CF'!$C$9:$DR$9) -> 0 | E6: =SUMIF('Monthly CF'!$C$4:$DR$4,E$3,'Monthly CF'!$C$9:$DR$9) -> 0 | F6: =SUMIF('Monthly CF'!$C$4:$DR$4,F$3,'Monthly CF'!$C$9:$DR$9) -> 0 | G6: =SUMIF('Monthly CF'!$C$4:$DR$4,G$3,'Monthly CF'!$C$9:$DR$9) -> 0 | H6: =SUMIF('Monthly CF'!$C$4:$DR$4,H$3,'Monthly CF'!$C$9:$DR$9) -> 0 | I6: =SUMIF('Monthly CF'!$C$4:$DR$4,I$3,'Monthly CF'!$C$9:$DR$9) -> 0 | J6: =SUMIF('Monthly CF'!$C$4:$DR$4,J$3,'Monthly CF'!$C$9:$DR$9) -> 0 | ... AQ6: =SUMIF('Monthly CF'!$C$4:$DR$4,AQ$3,'Monthly CF'!$C$9:$DR$9) -> 0
B7: Less: Credit Loss | C7: =SUMIF('Monthly CF'!$C$4:$DR$4,C$3,'Monthly CF'!$C$10:$DR$10) -> 0 | D7: =SUMIF('Monthly CF'!$C$4:$DR$4,D$3,'Monthly CF'!$C$10:$DR$10) -> 0 | E7: =SUMIF('Monthly CF'!$C$4:$DR$4,E$3,'Monthly CF'!$C$10:$DR$10) -> 0 | F7: =SUMIF('Monthly CF'!$C$4:$DR$4,F$3,'Monthly CF'!$C$10:$DR$10) -> 0 | G7: =SUMIF('Monthly CF'!$C$4:$DR$4,G$3,'Monthly CF'!$C$10:$DR$10) -> 0 | H7: =SUMIF('Monthly CF'!$C$4:$DR$4,H$3,'Monthly CF'!$C$10:$DR$10) -> 0 | I7: =SUMIF('Monthly CF'!$C$4:$DR$4,I$3,'Monthly CF'!$C$10:$DR$10) -> 0 | J7: =SUMIF('Monthly CF'!$C$4:$DR$4,J$3,'Monthly CF'!$C$10:$DR$10) -> 0 | ... AQ7: =SUMIF('Monthly CF'!$C$4:$DR$4,AQ$3,'Monthly CF'!$C$10:$DR$10) -> 0
B8: Effective Gross Income (EGI) | C8: =SUMIF('Monthly CF'!$C$4:$DR$4,C$3,'Monthly CF'!$C$11:$DR$11) -> 0 | D8: =SUMIF('Monthly CF'!$C$4:$DR$4,D$3,'Monthly CF'!$C$11:$DR$11) -> 0 | E8: =SUMIF('Monthly CF'!$C$4:$DR$4,E$3,'Monthly CF'!$C$11:$DR$11) -> 0 | F8: =SUMIF('Monthly CF'!$C$4:$DR$4,F$3,'Monthly CF'!$C$11:$DR$11) -> 0 | G8: =SUMIF('Monthly CF'!$C$4:$DR$4,G$3,'Monthly CF'!$C$11:$DR$11) -> 0 | H8: =SUMIF('Monthly CF'!$C$4:$DR$4,H$3,'Monthly CF'!$C$11:$DR$11) -> 0 | I8: =SUMIF('Monthly CF'!$C$4:$DR$4,I$3,'Monthly CF'!$C$11:$DR$11) -> 0 | J8: =SUMIF('Monthly CF'!$C$4:$DR$4,J$3,'Monthly CF'!$C$11:$DR$11) -> 0 | ... AQ8: =SUMIF('Monthly CF'!$C$4:$DR$4,AQ$3,'Monthly CF'!$C$11:$DR$11) -> 0
B9: Revenue | C9: =SUMIF('Monthly CF'!$C$4:$DR$4,C$3,'Monthly CF'!$C$12:$DR$12) -> 0 | D9: =SUMIF('Monthly CF'!$C$4:$DR$4,D$3,'Monthly CF'!$C$12:$DR$12) -> 0 | E9: =SUMIF('Monthly CF'!$C$4:$DR$4,E$3,'Monthly CF'!$C$12:$DR$12) -> 0 | F9: =SUMIF('Monthly CF'!$C$4:$DR$4,F$3,'Monthly CF'!$C$12:$DR$12) -> 0 | G9: =SUMIF('Monthly CF'!$C$4:$DR$4,G$3,'Monthly CF'!$C$12:$DR$12) -> 0 | H9: =SUMIF('Monthly CF'!$C$4:$DR$4,H$3,'Monthly CF'!$C$12:$DR$12) -> 0 | I9: =SUMIF('Monthly CF'!$C$4:$DR$4,I$3,'Monthly CF'!$C$12:$DR$12) -> 0 | J9: =SUMIF('Monthly CF'!$C$4:$DR$4,J$3,'Monthly CF'!$C$12:$DR$12) -> 0 | ... AQ9: =SUMIF('Monthly CF'!$C$4:$DR$4,AQ$3,'Monthly CF'!$C$12:$DR$12) -> 0
B10: TOTAL REVENUE | C10: =SUMIF('Monthly CF'!$C$4:$DR$4,C$3,'Monthly CF'!$C$13:$DR$13) -> 0 | D10: =SUMIF('Monthly CF'!$C$4:$DR$4,D$3,'Monthly CF'!$C$13:$DR$13) -> 0 | E10: =SUMIF('Monthly CF'!$C$4:$DR$4,E$3,'Monthly CF'!$C$13:$DR$13) -> 0 | F10: =SUMIF('Monthly CF'!$C$4:$DR$4,F$3,'Monthly CF'!$C$13:$DR$13) -> 0 | G10: =SUMIF('Monthly CF'!$C$4:$DR$4,G$3,'Monthly CF'!$C$13:$DR$13) -> 0 | H10: =SUMIF('Monthly CF'!$C$4:$DR$4,H$3,'Monthly CF'!$C$13:$DR$13) -> 0 | I10: =SUMIF('Monthly CF'!$C$4:$DR$4,I$3,'Monthly CF'!$C$13:$DR$13) -> 0 | J10: =SUMIF('Monthly CF'!$C$4:$DR$4,J$3,'Monthly CF'!$C$13:$DR$13) -> 0 | ... AQ10: =SUMIF('Monthly CF'!$C$4:$DR$4,AQ$3,'Monthly CF'!$C$13:$DR$13) -> 0
B12: OPERATING EXPENSES
B13: Property Management Fee (%EGI) | C13: =SUMIF('Monthly CF'!$C$4:$DR$4,C$3,'Monthly CF'!$C$16:$DR$16) -> 0 | D13: =SUMIF('Monthly CF'!$C$4:$DR$4,D$3,'Monthly CF'!$C$16:$DR$16) -> 0 | E13: =SUMIF('Monthly CF'!$C$4:$DR$4,E$3,'Monthly CF'!$C$16:$DR$16) -> 0 | F13: =SUMIF('Monthly CF'!$C$4:$DR$4,F$3,'Monthly CF'!$C$16:$DR$16) -> 0 | G13: =SUMIF('Monthly CF'!$C$4:$DR$4,G$3,'Monthly CF'!$C$16:$DR$16) -> 0 | H13: =SUMIF('Monthly CF'!$C$4:$DR$4,H$3,'Monthly CF'!$C$16:$DR$16) -> 0 | I13: =SUMIF('Monthly CF'!$C$4:$DR$4,I$3,'Monthly CF'!$C$16:$DR$16) -> 0 | J13: =SUMIF('Monthly CF'!$C$4:$DR$4,J$3,'Monthly CF'!$C$16:$DR$16) -> 0 | ... AQ13: =SUMIF('Monthly CF'!$C$4:$DR$4,AQ$3,'Monthly CF'!$C$16:$DR$16) -> 0
B14: Expenses | C14: =SUMIF('Monthly CF'!$C$4:$DR$4,C$3,'Monthly CF'!$C$17:$DR$17) -> 0 | D14: =SUMIF('Monthly CF'!$C$4:$DR$4,D$3,'Monthly CF'!$C$17:$DR$17) -> 0 | E14: =SUMIF('Monthly CF'!$C$4:$DR$4,E$3,'Monthly CF'!$C$17:$DR$17) -> 0 | F14: =SUMIF('Monthly CF'!$C$4:$DR$4,F$3,'Monthly CF'!$C$17:$DR$17) -> 0 | G14: =SUMIF('Monthly CF'!$C$4:$DR$4,G$3,'Monthly CF'!$C$17:$DR$17) -> 0 | H14: =SUMIF('Monthly CF'!$C$4:$DR$4,H$3,'Monthly CF'!$C$17:$DR$17) -> 0 | I14: =SUMIF('Monthly CF'!$C$4:$DR$4,I$3,'Monthly CF'!$C$17:$DR$17) -> 0 | J14: =SUMIF('Monthly CF'!$C$4:$DR$4,J$3,'Monthly CF'!$C$17:$DR$17) -> 0 | ... AQ14: =SUMIF('Monthly CF'!$C$4:$DR$4,AQ$3,'Monthly CF'!$C$17:$DR$17) -> 0
B16: TOTAL OPERATING EXPENSES | C16: =SUMIF('Monthly CF'!$C$4:$DR$4,C$3,'Monthly CF'!$C$18:$DR$18) -> 0 | D16: =SUMIF('Monthly CF'!$C$4:$DR$4,D$3,'Monthly CF'!$C$18:$DR$18) -> 0 | E16: =SUMIF('Monthly CF'!$C$4:$DR$4,E$3,'Monthly CF'!$C$18:$DR$18) -> 0 | F16: =SUMIF('Monthly CF'!$C$4:$DR$4,F$3,'Monthly CF'!$C$18:$DR$18) -> 0 | G16: =SUMIF('Monthly CF'!$C$4:$DR$4,G$3,'Monthly CF'!$C$18:$DR$18) -> 0 | H16: =SUMIF('Monthly CF'!$C$4:$DR$4,H$3,'Monthly CF'!$C$18:$DR$18) -> 0 | I16: =SUMIF('Monthly CF'!$C$4:$DR$4,I$3,'Monthly CF'!$C$18:$DR$18) -> 0 | J16: =SUMIF('Monthly CF'!$C$4:$DR$4,J$3,'Monthly CF'!$C$18:$DR$18) -> 0 | ... AQ16: =SUMIF('Monthly CF'!$C$4:$DR$4,AQ$3,'Monthly CF'!$C$18:$DR$18) -> 0
B18: NET OPERATING INCOME (NOI) | C18: =SUMIF('Monthly CF'!$C$4:$DR$4,C$3,'Monthly CF'!$C$20:$DR$20) -> 0 | D18: =SUMIF('Monthly CF'!$C$4:$DR$4,D$3,'Monthly CF'!$C$20:$DR$20) -> 0 | E18: =SUMIF('Monthly CF'!$C$4:$DR$4,E$3,'Monthly CF'!$C$20:$DR$20) -> 0 | F18: =SUMIF('Monthly CF'!$C$4:$DR$4,F$3,'Monthly CF'!$C$20:$DR$20) -> 0 | G18: =SUMIF('Monthly CF'!$C$4:$DR$4,G$3,'Monthly CF'!$C$20:$DR$20) -> 0 | H18: =SUMIF('Monthly CF'!$C$4:$DR$4,H$3,'Monthly CF'!$C$20:$DR$20) -> 0 | I18: =SUMIF('Monthly CF'!$C$4:$DR$4,I$3,'Monthly CF'!$C$20:$DR$20) -> 0 | J18: =SUMIF('Monthly CF'!$C$4:$DR$4,J$3,'Monthly CF'!$C$20:$DR$20) -> 0 | ... AQ18: =SUMIF('Monthly CF'!$C$4:$DR$4,AQ$3,'Monthly CF'!$C$20:$DR$20) -> 0
B20: Capital Expenditures | C20: =SUMIF('Monthly CF'!$C$4:$DR$4,C$3,'Monthly CF'!$C$23:$DR$23) -> 0 | D20: =SUMIF('Monthly CF'!$C$4:$DR$4,D$3,'Monthly CF'!$C$23:$DR$23) -> 0 | E20: =SUMIF('Monthly CF'!$C$4:$DR$4,E$3,'Monthly CF'!$C$23:$DR$23) -> 0 | F20: =SUMIF('Monthly CF'!$C$4:$DR$4,F$3,'Monthly CF'!$C$23:$DR$23) -> 0 | G20: =SUMIF('Monthly CF'!$C$4:$DR$4,G$3,'Monthly CF'!$C$23:$DR$23) -> 0 | H20: =SUMIF('Monthly CF'!$C$4:$DR$4,H$3,'Monthly CF'!$C$23:$DR$23) -> 0 | I20: =SUMIF('Monthly CF'!$C$4:$DR$4,I$3,'Monthly CF'!$C$23:$DR$23) -> 0 | J20: =SUMIF('Monthly CF'!$C$4:$DR$4,J$3,'Monthly CF'!$C$23:$DR$23) -> 0 | ... AQ20: =SUMIF('Monthly CF'!$C$4:$DR$4,AQ$3,'Monthly CF'!$C$23:$DR$23) -> 0
B22: Acquisition Costs (Yr 1 only) | C22: =SUMIF('Monthly CF'!$C$4:$DR$4,C$3,'Monthly CF'!$C$32:$DR$32) -> -5000 | D22: =SUMIF('Monthly CF'!$C$4:$DR$4,D$3,'Monthly CF'!$C$32:$DR$32) -> 0 | E22: =SUMIF('Monthly CF'!$C$4:$DR$4,E$3,'Monthly CF'!$C$32:$DR$32) -> 0 | F22: =SUMIF('Monthly CF'!$C$4:$DR$4,F$3,'Monthly CF'!$C$32:$DR$32) -> 0 | G22: =SUMIF('Monthly CF'!$C$4:$DR$4,G$3,'Monthly CF'!$C$32:$DR$32) -> 0 | H22: =SUMIF('Monthly CF'!$C$4:$DR$4,H$3,'Monthly CF'!$C$32:$DR$32) -> 0 | I22: =SUMIF('Monthly CF'!$C$4:$DR$4,I$3,'Monthly CF'!$C$32:$DR$32) -> 0 | J22: =SUMIF('Monthly CF'!$C$4:$DR$4,J$3,'Monthly CF'!$C$32:$DR$32) -> 0 | ... AQ22: =SUMIF('Monthly CF'!$C$4:$DR$4,AQ$3,'Monthly CF'!$C$32:$DR$32) -> 0
B24: DISPOSITION / EXIT
B25: Sale Proceeds | C25: =SUMIF('Monthly CF'!$C$4:$DR$4,C$3,'Monthly CF'!$C$35:$DR$35) -> 0 | D25: =SUMIF('Monthly CF'!$C$4:$DR$4,D$3,'Monthly CF'!$C$35:$DR$35) -> 0 | E25: =SUMIF('Monthly CF'!$C$4:$DR$4,E$3,'Monthly CF'!$C$35:$DR$35) -> 0 | F25: =SUMIF('Monthly CF'!$C$4:$DR$4,F$3,'Monthly CF'!$C$35:$DR$35) -> 0 | G25: =SUMIF('Monthly CF'!$C$4:$DR$4,G$3,'Monthly CF'!$C$35:$DR$35) -> 0 | H25: =SUMIF('Monthly CF'!$C$4:$DR$4,H$3,'Monthly CF'!$C$35:$DR$35) -> 0 | I25: =SUMIF('Monthly CF'!$C$4:$DR$4,I$3,'Monthly CF'!$C$35:$DR$35) -> 0 | J25: =SUMIF('Monthly CF'!$C$4:$DR$4,J$3,'Monthly CF'!$C$35:$DR$35) -> 0 | ... AQ25: =SUMIF('Monthly CF'!$C$4:$DR$4,AQ$3,'Monthly CF'!$C$35:$DR$35) -> 0
B26: Selling Costs | C26: =SUMIF('Monthly CF'!$C$4:$DR$4,C$3,'Monthly CF'!$C$36:$DR$36) -> 0 | D26: =SUMIF('Monthly CF'!$C$4:$DR$4,D$3,'Monthly CF'!$C$36:$DR$36) -> 0 | E26: =SUMIF('Monthly CF'!$C$4:$DR$4,E$3,'Monthly CF'!$C$36:$DR$36) -> 0 | F26: =SUMIF('Monthly CF'!$C$4:$DR$4,F$3,'Monthly CF'!$C$36:$DR$36) -> 0 | G26: =SUMIF('Monthly CF'!$C$4:$DR$4,G$3,'Monthly CF'!$C$36:$DR$36) -> 0 | H26: =SUMIF('Monthly CF'!$C$4:$DR$4,H$3,'Monthly CF'!$C$36:$DR$36) -> 0 | I26: =SUMIF('Monthly CF'!$C$4:$DR$4,I$3,'Monthly CF'!$C$36:$DR$36) -> 0 | J26: =SUMIF('Monthly CF'!$C$4:$DR$4,J$3,'Monthly CF'!$C$36:$DR$36) -> 0 | ... AQ26: =SUMIF('Monthly CF'!$C$4:$DR$4,AQ$3,'Monthly CF'!$C$36:$DR$36) -> 0
B27: NET SALE PROCEEDS | C27: =SUMIF('Monthly CF'!$C$4:$DR$4,C$3,'Monthly CF'!$C$37:$DR$37) -> 0 | D27: =SUMIF('Monthly CF'!$C$4:$DR$4,D$3,'Monthly CF'!$C$37:$DR$37) -> 0 | E27: =SUMIF('Monthly CF'!$C$4:$DR$4,E$3,'Monthly CF'!$C$37:$DR$37) -> 0 | F27: =SUMIF('Monthly CF'!$C$4:$DR$4,F$3,'Monthly CF'!$C$37:$DR$37) -> 0 | G27: =SUMIF('Monthly CF'!$C$4:$DR$4,G$3,'Monthly CF'!$C$37:$DR$37) -> 0 | H27: =SUMIF('Monthly CF'!$C$4:$DR$4,H$3,'Monthly CF'!$C$37:$DR$37) -> 0 | I27: =SUMIF('Monthly CF'!$C$4:$DR$4,I$3,'Monthly CF'!$C$37:$DR$37) -> 0 | J27: =SUMIF('Monthly CF'!$C$4:$DR$4,J$3,'Monthly CF'!$C$37:$DR$37) -> 0 | ... AQ27: =SUMIF('Monthly CF'!$C$4:$DR$4,AQ$3,'Monthly CF'!$C$37:$DR$37) -> 0
B29: CASHFLOW BEFORE DEBT SERVICE | C29: =SUMIF('Monthly CF'!$C$4:$DR$4,C$3,'Monthly CF'!$C$39:$DR$39) -> -5000 | D29: =SUMIF('Monthly CF'!$C$4:$DR$4,D$3,'Monthly CF'!$C$39:$DR$39) -> 0 | E29: =SUMIF('Monthly CF'!$C$4:$DR$4,E$3,'Monthly CF'!$C$39:$DR$39) -> 0 | F29: =SUMIF('Monthly CF'!$C$4:$DR$4,F$3,'Monthly CF'!$C$39:$DR$39) -> 0 | G29: =SUMIF('Monthly CF'!$C$4:$DR$4,G$3,'Monthly CF'!$C$39:$DR$39) -> 0 | H29: =SUMIF('Monthly CF'!$C$4:$DR$4,H$3,'Monthly CF'!$C$39:$DR$39) -> 0 | I29: =SUMIF('Monthly CF'!$C$4:$DR$4,I$3,'Monthly CF'!$C$39:$DR$39) -> 0 | J29: =SUMIF('Monthly CF'!$C$4:$DR$4,J$3,'Monthly CF'!$C$39:$DR$39) -> 0 | ... AQ29: =SUMIF('Monthly CF'!$C$4:$DR$4,AQ$3,'Monthly CF'!$C$39:$DR$39) -> 0
B31: DEBT SERVICE — SELLER FINANCE
B32: Beginning Balance | C32: {=INDEX('Monthly CF'!$C$42:$DR$42,MATCH((C$3-1)*3+1,'Monthly CF'!$C$3:$DR$3,0))} -> 0 | D32: {=INDEX('Monthly CF'!$C$42:$DR$42,MATCH((D$3-1)*3+1,'Monthly CF'!$C$3:$DR$3,0))} -> 0 | E32: {=INDEX('Monthly CF'!$C$42:$DR$42,MATCH((E$3-1)*3+1,'Monthly CF'!$C$3:$DR$3,0))} -> 0 | F32: {=INDEX('Monthly CF'!$C$42:$DR$42,MATCH((F$3-1)*3+1,'Monthly CF'!$C$3:$DR$3,0))} -> 0 | G32: {=INDEX('Monthly CF'!$C$42:$DR$42,MATCH((G$3-1)*3+1,'Monthly CF'!$C$3:$DR$3,0))} -> 0 | H32: {=INDEX('Monthly CF'!$C$42:$DR$42,MATCH((H$3-1)*3+1,'Monthly CF'!$C$3:$DR$3,0))} -> 0 | I32: {=INDEX('Monthly CF'!$C$42:$DR$42,MATCH((I$3-1)*3+1,'Monthly CF'!$C$3:$DR$3,0))} -> 0 | J32: {=INDEX('Monthly CF'!$C$42:$DR$42,MATCH((J$3-1)*3+1,'Monthly CF'!$C$3:$DR$3,0))} -> 0 | ... AQ32: {=INDEX('Monthly CF'!$C$42:$DR$42,MATCH((AQ$3-1)*3+1,'Monthly CF'!$C$3:$DR$3,0))} -> #N/A
B33: Loan Funding | C33: =SUMIF('Monthly CF'!$C$4:$DR$4,C$3,'Monthly CF'!$C$43:$DR$43) -> 0 | D33: =SUMIF('Monthly CF'!$C$4:$DR$4,D$3,'Monthly CF'!$C$43:$DR$43) -> 0 | E33: =SUMIF('Monthly CF'!$C$4:$DR$4,E$3,'Monthly CF'!$C$43:$DR$43) -> 0 | F33: =SUMIF('Monthly CF'!$C$4:$DR$4,F$3,'Monthly CF'!$C$43:$DR$43) -> 0 | G33: =SUMIF('Monthly CF'!$C$4:$DR$4,G$3,'Monthly CF'!$C$43:$DR$43) -> 0 | H33: =SUMIF('Monthly CF'!$C$4:$DR$4,H$3,'Monthly CF'!$C$43:$DR$43) -> 0 | I33: =SUMIF('Monthly CF'!$C$4:$DR$4,I$3,'Monthly CF'!$C$43:$DR$43) -> 0 | J33: =SUMIF('Monthly CF'!$C$4:$DR$4,J$3,'Monthly CF'!$C$43:$DR$43) -> 0 | ... AQ33: =SUMIF('Monthly CF'!$C$4:$DR$4,AQ$3,'Monthly CF'!$C$43:$DR$43) -> 0
B34: Interest Payment | C34: =SUMIF('Monthly CF'!$C$4:$DR$4,C$3,'Monthly CF'!$C$44:$DR$44) -> 0 | D34: =SUMIF('Monthly CF'!$C$4:$DR$4,D$3,'Monthly CF'!$C$44:$DR$44) -> 0 | E34: =SUMIF('Monthly CF'!$C$4:$DR$4,E$3,'Monthly CF'!$C$44:$DR$44) -> 0 | F34: =SUMIF('Monthly CF'!$C$4:$DR$4,F$3,'Monthly CF'!$C$44:$DR$44) -> 0 | G34: =SUMIF('Monthly CF'!$C$4:$DR$4,G$3,'Monthly CF'!$C$44:$DR$44) -> 0 | H34: =SUMIF('Monthly CF'!$C$4:$DR$4,H$3,'Monthly CF'!$C$44:$DR$44) -> 0 | I34: =SUMIF('Monthly CF'!$C$4:$DR$4,I$3,'Monthly CF'!$C$44:$DR$44) -> 0 | J34: =SUMIF('Monthly CF'!$C$4:$DR$4,J$3,'Monthly CF'!$C$44:$DR$44) -> 0 | ... AQ34: =SUMIF('Monthly CF'!$C$4:$DR$4,AQ$3,'Monthly CF'!$C$44:$DR$44) -> 0
B35: Principal Payment | C35: =SUMIF('Monthly CF'!$C$4:$DR$4,C$3,'Monthly CF'!$C$45:$DR$45) -> 0 | D35: =SUMIF('Monthly CF'!$C$4:$DR$4,D$3,'Monthly CF'!$C$45:$DR$45) -> 0 | E35: =SUMIF('Monthly CF'!$C$4:$DR$4,E$3,'Monthly CF'!$C$45:$DR$45) -> 0 | F35: =SUMIF('Monthly CF'!$C$4:$DR$4,F$3,'Monthly CF'!$C$45:$DR$45) -> 0 | G35: =SUMIF('Monthly CF'!$C$4:$DR$4,G$3,'Monthly CF'!$C$45:$DR$45) -> 0 | H35: =SUMIF('Monthly CF'!$C$4:$DR$4,H$3,'Monthly CF'!$C$45:$DR$45) -> 0 | I35: =SUMIF('Monthly CF'!$C$4:$DR$4,I$3,'Monthly CF'!$C$45:$DR$45) -> 0 | J35: =SUMIF('Monthly CF'!$C$4:$DR$4,J$3,'Monthly CF'!$C$45:$DR$45) -> 0 | ... AQ35: =SUMIF('Monthly CF'!$C$4:$DR$4,AQ$3,'Monthly CF'!$C$45:$DR$45) -> 0
B36: Loan Payoff | C36: =SUMIF('Monthly CF'!$C$4:$DR$4,C$3,'Monthly CF'!$C$46:$DR$46) -> 0 | D36: =SUMIF('Monthly CF'!$C$4:$DR$4,D$3,'Monthly CF'!$C$46:$DR$46) -> 0 | E36: =SUMIF('Monthly CF'!$C$4:$DR$4,E$3,'Monthly CF'!$C$46:$DR$46) -> 0 | F36: =SUMIF('Monthly CF'!$C$4:$DR$4,F$3,'Monthly CF'!$C$46:$DR$46) -> 0 | G36: =SUMIF('Monthly CF'!$C$4:$DR$4,G$3,'Monthly CF'!$C$46:$DR$46) -> 0 | H36: =SUMIF('Monthly CF'!$C$4:$DR$4,H$3,'Monthly CF'!$C$46:$DR$46) -> 0 | I36: =SUMIF('Monthly CF'!$C$4:$DR$4,I$3,'Monthly CF'!$C$46:$DR$46) -> 0 | J36: =SUMIF('Monthly CF'!$C$4:$DR$4,J$3,'Monthly CF'!$C$46:$DR$46) -> 0 | ... AQ36: =SUMIF('Monthly CF'!$C$4:$DR$4,AQ$3,'Monthly CF'!$C$46:$DR$46) -> 0
B37: Ending Balance | C37: {=INDEX('Monthly CF'!$C$47:$DR$47,MATCH(C$3*3,'Monthly CF'!$C$3:$DR$3,0))} -> 0 | D37: {=INDEX('Monthly CF'!$C$47:$DR$47,MATCH(D$3*3,'Monthly CF'!$C$3:$DR$3,0))} -> 0 | E37: {=INDEX('Monthly CF'!$C$47:$DR$47,MATCH(E$3*3,'Monthly CF'!$C$3:$DR$3,0))} -> 0 | F37: {=INDEX('Monthly CF'!$C$47:$DR$47,MATCH(F$3*3,'Monthly CF'!$C$3:$DR$3,0))} -> 0 | G37: {=INDEX('Monthly CF'!$C$47:$DR$47,MATCH(G$3*3,'Monthly CF'!$C$3:$DR$3,0))} -> 0 | H37: {=INDEX('Monthly CF'!$C$47:$DR$47,MATCH(H$3*3,'Monthly CF'!$C$3:$DR$3,0))} -> 0 | I37: {=INDEX('Monthly CF'!$C$47:$DR$47,MATCH(I$3*3,'Monthly CF'!$C$3:$DR$3,0))} -> 0 | J37: {=INDEX('Monthly CF'!$C$47:$DR$47,MATCH(J$3*3,'Monthly CF'!$C$3:$DR$3,0))} -> 0 | ... AQ37: {=INDEX('Monthly CF'!$C$47:$DR$47,MATCH(AQ$3*3,'Monthly CF'!$C$3:$DR$3,0))} -> #N/A
B38: Total Debt Service (SF) | C38: =SUMIF('Monthly CF'!$C$4:$DR$4,C$3,'Monthly CF'!$C$48:$DR$48) -> 0 | D38: =SUMIF('Monthly CF'!$C$4:$DR$4,D$3,'Monthly CF'!$C$48:$DR$48) -> 0 | E38: =SUMIF('Monthly CF'!$C$4:$DR$4,E$3,'Monthly CF'!$C$48:$DR$48) -> 0 | F38: =SUMIF('Monthly CF'!$C$4:$DR$4,F$3,'Monthly CF'!$C$48:$DR$48) -> 0 | G38: =SUMIF('Monthly CF'!$C$4:$DR$4,G$3,'Monthly CF'!$C$48:$DR$48) -> 0 | H38: =SUMIF('Monthly CF'!$C$4:$DR$4,H$3,'Monthly CF'!$C$48:$DR$48) -> 0 | I38: =SUMIF('Monthly CF'!$C$4:$DR$4,I$3,'Monthly CF'!$C$48:$DR$48) -> 0 | J38: =SUMIF('Monthly CF'!$C$4:$DR$4,J$3,'Monthly CF'!$C$48:$DR$48) -> 0 | ... AQ38: =SUMIF('Monthly CF'!$C$4:$DR$4,AQ$3,'Monthly CF'!$C$48:$DR$48) -> 0
B40: DEBT SERVICE — BANK LOAN
B41: Beginning Balance | C41: {=INDEX('Monthly CF'!$C$51:$DR$51,MATCH((C$3-1)*3+1,'Monthly CF'!$C$3:$DR$3,0))} -> 0 | D41: {=INDEX('Monthly CF'!$C$51:$DR$51,MATCH((D$3-1)*3+1,'Monthly CF'!$C$3:$DR$3,0))} -> 0 | E41: {=INDEX('Monthly CF'!$C$51:$DR$51,MATCH((E$3-1)*3+1,'Monthly CF'!$C$3:$DR$3,0))} -> 0 | F41: {=INDEX('Monthly CF'!$C$51:$DR$51,MATCH((F$3-1)*3+1,'Monthly CF'!$C$3:$DR$3,0))} -> 0 | G41: {=INDEX('Monthly CF'!$C$51:$DR$51,MATCH((G$3-1)*3+1,'Monthly CF'!$C$3:$DR$3,0))} -> 0 | H41: {=INDEX('Monthly CF'!$C$51:$DR$51,MATCH((H$3-1)*3+1,'Monthly CF'!$C$3:$DR$3,0))} -> 0 | I41: {=INDEX('Monthly CF'!$C$51:$DR$51,MATCH((I$3-1)*3+1,'Monthly CF'!$C$3:$DR$3,0))} -> 0 | J41: {=INDEX('Monthly CF'!$C$51:$DR$51,MATCH((J$3-1)*3+1,'Monthly CF'!$C$3:$DR$3,0))} -> 0 | ... AQ41: {=INDEX('Monthly CF'!$C$51:$DR$51,MATCH((AQ$3-1)*3+1,'Monthly CF'!$C$3:$DR$3,0))} -> #N/A
B42: Loan Funding | C42: =SUMIF('Monthly CF'!$C$4:$DR$4,C$3,'Monthly CF'!$C$52:$DR$52) -> 0 | D42: =SUMIF('Monthly CF'!$C$4:$DR$4,D$3,'Monthly CF'!$C$52:$DR$52) -> 0 | E42: =SUMIF('Monthly CF'!$C$4:$DR$4,E$3,'Monthly CF'!$C$52:$DR$52) -> 0 | F42: =SUMIF('Monthly CF'!$C$4:$DR$4,F$3,'Monthly CF'!$C$52:$DR$52) -> 0 | G42: =SUMIF('Monthly CF'!$C$4:$DR$4,G$3,'Monthly CF'!$C$52:$DR$52) -> 0 | H42: =SUMIF('Monthly CF'!$C$4:$DR$4,H$3,'Monthly CF'!$C$52:$DR$52) -> 0 | I42: =SUMIF('Monthly CF'!$C$4:$DR$4,I$3,'Monthly CF'!$C$52:$DR$52) -> 0 | J42: =SUMIF('Monthly CF'!$C$4:$DR$4,J$3,'Monthly CF'!$C$52:$DR$52) -> 0 | ... AQ42: =SUMIF('Monthly CF'!$C$4:$DR$4,AQ$3,'Monthly CF'!$C$52:$DR$52) -> 0
B43: Interest Payment | C43: =SUMIF('Monthly CF'!$C$4:$DR$4,C$3,'Monthly CF'!$C$53:$DR$53) -> 0 | D43: =SUMIF('Monthly CF'!$C$4:$DR$4,D$3,'Monthly CF'!$C$53:$DR$53) -> 0 | E43: =SUMIF('Monthly CF'!$C$4:$DR$4,E$3,'Monthly CF'!$C$53:$DR$53) -> 0 | F43: =SUMIF('Monthly CF'!$C$4:$DR$4,F$3,'Monthly CF'!$C$53:$DR$53) -> 0 | G43: =SUMIF('Monthly CF'!$C$4:$DR$4,G$3,'Monthly CF'!$C$53:$DR$53) -> 0 | H43: =SUMIF('Monthly CF'!$C$4:$DR$4,H$3,'Monthly CF'!$C$53:$DR$53) -> 0 | I43: =SUMIF('Monthly CF'!$C$4:$DR$4,I$3,'Monthly CF'!$C$53:$DR$53) -> 0 | J43: =SUMIF('Monthly CF'!$C$4:$DR$4,J$3,'Monthly CF'!$C$53:$DR$53) -> 0 | ... AQ43: =SUMIF('Monthly CF'!$C$4:$DR$4,AQ$3,'Monthly CF'!$C$53:$DR$53) -> 0
B44: Principal Payment | C44: =SUMIF('Monthly CF'!$C$4:$DR$4,C$3,'Monthly CF'!$C$54:$DR$54) -> 0 | D44: =SUMIF('Monthly CF'!$C$4:$DR$4,D$3,'Monthly CF'!$C$54:$DR$54) -> 0 | E44: =SUMIF('Monthly CF'!$C$4:$DR$4,E$3,'Monthly CF'!$C$54:$DR$54) -> 0 | F44: =SUMIF('Monthly CF'!$C$4:$DR$4,F$3,'Monthly CF'!$C$54:$DR$54) -> 0 | G44: =SUMIF('Monthly CF'!$C$4:$DR$4,G$3,'Monthly CF'!$C$54:$DR$54) -> 0 | H44: =SUMIF('Monthly CF'!$C$4:$DR$4,H$3,'Monthly CF'!$C$54:$DR$54) -> 0 | I44: =SUMIF('Monthly CF'!$C$4:$DR$4,I$3,'Monthly CF'!$C$54:$DR$54) -> 0 | J44: =SUMIF('Monthly CF'!$C$4:$DR$4,J$3,'Monthly CF'!$C$54:$DR$54) -> 0 | ... AQ44: =SUMIF('Monthly CF'!$C$4:$DR$4,AQ$3,'Monthly CF'!$C$54:$DR$54) -> 0
B45: Loan Payoff / Refi Payoff | C45: =SUMIF('Monthly CF'!$C$4:$DR$4,C$3,'Monthly CF'!$C$55:$DR$55) -> 0 | D45: =SUMIF('Monthly CF'!$C$4:$DR$4,D$3,'Monthly CF'!$C$55:$DR$55) -> 0 | E45: =SUMIF('Monthly CF'!$C$4:$DR$4,E$3,'Monthly CF'!$C$55:$DR$55) -> 0 | F45: =SUMIF('Monthly CF'!$C$4:$DR$4,F$3,'Monthly CF'!$C$55:$DR$55) -> 0 | G45: =SUMIF('Monthly CF'!$C$4:$DR$4,G$3,'Monthly CF'!$C$55:$DR$55) -> 0 | H45: =SUMIF('Monthly CF'!$C$4:$DR$4,H$3,'Monthly CF'!$C$55:$DR$55) -> 0 | I45: =SUMIF('Monthly CF'!$C$4:$DR$4,I$3,'Monthly CF'!$C$55:$DR$55) -> 0 | J45: =SUMIF('Monthly CF'!$C$4:$DR$4,J$3,'Monthly CF'!$C$55:$DR$55) -> 0 | ... AQ45: =SUMIF('Monthly CF'!$C$4:$DR$4,AQ$3,'Monthly CF'!$C$55:$DR$55) -> 0
B46: Ending Balance | C46: {=INDEX('Monthly CF'!$C$56:$DR$56,MATCH(C$3*3,'Monthly CF'!$C$3:$DR$3,0))} -> 0 | D46: {=INDEX('Monthly CF'!$C$56:$DR$56,MATCH(D$3*3,'Monthly CF'!$C$3:$DR$3,0))} -> 0 | E46: {=INDEX('Monthly CF'!$C$56:$DR$56,MATCH(E$3*3,'Monthly CF'!$C$3:$DR$3,0))} -> 0 | F46: {=INDEX('Monthly CF'!$C$56:$DR$56,MATCH(F$3*3,'Monthly CF'!$C$3:$DR$3,0))} -> 0 | G46: {=INDEX('Monthly CF'!$C$56:$DR$56,MATCH(G$3*3,'Monthly CF'!$C$3:$DR$3,0))} -> 0 | H46: {=INDEX('Monthly CF'!$C$56:$DR$56,MATCH(H$3*3,'Monthly CF'!$C$3:$DR$3,0))} -> 0 | I46: {=INDEX('Monthly CF'!$C$56:$DR$56,MATCH(I$3*3,'Monthly CF'!$C$3:$DR$3,0))} -> 0 | J46: {=INDEX('Monthly CF'!$C$56:$DR$56,MATCH(J$3*3,'Monthly CF'!$C$3:$DR$3,0))} -> 0 | ... AQ46: {=INDEX('Monthly CF'!$C$56:$DR$56,MATCH(AQ$3*3,'Monthly CF'!$C$3:$DR$3,0))} -> #N/A
B47: Total Debt Service (BL) | C47: =SUMIF('Monthly CF'!$C$4:$DR$4,C$3,'Monthly CF'!$C$57:$DR$57) -> 0 | D47: =SUMIF('Monthly CF'!$C$4:$DR$4,D$3,'Monthly CF'!$C$57:$DR$57) -> 0 | E47: =SUMIF('Monthly CF'!$C$4:$DR$4,E$3,'Monthly CF'!$C$57:$DR$57) -> 0 | F47: =SUMIF('Monthly CF'!$C$4:$DR$4,F$3,'Monthly CF'!$C$57:$DR$57) -> 0 | G47: =SUMIF('Monthly CF'!$C$4:$DR$4,G$3,'Monthly CF'!$C$57:$DR$57) -> 0 | H47: =SUMIF('Monthly CF'!$C$4:$DR$4,H$3,'Monthly CF'!$C$57:$DR$57) -> 0 | I47: =SUMIF('Monthly CF'!$C$4:$DR$4,I$3,'Monthly CF'!$C$57:$DR$57) -> 0 | J47: =SUMIF('Monthly CF'!$C$4:$DR$4,J$3,'Monthly CF'!$C$57:$DR$57) -> 0 | ... AQ47: =SUMIF('Monthly CF'!$C$4:$DR$4,AQ$3,'Monthly CF'!$C$57:$DR$57) -> 0
B49: DEBT SERVICE — REFINANCE LOAN
B50: Beginning Balance | C50: {=INDEX('Monthly CF'!$C$60:$DR$60,MATCH((C$3-1)*3+1,'Monthly CF'!$C$3:$DR$3,0))} -> 0 | D50: {=INDEX('Monthly CF'!$C$60:$DR$60,MATCH((D$3-1)*3+1,'Monthly CF'!$C$3:$DR$3,0))} -> 0 | E50: {=INDEX('Monthly CF'!$C$60:$DR$60,MATCH((E$3-1)*3+1,'Monthly CF'!$C$3:$DR$3,0))} -> 0 | F50: {=INDEX('Monthly CF'!$C$60:$DR$60,MATCH((F$3-1)*3+1,'Monthly CF'!$C$3:$DR$3,0))} -> 0 | G50: {=INDEX('Monthly CF'!$C$60:$DR$60,MATCH((G$3-1)*3+1,'Monthly CF'!$C$3:$DR$3,0))} -> 0 | H50: {=INDEX('Monthly CF'!$C$60:$DR$60,MATCH((H$3-1)*3+1,'Monthly CF'!$C$3:$DR$3,0))} -> 0 | I50: {=INDEX('Monthly CF'!$C$60:$DR$60,MATCH((I$3-1)*3+1,'Monthly CF'!$C$3:$DR$3,0))} -> 0 | J50: {=INDEX('Monthly CF'!$C$60:$DR$60,MATCH((J$3-1)*3+1,'Monthly CF'!$C$3:$DR$3,0))} -> 0 | ... AQ50: {=INDEX('Monthly CF'!$C$60:$DR$60,MATCH((AQ$3-1)*3+1,'Monthly CF'!$C$3:$DR$3,0))} -> #N/A
B51: Loan Funding | C51: =SUMIF('Monthly CF'!$C$4:$DR$4,C$3,'Monthly CF'!$C$61:$DR$61) -> 0 | D51: =SUMIF('Monthly CF'!$C$4:$DR$4,D$3,'Monthly CF'!$C$61:$DR$61) -> 0 | E51: =SUMIF('Monthly CF'!$C$4:$DR$4,E$3,'Monthly CF'!$C$61:$DR$61) -> 0 | F51: =SUMIF('Monthly CF'!$C$4:$DR$4,F$3,'Monthly CF'!$C$61:$DR$61) -> 0 | G51: =SUMIF('Monthly CF'!$C$4:$DR$4,G$3,'Monthly CF'!$C$61:$DR$61) -> 0 | H51: =SUMIF('Monthly CF'!$C$4:$DR$4,H$3,'Monthly CF'!$C$61:$DR$61) -> 0 | I51: =SUMIF('Monthly CF'!$C$4:$DR$4,I$3,'Monthly CF'!$C$61:$DR$61) -> 0 | J51: =SUMIF('Monthly CF'!$C$4:$DR$4,J$3,'Monthly CF'!$C$61:$DR$61) -> 0 | ... AQ51: =SUMIF('Monthly CF'!$C$4:$DR$4,AQ$3,'Monthly CF'!$C$61:$DR$61) -> 0
B52: Interest Payment | C52: =SUMIF('Monthly CF'!$C$4:$DR$4,C$3,'Monthly CF'!$C$62:$DR$62) -> 0 | D52: =SUMIF('Monthly CF'!$C$4:$DR$4,D$3,'Monthly CF'!$C$62:$DR$62) -> 0 | E52: =SUMIF('Monthly CF'!$C$4:$DR$4,E$3,'Monthly CF'!$C$62:$DR$62) -> 0 | F52: =SUMIF('Monthly CF'!$C$4:$DR$4,F$3,'Monthly CF'!$C$62:$DR$62) -> 0 | G52: =SUMIF('Monthly CF'!$C$4:$DR$4,G$3,'Monthly CF'!$C$62:$DR$62) -> 0 | H52: =SUMIF('Monthly CF'!$C$4:$DR$4,H$3,'Monthly CF'!$C$62:$DR$62) -> 0 | I52: =SUMIF('Monthly CF'!$C$4:$DR$4,I$3,'Monthly CF'!$C$62:$DR$62) -> 0 | J52: =SUMIF('Monthly CF'!$C$4:$DR$4,J$3,'Monthly CF'!$C$62:$DR$62) -> 0 | ... AQ52: =SUMIF('Monthly CF'!$C$4:$DR$4,AQ$3,'Monthly CF'!$C$62:$DR$62) -> 0
